Workbook

Sheet Monthly Statistics
B3: Type of Incident | E3: January | F3: February | G3: March | H3: April | I3: May | J3: June | K3: July | L3: August | M3: September | N3: October | O3: November | P3: December | Q3: Total | R3: Total by Classification
B4: LTA-F - Struck by Falling Rock | Q4: =SUM(E4:P4) -> 0 | R4: =SUM(Q4) -> 0
B5: LTA-NF - Struck by Falling Rock | Q5: =SUM(E5:P5) -> 0 | R5: =SUM(Q5:Q8) -> 0
B6: LTA-NF - Caught in Between | Q6: =SUM(E6:P6) -> 0
B7: LTA-NF - Struck by Object | Q7: =SUM(E7:P7) -> 0
B8: LTA-NF - Caught On | Q8: =SUM(E8:P8) -> 0
B9: FAC - Struck by Falling Rock | Q9: =SUM(E9:P9) -> 0 | R9: =SUM(Q9:Q18) -> 0
B10: FAC - Struck by Object | Q10: =SUM(E10:P10) -> 0
B11: FAC - Struck Against | Q11: =SUM(E11:P11) -> 0
B12: FAC - Caught in Between | Q12: =SUM(E12:P12) -> 0
B13: FAC - Punctured | Q13: =SUM(E13:P13) -> 0
B14: FAC - Contact with Smoke | Q14: =SUM(E14:P14) -> 0
B15: FAC - Contact with Electricity | Q15: =SUM(E15:P15) -> 0
B16: FAC - Contact with Chemical | Q16: =SUM(E16:P16) -> 0
B17: FAC - Contact with Object | Q17: =SUM(E17:P17) -> 0
B18: FAC - Fall on Same Level | Q18: =SUM(E18:P18) -> 0
B19: NM - Struck by Falling Rock | Q19: =SUM(E19:P19) -> 0 | R19: =SUM(Q19:Q20) -> 0
B20: NM - Fall on Lower Level | Q20: =SUM(E20:P20) -> 0
B21: Occupational Illness / Pain | Q21: =SUM(E21:P21) -> 0 | R21: =SUM(Q21) -> 0
B22: Property Damage - Fire | Q22: =SUM(E22:P22) -> 0 | R22: =SUM(Q22:Q25) -> 0
B23: Property Damage - NM | Q23: =SUM(E23:P23) -> 0
B24: Property Damage - Struck by Object | Q24: =SUM(E24:P24) -> 0
B25: Property Damage | Q25: =SUM(E25:P25) -> 0
B26: TOTAL | E26: =SUM(E4:E25) -> 0 | F26: =SUM(F4:F25) -> 0 | G26: =SUM(G4:G25) -> 0 | H26: =SUM(H4:H25) -> 0 | I26: =SUM(I4:I25) -> 0 | J26: =SUM(J4:J25) -> 0 | K26: =SUM(K4:K25) -> 0 | L26: =SUM(L4:L25) -> 0 | ... R26: =SUM(R4:R25) -> 0
B30: Occupation / Designation / Property | E30: January | F30: February | G30: March | H30: April | I30: May | J30: June | K30: July | L30: August | M30: September | N30: October | O30: November | P30: December | Q30: Total | R30: Total by Classification
B31: Assistant Miner | Q31: =SUM(E31:P31) -> 0 | R31: =SUM(Q31:Q52) -> 0
B32: Lead Miner | Q32: =SUM(E32:P32) -> 0
B33: Drill Trainee | Q33: =SUM(E33:P33) -> 0
B34: Drill Helper / Assistant Driller | Q34: =SUM(E34:P34) -> 0
B35: Track Man | Q35: =SUM(E35:P35) -> 0
B36: UG Patrol | Q36: =SUM(E36:P36) -> 0
B37: Geologist | Q37: =SUM(E37:P37) -> 0
B38: Geologic Aide | Q38: =SUM(E38:P38) -> 0
B39: Rock Mechanics Aide | Q39: =SUM(E39:P39) -> 0
B40: Geotech & Magsus Aide | Q40: =SUM(E40:P40) -> 0
B41: UG Sampler | Q41: =SUM(E41:P41) -> 0
B42: Mine Planning Engr. | Q42: =SUM(E42:P42) -> 0
B43: Section Head | Q43: =SUM(E43:P43) -> 0
... B52: Control Room Tender | Q52: =SUM(E52:P52) -> 0
B53: Lime Tender | Q53: =SUM(E53:P53) -> 0 | R53: =SUM(Q53:Q68) -> 0
B54: Electrical Engr. | Q54: =SUM(E54:P54) -> 0
B55: Jr. Electrician | Q55: =SUM(E55:P55) -> 0
B56: Grinding Operator | Q56: =SUM(E56:P56) -> 0
B57: Reagent Man | Q57: =SUM(E57:P57) -> 0
B58: Metallurgical Aide | Q58: =SUM(E58:P58) -> 0
B59: Mill Operations Aide | Q59: =SUM(E59:P59) -> 0
B60: Tails Treatment Aide | Q60: =SUM(E60:P60) -> 0
B61: Mill Mechanical Fitter | Q61: =SUM(E61:P61) -> 0
B62: Sr. Fabricator | Q62: =SUM(E62:P62) -> 0
B63: Sanitary Aide | Q63: =SUM(E63:P63) -> 0
B64: Safey Inspector | Q64: =SUM(E64:P64) -> 0
B65: Laboratory Analyst | Q65: =SUM(E65:P65) -> 0
... B68: Jr. Maintenance Man | Q68: =SUM(E68:P68) -> 0
B69: Sandfill line #2 | Q69: =SUM(E69:P69) -> 0 | R69: =SUM(Q69:Q79) -> 0
B70: Housing (Main Door) | Q70: =SUM(E70:P70) -> 0
B71: Nayak Electrical Post | Q71: =SUM(E71:P71) -> 0
B72: Electrical Lines | Q72: =SUM(E72:P72) -> 0
B73: Kalalaw Truck | Q73: =SUM(E73:P73) -> 0
B74: Blower Switch | Q74: =SUM(E74:P74) -> 0
B75: LHD #144 | Q75: =SUM(E75:P75) -> 0
B76: Crane #2 | Q76: =SUM(E76:P76) -> 0
B77: Elf Truck (Windshield) | Q77: =SUM(E77:P77) -> 0
B78: Perimeter Fence | Q78: =SUM(E78:P78) -> 0
B79: Welding Machine | Q79: =SUM(E79:P79) -> 0
B80: TOTAL | E80: =SUM(E31:E79) -> 0 | F80: =SUM(F31:F79) -> 0 | G80: =SUM(G31:G79) -> 0 | H80: =SUM(H31:H79) -> 0 | I80: =SUM(I31:I79) -> 0 | J80: =SUM(J31:J79) -> 0 | K80: =SUM(K31:K79) -> 0 | L80: =SUM(L31:L79) -> 0 | ... R80: =SUM(R31:R79) -> 0
B82: Shift | E82: January | F82: February | G82: March | H82: April | I82: May | J82: June | K82: July | L82: August | M82: September | N82: October | O82: November | P82: December | Q82: Total
B83: First | C83: LTA-NF | Q83: =SUM(E83:P83) -> 0 | R83: =SUM(Q83:Q87) -> 0
C84: FAC | Q84: =SUM(E84:P84) -> 0
C85: NM | Q85: =SUM(E85:P85) -> 0
C86: Property Damage | Q86: =SUM(E86:P86) -> 0
C87: Occupational Illness | Q87: =SUM(E87:P87) -> 0
B88: Second | C88: LTA-NF | Q88: =SUM(E88:P88) -> 0 | R88: =SUM(Q88:Q92) -> 0
C89: FAC | Q89: =SUM(E89:P89) -> 0
C90: Occupational Illness | Q90: =SUM(E90:P90) -> 0
C91: Property Damage | Q91: =SUM(E91:P91) -> 0
C92: NM | Q92: =SUM(E92:P92) -> 0
B93: Third | C93: LTA-F | Q93: =SUM(E93:P93) -> 0 | R93: =SUM(Q93:Q98) -> 0
C94: LTA-NF | Q94: =SUM(E94:P94) -> 0
C95: FAC | Q95: =SUM(E95:P95) -> 0
C96: Occupational Illness | Q96: =SUM(E96:P96) -> 0
C97: Property Damage | Q97: =SUM(E97:P97) -> 0
C98: NM | Q98: =SUM(E98:P98) -> 0
B99: TOTAL | E99: =SUM(E83:E98) -> 0 | F99: =SUM(F83:F98) -> 0 | G99: =SUM(G83:G98) -> 0 | H99: =SUM(H83:H98) -> 0 | I99: =SUM(I83:I98) -> 0 | J99: =SUM(J83:J98) -> 0 | K99: =SUM(K83:K98) -> 0 | L99: =SUM(L83:L98) -> 0 | ... Q99: =SUM(Q83:Q98) -> 0
B101: Workplace / Area | E101: January | F101: February | G101: March | H101: April | I101: May | J101: June | K101: July | L101: August | M101: September | N101: October | O101: November | P101: December | Q101: Total
B102: Stope | Q102: =SUM(E102:P102) -> 0
B103: Mainline / Access | Q103: =SUM(E103:P103) -> 0
B104: Development | Q104: =SUM(E104:P104) -> 0
B105: Raise | Q105: =SUM(E105:P105) -> 0
B106: UG Station/s | Q106: =SUM(E106:P106) -> 0
B107: Cuddy | Q107: =SUM(E107:P107) -> 0
B108: Chute | Q108: =SUM(E108:P108) -> 0
B109: Above Casubigan | Q109: =SUM(E109:P109) -> 0
B110: Housing | Q110: =SUM(E110:P110) -> 0
B111: Gate 4 | Q111: =SUM(E111:P111) -> 0
B112: Crushing Plant | Q112: =SUM(E112:P112) -> 0
B113: Grinding Plant | Q113: =SUM(E113:P113) -> 0
... B135: Conveyor | Q135: =SUM(E135:P135) -> 0
B136: TOTAL | E136: =SUM(E102:E135) -> 0 | F136: =SUM(F102:F135) -> 0 | G136: =SUM(G102:G135) -> 0 | H136: =SUM(H102:H135) -> 0 | I136: =SUM(I102:I135) -> 0 | J136: =SUM(J102:J135) -> 0 | K136: =SUM(K102:K135) -> 0 | L136: =SUM(L102:L135) -> 0 | ... Q136: =SUM(Q102:Q135) -> 0
B138: Group - Department | E138: January | F138: February | G138: March | H138: April | I138: May | J138: June | K138: July | L138: August | M138: September | N138: October | O138: November | P138: December | Q138: Total | R138: Total by Classification
B139: MOG | C139: Department 1 | Q139: =SUM(E139:P139) -> 0 | R139: =SUM(Q139:Q143) -> 0
...

Sheet Compliation
A1: Type of Incident | C1: January | J1: February | Q1: March | X1: April | AE1: May | AL1: June | AS1: July | AZ1: August | BG1: September | BN1: October | BU1: November | CB1: December | CI1: Total | CJ1: % Distribution
C2: LTA-F | D2: LTA-NF | E2: NLTA | F2: FAC | G2: NM | H2: OI | I2: PD | J2: LTA-F | K2: LTA-NF | L2: NLTA | M2: FAC | N2: NM | O2: OI | P2: PD | Q2: LTA-F | R2: LTA-NF | S2: NLTA | T2: FAC | U2: NM | V2: OI | W2: PD | X2: LTA-F | Y2: LTA-NF | Z2: NLTA | AA2: FAC | AB2: NM | AC2: OI | AD2: PD | AE2: LTA-F | AF2: LTA-NF | AG2: NLTA | AH2: FAC | AI2: NM | AJ2: OI | AK2: PD | AL2: LTA-F | AM2: LTA-NF | AN2: NLTA | AO2: FAC | AP2: NM | AQ2: OI | AR2: PD | AS2: LTA-F | AT2: LTA-NF | AU2: NLTA | AV2: FAC | AW2: NM | AX2: OI | AY2: PD | AZ2: LTA-F | BA2: LTA-NF | BB2: NLTA | BC2: FAC | BD2: NM | BE2: OI | BF2: PD | BG2: LTA-F | BH2: LTA-NF | BI2: NLTA | BJ2: FAC | BK2: NM | BL2: OI | BM2: PD | BN2: LTA-F | BO2: LTA-NF | BP2: NLTA | BQ2: FAC | BR2: NM | BS2: OI | BT2: PD | BU2: LTA-F | BV2: LTA-NF | BW2: NLTA | BX2: FAC | BY2: NM | BZ2: OI | CA2: PD | CB2: LTA-F | CC2: LTA-NF | CD2: NLTA | CE2: FAC | CF2: NM | CG2: OI | CH2: PD
A3: Struck by Falling Rock | F3: 1 | M3: 1 | T3: 1 | AA3: 2 | AF3: 1 | AS3: 1 | AT3: 2 | AW3: 1 | BA3: 1 | BF3: 1 | BH3: 1 | BJ3: 1 | BK3: 1 | BQ3: 2 | BV3: 1 | BX3: 2 | CI3: =SUM(C3:CH3) -> 20 | CJ3: {=_xlfn.IFS(CI3=0,0,CI3>=1,CI3/CI25)} -> 0.2173913
A4: Struck Against | AO4: 1 | AV4: 1 | BJ4: 1 | BQ4: 1 | BX4: 3 | CI4: =SUM(C4:CH4) -> 7 | CJ4: {=_xlfn.IFS(CI4=0,0,CI4>=1,CI4/CI25)} -> 0.076086957
A5: Struck by object | M5: 1 | T5: 1 | AA5: 1 | AM5: 1 | AV5: 2 | BA5: 1 | BC5: 2 | BH5: 1 | BQ5: 2 | BT5: 1 | BX5: 1 | CI5: =SUM(C5:CH5) -> 14 | CJ5: {=_xlfn.IFS(CI5=0,0,CI5>=1,CI5/CI25)} -> 0.15217391
A6: Caught in between | F6: 4 | K6: 1 | T6: 1 | AO6: 2 | AV6: 3 | BC6: 2 | BX6: 1 | CI6: =SUM(C6:CH6) -> 14 | CJ6: {=_xlfn.IFS(CI6=0,0,CI6>=1,CI6/CI25)} -> 0.15217391
A7: Caught on | CI7: =SUM(C7:CH7) -> 0 | CJ7: {=_xlfn.IFS(CI7=0,0,CI7>=1,CI7/CI25)} -> 0
A8: Fall on same level | AH8: 1 | BC8: 1 | BQ8: 1 | BX8: 1 | CI8: =SUM(C8:CH8) -> 4 | CJ8: {=_xlfn.IFS(CI8=0,0,CI8>=1,CI8/CI25)} -> 0.043478261
A9: Fall on Lower Level | U9: 1 | CI9: =SUM(C9:CH9) -> 1 | CJ9: {=_xlfn.IFS(CI9=0,0,CI9>=1,CI9/CI25)} -> 0.010869565
A10: Fall of material or structure | CI10: =SUM(C10:CH10) -> 0 | CJ10: {=_xlfn.IFS(CI10=0,0,CI10>=1,CI10/CI25)} -> 0
A11: Punctured | M11: 1 | AH11: 1 | AV11: 1 | CI11: =SUM(C11:CH11) -> 3 | CJ11: {=_xlfn.IFS(CI11=0,0,CI11>=1,CI11/CI25)} -> 0.032608696
A12: Over-exertion in lifting objects | CI12: =SUM(C12:CH12) -> 0 | CJ12: {=_xlfn.IFS(CI12=0,0,CI12>=1,CI12/CI25)} -> 0
A13: Over-exertion in pushing or pulling objects | CI13: =SUM(C13:CH13) -> 0 | CJ13: {=_xlfn.IFS(CI13=0,0,CI13>=1,CI13/CI25)} -> 0
A14: Over-exertion in handling or throwing objects | CI14: =SUM(C14:CH14) -> 0 | CJ14: {=_xlfn.IFS(CI14=0,0,CI14>=1,CI14/CI25)} -> 0
A15: Fire | BF15: 1 | CA15: 1 | CI15: =SUM(C15:CH15) -> 2 | CJ15: {=_xlfn.IFS(CI15=0,0,CI15>=1,CI15/CI25)} -> 0.02173913
A16: Eye contact with foreign object | CI16: =SUM(C16:CH16) -> 0 | CJ16: {=_xlfn.IFS(CI16=0,0,CI16>=1,CI16/CI25)} -> 0
A17: Contact with smoke | AA17: 1 | AO17: 1 | CI17: =SUM(C17:CH17) -> 2 | CJ17: {=_xlfn.IFS(CI17=0,0,CI17>=1,CI17/CI25)} -> 0.02173913
A18: Contact or exposure to extreme temperatures | CI18: =SUM(C18:CH18) -> 0 | CJ18: {=_xlfn.IFS(CI18=0,0,CI18>=1,CI18/CI25)} -> 0
A19: Exposure to radiation | CI19: =SUM(C19:CH19) -> 0 | CJ19: {=_xlfn.IFS(CI19=0,0,CI19>=1,CI19/CI25)} -> 0
A20: Contact with Object | BC20: 1 | CI20: =SUM(C20:CH20) -> 1 | CJ20: {=_xlfn.IFS(CI20=0,0,CI20>=1,CI20/CI25)} -> 0.010869565
A21: Contact with Electricity | AA21: 1 | CI21: =SUM(C21:CH21) -> 1 | CJ21: {=_xlfn.IFS(CI21=0,0,CI21>=1,CI21/CI25)} -> 0.010869565
A22: Contact with Chemical | AO22: 1 | CI22: =SUM(C22:CH22) -> 1 | CJ22: {=_xlfn.IFS(CI22=0,0,CI22>=1,CI22/CI25)} -> 0.010869565
A23: Occupational Illness/Pain | H23: 2 | O23: 1 | V23: 3 | AJ23: 2 | AX23: 2 | BE23: 2 | BL23: 1 | BS23: 1 | CI23: =SUM(C23:CH23) -> 14 | CJ23: {=_xlfn.IFS(CI23=0,0,CI23>=1,CI23/CI25)} -> 0.15217391
A24: Property Damage | I24: 2 | AK24: 2 | AR24: 2 | BK24: 1 | BT24: 1 | CI24: =SUM(C24:CH24) -> 8 | CJ24: {=_xlfn.IFS(CI24=0,0,CI24>=1,CI24/CI25)} -> 0.086956522
A25: TOTAL | C25: =SUM(C3:C24) -> 0 | D25: =SUM(D3:D24) -> 0 | E25: =SUM(E3:E24) -> 0 | F25: =SUM(F3:F24) -> 5 | G25: =SUM(G3:G24) -> 0 | H25: =SUM(H3:H24) -> 2 | I25: =SUM(I3:I24) -> 2 | J25: =SUM(J3:J24) -> 0 | ... CJ25: =SUM(CJ3:CJ24) -> 1
A27: Occupation/ Equipment | C27: January | J27: February | Q27: March | X27: April | AE27: May | AL27: June | AS27: July | AZ27: August | BG27: September | BN27: October | BU27: November | CB27: December | CI27: Total | CJ27: Total by Nature of Accident
C28: LTA-F | D28: LTA-NF | E28: NLTA | F28: FAC | G28: NM | H28: OI | I28: PD | J28: LTA-F | K28: LTA-NF | L28: NLTA | M28: FAC | N28: NM | O28: OI | P28: PD | Q28: LTA-F | R28: LTA-NF | S28: NLTA | T28: FAC | U28: NM | V28: OI | W28: PD | X28: LTA-F | Y28: LTA-NF | Z28: NLTA | AA28: FAC | AB28: NM | AC28: OI | AD28: PD | AE28: LTA-F | AF28: LTA-NF | AG28: NLTA | AH28: FAC | AI28: NM | AJ28: OI | AK28: PD | AL28: LTA-F | AM28: LTA-NF | AN28: NLTA | AO28: FAC | AP28: NM | AQ28: OI | AR28: PD | AS28: LTA-F | AT28: LTA-NF | AU28: NLTA | AV28: FAC | AW28: NM | AX28: OI | AY28: PD | AZ28: LTA-F | BA28: LTA-NF | BB28: NLTA | BC28: FAC | BD28: NM | BE28: OI | BF28: PD | BG28: LTA-F | BH28: LTA-NF | BI28: NLTA | BJ28: FAC | BK28: NM | BL28: OI | BM28: PD | BN28: LTA-F | BO28: LTA-NF | BP28: NLTA | BQ28: FAC | BR28: NM | BS28: OI | BT28: PD | BU28: LTA-F | BV28: LTA-NF | BW28: NLTA | BX28: FAC | BY28: NM | BZ28: OI | CA28: PD | CB28: LTA-F | CC28: LTA-NF | CD28: NLTA | CE28: FAC | CF28: NM | CG28: OI | CH28: PD
A29: Assistant Miner
A30: Lead Miner
A31: LHD/ LPT Optr
A32: Locomotive Optr./ Helper
A33: Shiftboss
A34: Driller/ Drill Helper
A35: Loco. Optr./ Helper
A36: Track Man
A37: Maintenance Man (GMS)
A38: UG Warehouse Man (IMD)
A39: Maintenance Man (MME)
A40: Mine Patrol
... A49: Main Entry Door of Housing
A50: TOTAL | C50: =SUM(C29:C49) -> 0 | D50: =SUM(D29:D49) -> 0 | E50: =SUM(E29:E49) -> 0 | F50: =SUM(F29:F49) -> 0 | G50: =SUM(G29:G49) -> 0 | H50: =SUM(H29:H49) -> 0 | I50: =SUM(I29:I49) -> 0 | J50: =SUM(J29:J49) -> 0 | ... CJ50: =SUM(CJ29:CJ49) -> 0
R61: who | S61: sndv
R62: what | S62: mdsvlksnd
R63: where | S63: mlsdnvl
R64: when | S64: lsvdnsdv
S67: enter

Sheet SCAT Reference
B1: System Cause Analysis Technique (SCAT)
A3: # | B3: Types of Contact | C3: I/D Causes | E3: # | F3: Immediate / Direct Causes | G3: B/U Causes | I3: # | J3: - | K3: Basic / Underlying Causes | L3: -2 | M3: CAN | O3: # | P3: - | Q3: Control Action Needs | R3: Program Activity | S3: Program Standards are Established | T3: Full Compliance to Standards Achieved
A4: 1 | B4: Struck Against (Running or Bumping Into) | C4: 1,2,4,5,12,14-19,26 | F4: Substandard Acts | K4: Personal Factors | R4: Accomplishment Levels
A5: 2 | B5: Struck By (Hit by Moving Object) | C5: 1,2,4-6,9,10,12-16,20,26 | E5: 1 | F5: Operating Equipment without Authority | G5: 2,4,5,7,8,12,13,15 | I5: 1 | J5: Inadequate Physical / Physiological Capabality | M5: 6,9,12,15,18
A6: 3 | B6: Fall From Elevation to Lower Level | C6: 1,3,5-7,11-17,22 | E6: 2 | F6: Failure to Warn | G6: 1-9,12,13,15 | J6: 1.1 | K6: Inappropriate height, weight, size, strength, reach, etc. | O6: 1 | P6: Leadership and Administration
A7: 4 | B7: Fall on Same Level (Slip & Fall, Trip Over) | C7: 4,9,13-16,19,22,26 | E7: 3 | F7: Failure to Secure | G7: 2-9,12,13,15 | J7: 1.2 | K7: Restricted range of body movement | P7: 1.2 | Q7: Loss Control Coordinator
A8: 5 | B8: Caught On (Snegged / Hung) | C8: 5,6,11,13,14-16,18 | E8: 4 | F8: Operating at Improper Speed | G8: 2-9,11-13,15 | J8: 1.3 | K8: Limited ability to sustain body positions | P8: 1.3 | Q8: Senior and Middle Management Participation
A9: 6 | B9: Caught Between or Under (Crushed or Amputated) | C9: 5,6,11-16,18 | E9: 5 | F9: Making Safety Devices Inoperative | G9: 2-9,12,13,15 | J9: 1.4 | K9: Substance sensitivities / allergies | P9: 1.4 | Q9: Establish Loss Control Performance Strandards
A10: 7 | B10: Contact With (Electricity, Heat, Cold, Radiation, Caustics, Toxics, Biological, Noise) | C10: 1,2,5,6,9,11-16,22,28 | E10: 6 | F10: Using Defective Equipment | G10: 2-15 | J10: 1.5 | K10: Sensitivities to sensory extremes (temperature, sound, etc.) | P10: 1.5 | Q10: Participation in Special Loss Control Activities
A11: 8 | B11: Overstress (Overexertion, Overload, Overexposure, Ergonomic) | C11: 5-7,11-18,20,21,23-25, 27,28 | E11: 7 | F11: Failing to Use PPE Properly | G11: 2-5,7,8,10,12,13,15 | J11: 1.6 | K11: Vision deficiency | P11: 1.6 | Q11: Agenda Item in Management Meetings
E12: 8 | F12: Improper Loading | G12: 1-9,11-13,15 | J12: 1.7 | K12: Hearing deficiency | P12: 1.7 | Q12: Loss Control Reference Manual
E13: 9 | F13: Improper Placement | G13: 1-9,12,13,15 | J13: 1.8 | K13: Other sensory deficiency (touch, taste, smell, balance) | P13: 1.8 | Q13: Internal Audits Conducted
E14: 10 | F14: Improper Lifting | G14: 1-9,12,13,15 | J14: 1.9 | K14: Respiratory Incapability | P14: 1.9 | Q14: Individual Responsibility for Loss Control Assigned
E15: 11 | F15: Improper Position for Task | G15: 1-9,12,13,15 | J15: 1.10 | K15: Other permanent physical capabilities | P15: 1.10 | Q15: Annual Loss Control Objectives Established
E16: 12 | F16: Servicing Equipment in Operation | G16: 2-9,12,13,15 | J16: 1.11 | K16: Temporary disabilities | P16: 1.11 | Q16: Joint Safety and Health Committees and / or Safety and Health Representatives
E17: 13 | F17: Horseplay | G17: 2-5,7,8,13,15 | I17: 2 | J17: Inadequate Mental / Psychological Capability | M17: 6,9,10,15,18 | P17: 1.12 | Q17: Policy on Refusal to work due to hazards
E18: 14 | F18: Under Influence of Alcohol and / or Other Drugs | G18: 2-5,7,8,13,15 | J18: 2.1 | K18: Fear and phobias | P18: 1.13 | Q18: Reference Library
E19: 15 | F19: Using Equipment Improperly | G19: 1-10,12,13,15 | J19: 2.2 | K19: Emotional disturbance | P19: 1.14 | Q19: Document Control System
F20: Substandard Conditions | J20: 2.3 | K20: Mental Illness | P20: 1.15 | Q20: Applicable regulations, Codes and Standards Identified
E21: 16 | F21: Inadequate Guards / Barriers | G21: 5,7-13,15 | J21: 2.4 | K21: Intelligence level | P21: 1.16 | Q21: Communicating with External parties
E22: 17 | F22: Inadequate / Improper Protective Equipment | G22: 5,7-10,12,13 | J22: 2.5 | K22: Inability to comprehend | O22: 2 | P22: Leadership Training
E23: 18 | F23: Defective Tools, Equipment or Materials | G23: 8-13 | J23: 2.6 | K23: Poor judgement | P23: 2.1 | Q23: Training Needs Analysis
E24: 19 | F24: Congestion or Restricted Action | G24: 8,9,13 | J24: 2.7 | K24: Poor coordination | P24: 2.2 | Q24: Loss Control Orientation / Induction for New Leaders / Managers
E25: 20 | F25: Inadequate Warning System | G25: 8-15 | J25: 2.8 | K25: Slow reaction time | P25: 2.3 | Q25: Initial Training of Senior Management
E26: 21 | F26: Fire and Explosion Hazards | G26: 5-13, 15 | J26: 2.9 | K26: Low mechanical aptitude | P26: 2.4 | Q26: Update Training of Senior Management
E27: 22 | F27: Poor Housekeeping / Disporder | G27: 5-13, 15 | J27: 2.10 | K27: Low learning aptitude | P27: 2.5 | Q27: Initial Loss Control Training for Leaders / Managers
E28: 23 | F28: Noise Exposure | G28: 5-14 | J28: 2.11 | K28: Memory failure | P28: 2.6 | Q28: Update Loss Control Training for Leaders / Managers
E29: 24 | F29: Radiation Exposure | G29: 5-14 | I29: 3 | J29: Physical / Physiological Stress | M29: 4,6,9,11-13,15,18,20 | P29: 2.7 | Q29: Formal Training of Loss Control Coordinator
E30: 25 | F30: Temperature Extremes | G30: 1-3,8,9,11,12 | J30: 3.1 | K30: Injury / Illness | P30: 2.8 | Q30: Records of Leadership Training
E31: 26 | F31: Inadequate / Excess Illumination | G31: 8-12 | J31: 3.2 | K31: Fatigue due to task load / duration | O31: 3 | P31: Planned Inspection and Maintenance
E32: 27 | F32: Inadequate Ventilation | G32: 8-13 | J32: 3.3 | K32: Fatigue dur to lack of rest | P32: 3.1 | Q32: Planned General Inspections
E33: 28 | F33: Hazardous Environment Conditions | G33: 8-11 | J33: 3.4 | K33: Fatigue due to sensory overload | P33: 3.2 | Q33: Forllow-up System
J34: 3.5 | K34: Exposure to health hazards | P34: 3.3 | Q34: Inspection Report Analysis
J35: 3.6 | K35: Exposure to temperature extremes | P35: 3.4 | Q35: Critical Parts / Items Inpections
J36: 3.7 | K36: Oxygen deficiency | P36: 3.5 | Q36: Preventive Maintenance System
J37: 3.8 | K37: Atmospheric pressure constrained movement | P37: 3.6 | Q37: Special Systemas Inspections
J38: 3.9 | K38: Constrained movement | P38: 3.7 | Q38: Pre-use Equioment Inspections
J39: 3.10 | K39: Blood sugar insufficiency | P39: 3.8 | Q39: System for Employees to report Substandard Conditions in Writing
J40: 3.11 | K40: Drugs | P40: 3.9 | Q40: Compliance with Regulatory Requirements for Inspections
I41: 4 | J41: Mental / Psychological Stress | M41: 1,4,-6,9-12,15,16,18,20 | O41: 4 | P41: Critical Task Analysis Procedure
J42: 4.1 | K42: Emotional Overload | P42: 4.1 | Q42: Task Analysis Systems Established
J43: 4.2 | K43: Fatigue due to mental task load / speed | P43: 4.2 | Q43: Critical Tasks Identified
J44: 4.3 | K44: Extreme judgement / decision demands | P44: 4.3 | Q44: Controls Developed for Potential Losses
J45: 4.4 | K45: Routine, monotony, demand for uneventful vigilance | P45: 4.4 | Q45: Controls Incorporated into Procedure and Practices
J46: 4.5 | K46: Extreme concentration / perception demands | P46: 4.5 | Q46: Critical Task Procedures / Practices Updated
J47: 4.6 | K47: "Meaningless" / "Degrading Activities" | O47: 5 | P47: Accident / Incident Investigation
J48: 4.7 | K48: Confusing directions / demands | P48: 5.1 | Q48: Accident / Incident Investigation System
J49: 4.8 | K49: Conflicting directions / demands | P49: 5.2 | Q49: Operating Management Participation
J50: 4.9 | K50: Preoccupation with problems | P50: 5.3 | Q50: Review of Major and High-Potential Accident / Incidents
J51: 4.10 | K51: Frustration | P51: 5.4 | Q51: Remedia; Action and Follow-up
J52: 4.11 | K52: Mental Illness | P52: 5.5 | Q52: Incidents (Near Miss) Reporting and Investigation
I53: 5 | J53: Lack of Knowledge | M53: 2,4-13,15,16,18,20 | P53: 5.6 | Q53: Accident / Incident Report Maintenance
J54: 5.1 | K54: Lack of experience | O54: 6 | P54: Task Observation
J55: 5.2 | K55: Inadequate orientation | P55: 6.1 | Q55: Administration
J56: 5.3 | K56: Inadequate initial training | P56: 6.2 | Q56: System for Partial / Spot Task Observation
J57: 5.4 | K57: Inadequate update training | P57: 6.3 | Q57: System for Complete Task Observation
J58: 5.5 | K58: Misunderstood directions | P58: 6.4 | Q58: Critical Task Observation Performed
I59: 6 | J59: Lack of Skill | M59: 2,4-10,13,15,16 | P59: 6.5 | Q59: Follow-up System
J60: 6.1 | K60: Inadequate initial instruction | P60: 6.6 | Q60: Task Observation Report Analysis
J61: 6.2 | K61: Inadequate practice | O61: 7 | P61: Emergency Preparedness
J62: 6.3 | K62: Infrequent performance | P62: 7.1 | Q62: Administration
J63: 6.4 | K63: Lack of coaching | P63: 7.2 | Q63: Identification of Potential Emergencies
J64: 6.5 | K64: Inadequate review instruction | P64: 7.3 | Q64: Emergency Plan
I65: 7 | J65: Improper Motivation | M65: 1,2,4-6,8,10,11,13,14,17,18 | P65: 7.4 | Q65: Off-site Emergencies
J66: 7.1 | K66: Improper performance is rewarded (tolerated) | P66: 7.5 | Q66: Sources of Energy Controls
J67: 7.2 | K67: Proper performance is punished | P67: 7.6 | Q67: Protective and Rescue Systems
J68: 7.3 | K68: Lack of incentives | P68: 7.7 | Q68: Emergency Teams
J69: 7.4 | K69: Excessive frustration | P69: 7.8 | Q69: Lessons Learned System
J70: 7.5 | K70: Inappropriate aggression | P70: 7.9 | Q70: First Aid
J71: 7.6 | K71: Improper attempt to save time and effort | P71: 7.10 | Q71: Organized Outside Help and Mutual Aid
J72: 7.7 | K72: Improper attempt to avoid discomfort | P72: 7.11 | Q72: Post Event Planning
J73: 7.8 | K73: Improper attempt to gain attention | P73: 7.12 | Q73: Emergency Communication
J74: 7.9 | K74: Inadequate discipline | P74: 7.13 | Q74: Communication with the Community
J75: 7.10 | K75: Inappropriate peer pressure | O75: 8 | P75: Rules and Work Permits
J76: 7.11 | K76: Improper Supervisory example | P76: 8.1 | Q76: General Loss Control Rules
J77: 7.12 | K77: Inadequate performance feedback | P77: 8.2 | Q77: Specialized Work Rules
J78: 7.13 | K78: Inadequate reinforcement of proper behavior | P78: 8.3 | Q78: Specialized Work Permit Systems
J79: 7.14 | K79: Improper production incentives | P79: 8.4 | Q79: Regulatory Permit-To-Operate Systems
K80: Job Factors | P80: 8.5 | Q80: Rule Education and Review
I81: 8 | J81: Inadequate Leadership &/or Supervision | M81: 1-6,8-18 | P81: 8.6 | Q81: Rule Compliance and Recognition
J82: 8.1 | K82: Unclear / Conflicting reporting relationships | P82: 8.7 | Q82: Use of Educational Signs and Color Codes
J83: 8.2 | K83: Unclear / Conflicting assignment of activity | O83: 9 | P83: Accident / Incident Analysis
J84: 8.3 | K84: Improper / Insufficient delegation | P84: 9.1 | Q84: Consequence Measurements
J85: 8.4 | K85: Giving inadequate policy, procedure, practices of guidelines | P85: 9.2 | Q85: Cause and Control Analysis
J86: 8.5 | K86: Giving objectives, goals, or standards that conflict | P86: 9.3 | Q86: Property Damage / Process Loss Identification and Analysis
J87: 8.6 | K87: Inadequate work planning / programming | P87: 9.4 | Q87: Incident (Near Miss) Analysis
J88: 8.7 | K88: Inadequate instructions, orientation and/or training | P88: 9.5 | Q88: Problem-Solving Project Teams
J89: 8.8 | K89: Providing inadequate reference documents, directives & guidance publications | O89: 10 | P89: Knowledege and Skill Training
J90: 8.9 | K90: Inadequate identification & evaluation of loss exposure | P90: 10.1 | Q90: Administration
J91: 8.10 | K91: Lack of supervisory / management job knowledge | P91: 10.2 | Q91: Training Needs Analysis
J92: 8.11 | K92: Inadequate matching of individuak qualifications & job / task requirements | P92: 10.3 | Q92: Instructor Qualifications
J93: 8.12 | K93: Inadequate performance measurement and evaluation | P93: 10.4 | Q93: Training Systems
J94: 8.13 | K94: Inadequate / Incorrect performance feedback | P94: 10.5 | Q94: Training System Eveluation and Follow-up
I95: 9 | J95: Inadequate Engineering | M95: 1,3,4,9,12,14 | O95: 11 | P95: Personal Protective Equipment
J96: 9.1 | K96: Inadequate assessment of loss exposures | P96: 11.1 | Q96: Identification of PPE Needs
J97: 9.2 | K97: Inadequate consideration of human factors / ergonomics | P97: 11.2 | Q97: PPE Available
J98: 9.3 | K98: Inadequate standards, specifications and/or design criteria | P98: 11.3 | Q98: Enforcement of Standards
J99: 9.4 | K99: Inadequate monitoring of construction | O99: 12 | P99: Health and Hygiene Control
J100: 9.5 | K100: Inadequate assessment of operational readiness | P100: 12.1 | Q100: Administration
J101: 9.6 | K101: Inadequate or improper controls | P101: 12.2 | Q101: Health Hazard Identification and Evaluation
...

Sheet DataReferences
A1: MMMM-YYYY | B1: Section | C1: Occupation / Designation / Property | D1: Workplace / Area | E1: Level | F1: Shift | G1: Department Heads | H1: Section Heads | I1: Immediate Supervisor | J1: Nature of Injury | K1: Type of Incident | L1: Group | M1: Department | N1: Section | O1: Group / Dept. / Sect. | P1: Recorder | Q1: GENERAL MANAGEMENT: | R1: ADMINISTRATIVE SVCS. GROUP: | S1: FINANCE SERVICES GROUP: | T1: TECHNICAL SERVICES GROUP: | U1: MINE GROUP: | V1: MINE ENG'G,GEOLOGY AND VENT: | W1: EXPLORATION GROUP: | X1: MILL GROUP:
A2: JANUARY, 2026 | B2: Surface | C2: N/A | D2: Aerodome Area | E2: S (N/A) | F2: First | G2: N/A | H2: N/A | I2: N/A | J2: LTA-F | K2: Struck by Falling Rock | L2: N/A - Community | M2: N/A - Community | N2: N/A - Community | O2: N/A - Emergency Incident | P2: MAAT | Q2: General Management Office | R2: Legal Services | S2: Accounting | T2: Technical Management Office | U2: Mining | V2: Engineering | W2: Exploration | X2: Mill Management
A3: FEBRUARY, 2026 | B3: Underground | C3: Assistant Miner | D3: Assay Laboratory | E3: 670L | F3: Second | G3: Abraham L. Davis | H3: Alfon B. Yodong | I3: Allan F. Takayeng | J3: LTA-NF | K3: Struck by Flying Object | L3: Contracts | M3: Dept. 1 | N3: Contracts | O3: MOG - 1: Section 1 | P3: KTAA | Q3: Safety Department | R3: Administrative Management | S3: Purchasing | T3: Enercon | U3: Mine Management | V3: Geology | X3: Mill Operations
A4: MARCH, 2026 | C4: Cadet Mechanical Engineer | D4: Breast Hole | E4: 800L | F4: Third | G4: DDCP - Allan R. Domalsin | H4: Allab B. Lal-wet | I4: Andy M. Delumen | J4: NLTA | K4: Struck by Object | L4: ASG | M4: Dept. 2 | N4: Section 1 | O4: MOG - 1: Section 2 | P4: MBM | Q4: MEPEO | R4: IOSD-Communication & AS | S4: Inventory Management Dept. | T4: Project Engineering, Surf. Survey & SWM | U4: General Mine Services( A&W,TSO,NSO, UG Sandfilling, UG Crushing, Haulage,UG Cons. & Special Projects) | V4: Mine Ventilation | X4: Metallurgical Laboratory
A5: APRIL, 2026 | C5: Carpenter | D5: Boiler Room Extension | E5: 830L | G5: Dexter B. Arevalo | H5: Art Benzene E. Lanip | I5: Angelito A. Delim | J5: NM | K5: Struck Against | L5: Exploration | M5: MMME | N5: Section 2 | O5: MOG - 1: Section 3 | P5: AOV | Q5: SDD | R5: Medical Dept. | T5: Mechanical Workshops (Machine,Fabrication, Overhauling & TSG-Mine Shops) | U5: Mine Mechanical & Electrical | X5: Tamangan Lime Plant
A6: MAY, 2026 | C6: CIP Operator | D6: Bonanza Quarry, TSF | E6: 840L | G6: Fabrian Roderick S. Likigan | H6: Baker S. Calbid | I6: Antonio D. Siyao | J6: FAC | K6: Caught on | L6: FSG | M6: GMS | N6: Section 3 | O6: MOG - 2: Section 4 | P6: HMBR | Q6: Communication Dept. | R6: HR | T6: Surface Mechanical & Electrical (Trans.Svcs., Power Plant, Surface Elect'l.Svcs., Instrument Calib.) | U6: ADIT Rehab | X6: Upper and Lower Tram Operations
A7: JUNE, 2026 | C7: Crusher Operator | D7: Buaki, Sapid | E7: 850L | G7: Fe Marie W. Mates | H7: Benito A. Islao Jr. | I7: Ambros C. Gabriel | J7: OI | K7: Caught in Between | L7: GMG | M7: Safety | N7: Section 4 | O7: MOG - 2: Section 5 | Q7: MISD | X7: Mill Mechanical & Electrical
A8: JULY, 2026 | C8: DeviGyro HQ Mid Centralizer | D8: Bulalacao, Mankayan, Benguet | E8: 860L | G8: Fernando A. Bustillo Jr. | H8: Bullet P. Tangcalagan | I8: Art Benzene E. Lanip | J8: PD | K8: Fall on Same Level | L8: MEGG | M8: Mine Management | N8: Section 5 | O8: MOG - 2: Section 6 | Q8: Tailings Storage Facility | X8: Mill Eng'g.-PCEA's
A9: AUGUST, 2026 | C9: Drill Helper / Drilling Aide | D9: Carpentry Shop | E9: 870L | G9: Hilbert G. Andong | H9: Christopher T. Baniaga | I9: Arthur M. Padica | J9: EI | K9: Fall on Lower level | L9: MOG | M9: Mine Engineering | N9: Section 6 | O9: MOG - MMME - Mobile | Q9: Waste Water Management
A10: SEPTEMBER, 2026 | C10: Electrician | D10: Casubigan / Marivic Area | E10: 880L | G10: Jayson T. Capia-ao | H10: Darwin S. Coloma | I10: Aquino P. Lawana Jr. | K10: Punctured | L10: MPG | M10: Mine Study | N10: Mine Technical Services | O10: MOG - MMME - Non-Mobile | Q10: Assay
A11: OCTOBER, 2026 | C11: Forest Fire | D11: Casubigan, Sapid | E11: 900L | G11: John Paul C. Licot | H11: DDCP - Allan Raymund Domalsin | I11: Bernard M. Itliong | K11: Over-Exertion in Lifting Objects | L11: TSG | M11: Mine Geology | N11: Mobile | O11: MOG - MMME - Electrical
A12: NOVEMBER, 2026 | C12: Fuse Cut-Off Switch | D12: Chute | E12: 970L | G12: Kay B. Lacambra | H12: Dember F. Dictaan Jr. | I12: Clinton O. Lingyasan | K12: Over-Exertion in Pushing / Pulling Objects | M12: Mine Ventilation | N12: Non-Mobile | O12: MOG - GMS - Nayak Shaft / UG Construction
A13: DECEMBER, 2026 | C13: Garbage Fire | D13: CIP - Barren Pump Area | E13: 980L | G13: Kurt Linis Ljomir Ursua | H13: Dimas S. Gao-ay | I13: Danilo M. Galande | K13: Over-Exertion in Handling or Throwing Objects | M13: TSF 5A | N13: Electrical | O13: MOG - GMS - Tubo Shaft
C14: Geologic Sampler | D14: CIP - ILR | E14: 1000L | G14: Larry E. Arigue | H14: Edie S. Pacsay | I14: DDCP - Allan Kitma | K14: Fire | M14: Mill Operations | N14: Stope Services Crew | O14: MOG - GMS - Drift and Track Maintenance
C15: Geotech Aide | D15: CIP - Refinery | E15: 1040L | G15: Lourdes F. Inao | H15: Ernesto L. Locaben Jr. | I15: DDCP - Clarence Avila | K15: Contact with Object | M15: Mill Mechanical | N15: Nayak Shaft Operation / UG Construction | O15: MOG - GMS - Underground Crusher
C16: Grade Application Analyst | D16: Cone Crusher Conveyor Feed | E16: 1100L | G16: Mary Grace C. Torres | H16: Florence S. Sayson | I16: Dominador B. Dampilag | K16: Contact with Smoke | M16: Mill Electrical | N16: Tubo Shaft Operation / 670L Pumping | O16: MOG - GMS - Adit 1&2
C17: Grinding Operator | D17: Crushing Area | E17: 1150L | G17: Michael P. Lamagan - OIC | H17: Francis E. Mabunga | I17: Dummory Joseff Febrei O. Estepa | K17: Contact / Exposure to Extreme Temperatures | M17: Mill Engineering | N17: Underground Crusher | O17: MOG - GMS - Air and Water
C18: Head Nurse | D18: Cuddy | E18: 1250L | G18: Nelson L. Baguya II | H18: James I. Consolacion | I18: Efren L. Mangamti | K18: Exposure to Extreme Temperatures | M18: Metallurgy | N18: Main Haulage / Drift & Track Maintenance | O18: MOG - Safety - Surface Safety
C19: Heavy Equipment Operator | D19: Development | G19: Richard C. Ducusin | H19: Jeah B. Taguran | I19: Ernie S. Ringor | K19: Exposure to Radiation | M19: Assay | N19: Surface Safety | O19: MOG - Safety - Nayak/UG Safety
C20: Jr. Machinist | D20: Fuel Storage Area | G20: Rolando E. Ventura | H20: Jenipher B. Rosito | I20: Ephraim K. Pitok | K20: Foreign Object in the Eye/s | M20: Mill Management | N20: Nayak/UG Safety | O20: MOG - Mine Management
C21: Jr. Maintenance Man | D21: IMD Substation | G21: SNSAI - Mary Joyce Adaclog - OIC | H21: Jeric T. Dulawan | I21: Eufrosino A. De Leon Jr. | K21: Eye Contact with Foreign Object | M21: Exploration | N21: Control | O21: EXPLO - Exploration
C22: Jr. Mechanic | D22: Gate 1, Panad | G22: Venancio A. Bad-ay | H22: Jerry G. Gatinao Jr. | I22: Frank C. Samdao Jr. | K22: Occupational Illness / Pain | M22: MEPEO | N22: Refinery | O22: MEGG - Mine Engineering
C23: Jr. Mechanic / Driver | D23: Golf Course, Sapid | G23: Zerubabel D. Pateña | H23: Jet Lee V. Chinanglas | I23: Higenio Ginpac - Consultant | K23: Property Damage | M23: ComRel | N23: CIP | O23: MEGG - Mine Study
C24: Jr. Mechanical Engineer | D24: Gravel Pit, Sapid | H24: Jordan P. Masidong | I24: Jefferson V. Ramos | K24: Near Miss | M24: MWSO | N24: Services | O24: MEGG - Mine Geology
C25: Kalalaw Truck | D25: Hoist Room | H25: Julian Manuel S. Casuga | I25: Jerry I. Garwageo | K25: Earthquake | M25: SMED | N25: Crushing & Grinding | O25: MEGG - Mine Ventilation
C26: Laboratory Technician | D26: Hospital | H26: Julius B. Liban | I26: Joel M. Lopez | K26: Environmental Incident - Chemical Spill | M26: PCES | N26: Sand Production | O26: MEGG - Rock Mechanics
C27: Lead Miner | D27: La Guerta Area | H27: Julius K. Finatec | I27: John I. Naweywey | K27: Explosion | M27: IOSD | N27: Water Recovery | O27: MPG - Mill Operations - Refinery
C28: LHD Optr | D28: Lime Plant | H28: June O. Golocan | I28: John Pauline M. Refugia | M28: Legal Office | N28: Fabrication Shop | O28: MPG - Mill Operations - CIP
C29: Leach Tank | D29: LMD Hospital | H29: Keziah C. Chamollog | I29: John Ray T. Salguit | M29: Human Resources | N29: Overhauling Shop | O29: MPG - Mill Operations - Services
C30: Lifting Equipment | D30: LMD Morgue Area | H30: Mariel T. Ayong | I30: Karl Lloyd S. Valentin | M30: Medical Services | N30: 900L Mine Shop | O30: MPG - Mill Operations - Sand Production
C31: Lime Surge Tank | D31: LMD Roadway | H31: Melno S. Palayen | I31: Kathy M. Domogo | M31: DDCP | N31: Machine Shop | O31: MPG - Mill Operations - Water Recovery
C32: Locomotive Optr. / Helper | D32: Loading Bay | H32: Nathaneal D. Jugal | I32: Kristian Lloyd D. Bulay | M32: MD&C Construction | N32: Surface Electrical | O32: MPG - Mill Operations - Crushing & Grinding
C33: LPT Optr | D33: Lower Tram | H33: Neil Marcel F. Paquito | I33: Larry S. Andomang | M33: VSAI | N33: Powerplant, Nayak & Tubo Compressor | O33: MPG - Mill Mechanical
C34: Maintenance Man (GMS) | D34: Machine Shop | H34: Reynaldo G. Cawi | I34: Lambert I. Domogen Jr. | M34: SNSAI | N34: Energy Conservation | O34: MPG - Mill Engineering
C35: Maintenance Man (MMME) | D35: Mainline / Access | H35: Reynaldo P. Kiking | I35: Leo D. Bulawit | M35: RBDanao | N35: Instrument Calibration | O35: MPG - Metallurgy - Laboratory
C36: Maintenance Man (PCES) | D36: Marivic Rd., Sapid | H36: Ruben T. Saliwey | I36: Leonard K. Fawayan | M36: Accounting | N36: Motorpool / Transport | O36: TSG - MWSO - Fabrication Shop
C37: Maintenance Man (TSF) | D37: Mill Office | H37: Samson A. Fotyong | I37: Mark D. Banasan | M37: IMD | N37: Project Engineering | O37: TSG - MWSO - Overhauling Shop
C38: Mill Engineering Service Vehicle | D38: Nayak Mine Office Compound | H38: Randolf O. Anongos | I38: Marry Joy S. Ronulo | N38: Surface Survey | O38: TSG - MWSO - 900L Mine Shop
C39: Mill Mechanical ADH | D39: Old Gate 3 | H39: Wendel D. Balag-ey | I39: Marvin B. Caligner | N39: Solid Waste & Tamangan ESL Management | O39: TSG - MWSO - Machine Shop
C40: Mill Mechanical Fitter | D40: Old Traffic Area / Junction | I40: Mauricio D. Bangngayon | N40: Carpentry Shop | O40: TSG - MWSO - Motorpool
C41: Mill Operations Aide | D41: On the road | I41: Nathaneal D. Jugal | N41: Plumbing and Water Supply | O41: TSG - PCES - Project Engineering
C42: Mine Foreman | D42: Panad Roadway, Poblacion | I42: Nicole C. Dompayag | N42: Jobs in Progress | O42: TSG - PCES - Surface Survey
C43: Mine Services Aide | D43: Poblacion, Mankayan | I43: Paterno B. Basingan | N43: Water Source Management & Maintenance | O43: TSG - PCES - Solid Waste & Tamagan ESL Mgmt.
C44: OJT | D44: Pukitan Area | I44: Pedro B. Lambino | N44: Building Maintenance | O44: TSG - PCES - Carpentry Shop
C45: PMS Foreman (Acting) | D45: Raise | I45: Ranel R. Narciso | N45: Road & Camp Maintenance | O45: TSG - PCES - Plumbing and Water Supply
C46: QA/QC Aide | D46: Ramp | I46: Raul S. Visperas | N46: Sand & Gravel Plant | O46: TSG - PCES - Jobs in Progress
C47: Sand Production Operator | D47: Repair Bay | I47: Raymund D. Bonilla | N47: Underground Patrol | O47: TSG - PCES - Water Source Mgmt. & Maintenance
C48: Shaftman | D48: Rock Drill Shop | I48: Regie D. Espinosa | N48: Investigations | O48: TSG - PCES - Building Maintenance
C49: Shiftboss | D49: San Antonio Area | I49: Reynaldo C. Agno | N49: Planning & Budgeting | O49: TSG - PCES - Road & Camp Maint.
C50: Shipside - Volvo Truck | D50: Sapid Crusher | I50: Romy A. Domyong | N50: Cashier | O50: TSG - PCES - Sand & Gravel Plant
C51: Surface Warehouseman | D51: Shaft Station / Resting Area | I51: Ruben L. Gorero | N51: General Accounting | O51: TSG - SMED - Surface Electrical
... C55: Ventilation Installation Man | D55: Sump | I55: Silvestre L. Miguel | N55: Inventory Control | O55: ASG - IOSD - Underground Patrol
D56: Surface LMD Camp | I56: Sidney Lee B. Balong | N56: Disposal | O56: ASG - IOSD - Investigations
D57: Tagumbao, Sapid | I57: Tofer T. Padsoyan | N57: Underground Warehouse | O57: ASG - IOSD - Surface
D58: Tamangan Area, Lime 2 | I58: Vincent S. Camiling | N58: Rock Mechanics | O58: ASG - HR - Training
D59: Timber Yard, Nayak | I59: Wincy C. Awingan | N59: Laboratory | O59: ASG - Medical Services - Nurse
D60: TP3 Dam Area | N60: Mine Geology Operations | O60: Contracts - DDCP
D61: TSF 5A | N61: Mine Resource and Ore Reserves | O61: Contracts - MD&C Construction
D62: Tubo, Sapid | N62: Mill Projects | O62: Contracts - VSAI -
D63: UG Crusher | N63: HR-Training | O63: Contracts - SNSAI -
D64: Upper Tram | N64: Upper Tram | O64: Contracts - RBDanao -
D65: Undetermined | N65: Mill Maintenance Planning | O65: FSG - IMD - Surface Warehouse
D66: 670L Dewatering | N66: Maintenance - Electrical | O66: FSG - IMD - Inventory Control
N67: Maintenance - Mechanical | O67: FSG - IMD - Disposal
N68: Record | O68: FSG - IMD - Underground Warehouse
N69: Nurse | O69: GMG - Assay - Fire Assay
N70: Laboratory | O70: GMG - Assay - Wet Assay / Mineral Lab
N71: Pharmacy | O71: GMG - Assay - Sample Preparation
N72: Radiology | O72: GMG - Assay - Oil Laboratory
N73: Utility | O73: GMG - TSF5A
N74: Laundry
N75: Drivers
N76: Fire Assay
N77: Wet Assay / Mineral Lab
N78: Sample Preparation
N79: Oil Laboratory

Sheet input
A1: MONTH - YEAR | B1: SECTION (SURFACE / UNDERGROUND) | C1: VICTIM / DAMAGED PROPERTY | D1: CN / Unit # | E1: OCCUPATION / DESIGNATION | F1: TYPE OF INCIDENT | G1: WORKPLACE / AREA | H1: LEVEL | I1: DATE | J1: TIME | K1: SHIFT | L1: DEPARTMENT HEAD | M1: SECTION HEAD | N1: IMMEDIATE SUPERVISOR | O1: NATURE OF INJURY | P1: ON-GOING ACTIVITY | Q1: SAFETY INSPECTOR ON DUTY | R1: GROUP | S1: DEPARTMENT | T1: SECTION | U1: RECORDED BY | V1: OTHER INFO.: LOCATION | W1: HEADS | X1: GRP/DEPT/SECT | Y1: MEDICAL FINDINGS | Z1: DETAILS OF TREATMENT PROVIDED | AA1: REHABILITATION PLAN | AB1: Unsafe Acts | AC1: Personal Factors | AD1: Unsafe Conditions | AE1: Job Factors
A2: JANUARY, 2026 | B2: Underground | C2: RYAN DAVE MAWI-IT | D2: 8471 | E2: Assistant Miner | F2: Occupational Illness / Pain | G2: Shaft Station / Resting Area | H2: 900L | I2: 46032 | J2: 0.97916667 | K2: Second | L2: Hilbert G. Andong | M2: Reynaldo P. Kiking | N2: Stephen Adams D. Mamanteo | O2: OI | P2: Cleaning of canal. | Q2: WDL / MAT | R2: MOG | S2: Dept. 2 | T2: Section 6 | U2: MAT | V2: RP No. 22 | W2: HGA / RPK / SADM | X2: MOG - 2: Section 6
A3: JANUARY, 2026 | B3: Underground | C3: JOEY A. LASSIN | D3: 9728 | E3: Assistant Miner | F3: Struck by Falling Rock | G3: Stope | H3: 970L | I3: 46038 | J3: 0.97916667 | K3: Second | L3: Venancio A. Bad-ay | M3: Mariel T. Ayong | N3: Leonard K. Fawayan | O3: FAC | P3: Rock Bolting | Q3: JAW / EAR / MAT / AOV | R3: MOG | S3: Dept. 1 | T3: Section 2 | U3: MAT | V3: 21516 4M4 | W3: VAB / MTA / LKF | X3: MOG - 1: Section 2 | Y3: MULTIPLE PHYSICAL INJURY | Z3: WOUND CARE. XRAY OF LEFT KNEE,LSV,TCAGE, ANTIBIOTIC, ANALGESIC, TETANUS TOXOID. | AA3: ADMITTED AT THE HOSPITAL FOR HEALING
A4: JANUARY, 2026 | B4: Underground | C4: MANUEL D. BALAIS | D4: 1209 | E4: Shiftboss | F4: Foreign Object in the Eye/s | G4: Ramp | H4: 1100L | I4: 46046 | J4: 0.125 | K4: First | L4: Hilbert G. Andong | M4: Allab B. Lal-wet | N4: Dummory Joseff Febrei O. Estepa | O4: FAC | P4: Operating the breaker | Q4: WLT / SUU / FPP | R4: MOG | S4: Dept. 2 | T4: Section 4 | U4: MAT | V4: 305 RAMP | W4: HGA / ABL / DJFOE | X4: MOG - 2: Section 4
A5: JANUARY, 2026 | B5: Underground | C5: WILBUR D. AWIS | D5: 9940 | E5: Maintenance Man (MMME) | F5: Occupational Illness / Pain | G5: Shaft Station / Resting Area | H5: 900L | I5: 46047 | J5: 0.29166667 | K5: Second | L5: Fernando A. Bustillo Jr. | M5: Alfon B. Yodong | N5: John Pauline M. Refugia | O5: OI | P5: Preparing for task | Q5: SUU | R5: MOG | S5: MMME | T5: Mobile | U5: MAT | V5: RP No. 22 | W5: FABJr. / ABY / JPMR | X5: MOG - MMME - Mobile
A6: JANUARY, 2026 | B6: Underground | C6: DUMAGUING M. LIBAN | D6: 1336 | E6: LHD Optr | F6: Caught in Between | G6: Ramp | H6: 1000L | I6: 46048 | J6: 0.8125 | K6: Third | L6: Venancio A. Bad-ay | M6: June O. Golocan | N6: Danilo M. Galande | O6: LTA-F | P6: Descending towards 900L | Q6: WLT / EAR | R6: MOG | S6: Dept. 1 | T6: Section 3 | U6: MAT | V6: 207 K Ramp, 1012 Elevation | W6: VAB / JOG / DMG | X6: MOG - 1: Section 3 | Y6: IMMEDIATE CAUSE: MECHANICAL ASPHYXIA ANTECEDENT CAUSE: CRUSHING INJURY TO THE TORSO UNDERLYING CAUSE: CAUGHT BETWEEN THE HEAVY EQUIPMENT AND A MUCK PILE | Z6: N/A | AA6: N/A
A7: JANUARY, 2026 | B7: Underground | C7: GLENN MARK B. LABOTAN | D7: 9346 | E7: UG Senior Warehouseman | F7: Caught in Between | G7: Fuel Storage Area | H7: 900L | I7: 46052 | J7: 0.40625 | K7: Second | L7: Fe Marie W. Mates | M7: Samson A. Fotyong | N7: Marvin B. Caligner | O7: LTA-NF | P7: Unloading fuel oil drum | Q7: MAT / AOV | R7: FSG | S7: IMD | T7: Underground Warehouse | U7: KTA | V7: C30 Fuel Storage | W7: FMWM / SAF / MBC | X7: FSG - IMD - Underground Warehouse | Y7: AVULSED WOUND, OPEN FRACTURE 2ND/3RD DISTAL PHALANX LEFT HAND | Z7: WOUND SUTURING WITH AMPUTATION OF DISTAL PHALANX 2ND DIGIT LEFT HAND | AA7: FOR RUTHER MEDICAL EVALUATION
A8: JANUARY, 2026 | B8: Surface | C8: BINSON I. ZAPARITA | D8: 9901 | E8: Jr. Machinist | F8: Caught in Between | G8: Machine Shop | H8: S (N/A) | I8: 46039 | J8: 0.46527778 | K8: Second | L8: Larry A. Arigue | M8: James I. Consolacion | N8: N/A | O8: FAC | P8: Unloading via crane operation | Q8: MBK / RML | R8: TSG | S8: MWSO | T8: Machine Shop | U8: RML | V8: N/A | W8: LAA / JIC / - | X8: TSG - MWSO - Machine Shop | Y8: AVULSED WOUND, 4TH DIGIT, RIGHT HAND | Z8: WOUND IRRIGATION AND PACKING, ATS, TT VACCINE, ANALGESIC, XRAY. | AA8: TRANSFERRED TO LUIS HORA FOR FURTHER MANAGEMENT
A9: JANUARY, 2026 | B9: Surface | C9: ROWELL C. DELA CRUZ | D9: 9386 | E9: Surface Warehouseman | F9: Contact with Object | G9: Steel Yard | H9: S (N/A) | I9: 46034 | J9: 0.32291667 | K9: Second | L9: Fe Marie W. Mates | M9: Julian Manuel S. Casuga | N9: Karl Lloyd S. Valentin | O9: FAC | P9: Loading of Causic Soda | Q9: ENC / RML | R9: FSG | S9: IMD | T9: Surface Warehouse | U9: RML | V9: N/A | W9: FMWM / JMSC / KLSV | X9: FSG - IMD - Surface Warehouse | Y9: CHEMICAL BURN LEFT FOOT SECONDARY TO METABISULFITE | Z9: WOUND DEBRIDEMENT/DRESSING
A10: JANUARY, 2026 | B10: Surface | C10: JOHN REY BAGUIYAC | D10: N/A - Contracts | E10: Carpenter | F10: Caught in Between | G10: Hospital | H10: S (N/A) | I10: 46045 | J10: 0.33333333 | K10: Second | L10: Abraham L. Davis | M10: Nathaneal D. Jugal | N10: Kathy M. Domogo | O10: FAC | P10: Hauling of H-beams | Q10: ENC / RML | R10: Contracts | S10: MD&C Construction | T10: Building Maintenance | U10: RML | V10: Proposed Hemodialysis Station | W10: Contracts - MD&C Construction | X10: Contracts - MD&C Construction
A11: JANUARY, 2026 | B11: Surface | C11: FUSE CUT-OFF SWITCH | D11: N/A - PD | E11: Fuse Cut-Off Switch | F11: Property Damage | G11: UG Crusher | H11: S (N/A) | I11: 46039 | J11: 0.77083333 | K11: Third | L11: Fernando A. Bustillo Jr. | M11: Neil Marcel F. Paquito | N11: Pedro B. Lambino | O11: PD | P11: Sudden Power Loss | Q11: MBK | R11: MOG | S11: MMME | T11: Electrical | U11: KTA | V11: 300 KVA Substation | W11: FABJr. / NMFP / PBL | X11: MOG - MMME - Electrical
A12: JANUARY, 2026 | B12: Surface | C12: PINE TREES | D12: N/A - EI | E12: Forest Fire | F12: Fire | G12: Buaki, Sapid | H12: S (N/A) | I12: 46043 | J12: 0.66666667 | K12: Second | L12: N/A | M12: N/A | N12: N/A | O12: EI | Q12: MBK | R12: ASG | S12: IOSD | T12: N/A - Community | U12: KTA | W12: N/A | X12: N/A - Emergency Incident
A13: JANUARY, 2026 | B13: Surface | C13: BURNT GARBAGE | D13: N/A - EI | E13: Forest Fire | F13: Fire | G13: Golf Course, Sapid | H13: S (N/A) | I13: 46046 | J13: 0.82361111 | K13: Third | L13: N/A | M13: N/A | N13: N/A | O13: EI | Q13: ENC | R13: ASG | S13: IOSD | T13: N/A - Community | U13: KTA | W13: N/A | X13: N/A - Emergency Incident | Y13: N/A
A14: JANUARY, 2026 | B14: Surface | C14: VOLVO TRUCK | D14: TDQ 954 | E14: Shipside - Volvo Truck | F14: Fall on Lower level | G14: Tubo, Sapid | H14: S (N/A) | I14: 46052 | J14: 0.29027778 | K14: Second | L14: N/A | M14: N/A | N14: N/A | O14: EI | P14: Delivery of goods | Q14: MBK | R14: FSG | S14: IMD | T14: Surface Warehouse | U14: KTA | W14: N/A | X14: N/A - Emergency Incident
A15: FEBRUARY, 2026 | B15: Underground | C15: NOREL ALAGON | D15: N/A - Contracts | E15: Drill Helper / Drilling Aide | F15: Struck by Object | G15: Cuddy | H15: 1000L | I15: 46062 | J15: 0.625 | K15: Second | L15: Venancio A. Bad-ay | M15: DDCP - Allan Raymund Domalsin | N15: DDCP - Clarence Avila | O15: FAC | P15: Retreiving inner drill tube | Q15: WDL / RWV | R15: Contracts | S15: DDCP | T15: Section 3 | U15: MAT | V15: LM90 Cuddy | W15: VAB / ARD / CTA | X15: Contracts - DDCP
A16: FEBRUARY, 2026 | B16: Underground | C16: JULUIS M. FANGGOT | D16: 9027 | E16: Assistant Miner | F16: Caught in Between | G16: Raise | H16: 1000L | I16: February 11, 2026 | J16: 0.72569444 | K16: Third | L16: Venancio A. Bad-ay | M16: June O. Golocan | N16: Jerry I. Garwageo | O16: LTA-NF | P16: Hand Mucking | Q16: RWV / FPP | R16: MOG | S16: Dept. 1 | T16: Section 3 | U16: MAT | V16: 21516 Raise Access | W16: VAB / JOG / JIG | X16: MOG - 1: Section 3 | Y16: Fracture Closed Non-Displaces Medial Malleolus Left Tibia | Z16: Short Posterior Mold L Foot | AA16: Week 0-2: Immobilization. Maintain cast, non-weight bearing, with crutches; Week 2-6: Continue Immobilization. Partial Weight bearing; Week 6-8: Full weight bearing as tolerated. Light work and activity Week 8-12: Return to full activity
A17: FEBRUARY, 2026 | B17: Underground | C17: ALJON J. VALDEZ | D17: 1 | E17: Lead Miner | F17: Occupational Illness / Pain | G17: Shaft Station / Resting Area | H17: 900L | I17: February 15, 2026 | J17: 0.90277778 | K17: Third | L17: Venancio A. Bad-ay | M17: Dimas S. Gao-ay | N17: Regie D. Espinosa | O17: OI | P17: Resting | Q17: ACBJr. | R17: MOG | S17: Dept. 1 | T17: Section 1 | U17: MAT | V17: 249 Station 900L | W17: VAB / DSG / RDE | X17: MOG - 1: Section 1
A18: FEBRUARY, 2026 | B18: Underground | C18: RAMIL A BAYYOC | D18: 7844 | E18: Maintenance Man (GMS) | F18: Occupational Illness / Pain | G18: Shaft Station / Resting Area | H18: 900L | I18: February 16, 2027 | J18: 0.35416667 | K18: Second | L18: Jayson T. Capia-ao | M18: Julius B. Liban | N18: Ephraim K. Pitok | O18: OI | P18: Waiting for the locomotive to charge | Q18: WDL/MAT/ AOV | R18: MOG | S18: GMS | T18: Nayak Shaft Operation / UG Construction | U18: MAT | V18: 249 Station 900L | W18: JTC / JBL / EKP | X18: MOG - GMS - Nayak Shaft / UG Construction
A19: FEBRUARY, 2026 | B19: Underground | C19: WILLARD S. BAGYON | D19: 621 | E19: Assistant Miner | F19: Occupational Illness / Pain | G19: Mainline / Access | H19: 980L | I19: February 19, 2028 | J19: 0.14583333 | K19: First | L19: Venancio A. Bad-ay | M19: Mariel T. Ayong | N19: Frank C. Samdao Jr. | O19: OI | P19: Jack up Activity | Q19: JAW | R19: MOG | S19: Dept. 1 | T19: Section 2 | U19: MAT | V19: 2091 Access 980L | W19: VAB / MTA / FCSJr | X19: MOG - 1: Section 2
A20: FEBRUARY, 2026 | B20: Underground | C20: JHON JHON B. ANGDASON | D20: 30 | E20: Assistant Miner | F20: Caught in Between | G20: Stope | H20: 870L | I20: February 20, 2029 | J20: 0.10416667 | K20: First | L20: Hilbert G. Andong | M20: Reynaldo P. Kiking | N20: Allan F. Takayeng | O20: FAC | P20: Hand Mucking | Q20: JAW | R20: MOG | S20: Dept. 2 | T20: Section 6 | U20: MAT | V20: 12541 G31S | W20: HGA / RPK / AFT | X20: MOG - 2: Section 6
A21: FEBRUARY, 2026 | B21: Underground | C21: JACKFORD L. PALSAAN | D21: 1858 | E21: LHD Optr | F21: Struck by Falling Rock | G21: Stope | H21: 890L | I21: 46076 | J21: 0.85416667 | K21: Third | L21: Venancio A. Bad-ay | M21: Dimas S. Gao-ay | N21: Ryan M. Macaburas | O21: FAC | P21: LHD Mucking Activity | Q21: JAW/SAU | R21: MOG | S21: Dept. 1 | T21: Section 1 | U21: MAT | V21: 2325 6M4 | W21: VAB / DSG / RMM | X21: MOG - 1: Section 1
A22: FEBRUARY, 2026 | B22: Underground | C22: CRAYTON B. CALSIYAO | D22: 9690 | E22: Assistant Miner | F22: Punctured | G22: Stope | H22: 1000L | I22: 46077 | J22: 0.0625 | K22: First | L22: Venancio A. Bad-ay | M22: June O. Golocan | N22: Bernard M. Itliong | O22: FAC | P22: Pulling out Timber Logs | Q22: RWV | R22: MOG | S22: Dept. 1 | T22: Section 3 | U22: MAT | V22: 205 4M4 | W22: VAB / JOG / BMI | X22: MOG - 1: Section 3
A23: FEBRUARY, 2026 | B23: Underground | C23: LEONARD D. SALINGSING | D23: 9820 | E23: Geotech Aide | F23: Struck by Falling Rock | G23: Stope | H23: 880L | I23: 46077 | J23: 0.32291667 | K23: Second | L23: Kurt Linis Ljomir Ursua | M23: Benito A. Islao Jr. | N23: Romy A. Domyong | O23: LTA-NF | P23: Ground Condition & Support Assessment | Q23: AOV/ACB/WLT | R23: MEGG | S23: Min Geology | T23: Rock Mechanics | U23: MAT | V23: 12508 H31N | W23: KLLU / BAIJr. / RAD | X23: MEGG - Rock Mechanics
A24: FEBRUARY, 2026 | B24: Underground | C24: JERRY L. BISTAYOK | D24: 7230 | E24: Assistant Miner | F24: Struck by Falling Rock | G24: Development | H24: 1000L | I24: 46078 | J24: 0.40625 | K24: Second | L24: Hilbert G. Andong | M24: Ruben T. Saliwey | N24: N/A | O24: FAC | P24: Bar down | Q24: AOV/ACB/WLT/EAR/MAT | R24: MOG | S24: Dept. 2 | T24: Section 5 | U24: MAT | V24: 320 XCE | W24: HGA / RTS / - | X24: MOG - 2: Section 5
A25: FEBRUARY, 2026 | B25: Surface | C25: TALIWAN JR., SIMON A. | D25: 790 | E25: Laboratory Technician | F25: Fall on Lower level | G25: Crushing Area | H25: S (N/A) | I25: 46077 | J25: 0.39583333 | K25: Second | L25: John Paul C. Licot | M25: N/A | N25: Marry Joy S. Ronulo | O25: NM | P25: Descending the ramp | Q25: RML / MBK | R25: MPG | S25: Metallurgy | T25: Laboratory | U25: KTA | V25: Gap b/n conveyor and ramp | W25: JPC / - / MJSR | X25: MPG - Metallurgy - Laboratory
A26: FEBRUARY, 2026 | B26: Surface | C26: BURNT GARBAGE | D26: N/A - EI | E26: Forest Fire | F26: Fire | G26: Gravel Pit, Sapid | H26: S (N/A) | I26: 46059 | J26: 0.71180556 | K26: Third | L26: N/A | M26: N/A | N26: N/A | O26: EI | P26: IEC at Brgy. Sapid | Q26: MBK | R26: ASG | S26: IOSD | T26: N/A - Community | U26: KTA | W26: N/A | X26: N/A - Emergency Incident
A27: FEBRUARY, 2026 | B27: Surface | C27: LMD EMPLOYEES | D27: N/A - EI | E27: N/A | F27: Earthquake | G27: Surface LMD Camp | H27: S (N/A) | I27: 46069 | J27: 0.40277778 | K27: Second | L27: N/A | M27: N/A | N27: N/A | O27: EI | P27: Normal Surface Operations | Q27: RML | R27: ASG | S27: IOSD | T27: N/A - Community | U27: KTA | W27: N/A | X27: N/A - Emergency Incident
A28: FEBRUARY, 2026 | B28: Surface | C28: PINE TREES | D28: N/A - EI | E28: Forest Fire | F28: Fire | G28: Golf Course, Sapid | H28: S (N/A) | I28: 46074 | J28: 0.69791667 | K28: Third | L28: N/A | M28: N/A | N28: N/A | O28: EI | P28: Normal Surface Operations | Q28: MBK | R28: ASG | S28: IOSD | T28: N/A - Community | U28: KTA | W28: N/A | X28: N/A - Emergency Incident
A29: FEBRUARY, 2026 | B29: Surface | C29: PINE TREES | D29: N/A - EI | E29: Forest Fire | F29: Fire | G29: Tagumbao, Sapid | H29: S (N/A) | I29: February 26, 2026 | J29: 0.85763889 | K29: Third | L29: N/A | M29: N/A | N29: N/A | O29: EI | P29: Normal Surface Operations | Q29: ACG | R29: ASG | S29: IOSD | T29: N/A - Community | U29: KTA | W29: N/A | X29: N/A - Emergency Incident
A30: FEBRUARY, 2026 | B30: Surface | C30: HOSE | D30: N/A - EI | E30: Forest Fire | F30: Fire | G30: Aerodome Area | H30: S (N/A) | I30: February 28, 2026 | J30: 0.48888889 | K30: Second | L30: N/A | M30: N/A | N30: N/A | O30: EI | P30: Normal Surface Operations | Q30: RML | R30: ASG | S30: IOSD | T30: N/A - Community | U30: KTA | W30: N/A | X30: N/A - Emergency Incident
A31: MARCH, 2026 | B31: Surface | C31: FOREST FIRE | D31: N/A - EI | E31: Forest Fire | F31: Fire | G31: Golf Course, Sapid | H31: S (N/A) | I31: March 6, 2026 | J31: 0.91041667 | K31: Third | L31: N/A | M31: N/A | N31: N/A | O31: EI | P31: Burning of dry grass | Q31: ENC | R31: ASG | S31: IOSD | T31: N/A - Community | U31: KTA | W31: N/A | X31: N/A - Emergency Incident | Y31: N/A | Z31: N/A | AA31: N/A
A32: MARCH, 2026 | B32: Surface | C32: OIL SPILL | D32: TFQ 524 | E32: Mill Engineering Service Vehicle | F32: Property Damage | G32: LMD Roadway | H32: S (N/A) | I32: March 9, 2026 | J32: 0.40208333 | K32: Second | L32: Abraham L. Davis | M32: Julius K. Finatec | N32: N/A | O32: EI | P32: Whilst backing: Parking inside GO | Q32: MBK / RML | R32: MPG | S32: Mill Engineering | U32: KTA | V32: General Office Area | W32: ALD / JKF / - | X32: MPG - Mill Engineering | Y32: N/A | Z32: N/A | AA32: N/A
A33: MARCH, 2026 | B33: Surface | C33: LIME SURGE TANK | D33: N/A - PD | E33: Lime Surge Tank | F33: Contact with Object | G33: Lime Plant | H33: S (N/A) | I33: March 14, 2026 | J33: 0.9375 | K33: Third | L33: Dexter B. Arevalo | M33: Jeric T. Dulawan | N33: Lawana Jr., Aquino P. | O33: PD | P33: Normal Surface Operations | Q33: MBK | R33: MPG | S33: Mill Operations | T33: Grinding | U33: KTA | V33: Lime Tank 17/25 | W33: DBA / JTD / APLJr. | X33: MPG - Mill Operations - Crushing & Grinding | Y33: N/A | Z33: N/A | AA33: N/A
A34: MARCH, 2026 | B34: Surface | C34: FOREST FIRE | D34: N/A - EI | E34: Forest Fire | F34: Fire | G34: Slaughter, San Roque | H34: S (N/A) | I34: March 14, 2026 | J34: 0.75 | K34: Third | L34: N/A | M34: N/A | N34: N/A | O34: EI | P34: Burning of dry grass | Q34: MBK | R34: ASG | S34: IOSD | T34: N/A - Community | U34: KTA | W34: N/A | X34: N/A - Emergency Incident | Y34: N/A | Z34: N/A | AA34: N/A
A35: MARCH, 2026 | B35: Surface | C35: FOREST FIRE | D35: N/A - EI | E35: Forest Fire | F35: Fire | G35: Tagumbao, Sapid | H35: S (N/A) | I35: March 14, 2026 | J35: 0.75 | K35: Third | L35: N/A | M35: N/A | N35: N/A | O35: EI | P35: Burning of Garbage | Q35: MBK | R35: ASG | S35: IOSD | T35: N/A - Community | U35: KTA | W35: N/A | X35: N/A - Emergency Incident | Y35: N/A | Z35: N/A | AA35: N/A
A36: MARCH, 2026 | B36: Underground | C36: JUN JUN G. DAGYO | D36: 9923 | E36: Assistant Miner | F36: Occupational Illness / Pain | G36: Stope | H36: 870L | I36: March 9, 2026 | J36: 0.45833333 | K36: Second | L36: Venancio A. Bad-ay | M36: Dimas S. Gao-ay | N36: Ryan M. Macaburas | O36: OI | P36: Hand Mucking | Q36: MAT/WDL/RWV | R36: MOG | S36: Dept. 1 | T36: Section 1 | U36: MAT | V36: 225 6L1 | W36: VAB / DSG / RMM | X36: MOG - 1: Section 1 | Y36: T/C Electrolyte Imbalance | Z36: IVF Hydration | AA36: Fit to Work
A37: MARCH, 2026 | B37: Underground | C37: NESTOR O. DUGAO | D37: 9771 | E37: Geologic Sampler | F37: Contact with Smoke | G37: Mainline / Access | H37: 870L | I37: 46092 | J37: 0.38194444 | K37: Second | L37: Kurt Linis Ljomir Ursua | M37: Bullet P. Tangcalagan | N37: Sandro Daniel G. Cababa | O37: OI | P37: Waiting for the LHD mucking activity | Q37: AOV/WLT/EAR/MAT | R37: MEGG | S37: Mine Geology | T37: Mine Geology Operations | U37: KTA | V37: 256 RB Access | W37: KLLU / BPT / SDGC | X37: MEGG - Mine Geology | Y37: Smoke Inhalation Injury | Z37: Admission | AA37: For further Medical Evaluation: For in-patient management
A38: MARCH, 2026 | B38: Underground | C38: JOMEL W. DAWING | D38: 9697 | E38: Maintenance Man (MMME) | F38: Struck by Object | G38: Rock Drill Shop | H38: 1000L | I38: 46095 | J38: 0.33333333 | K38: Third | L38: Fernando A. Bustillo Jr. | M38: Baker S. Calbid | N38: N/A | O38: FAC | P38: In the process of knocking out the control valve assembly of RDM #22013 | Q38: SAU | R38: MOG | S38: MMME | T38: Non-Mobile | U38: MAT | V38: 249 Rock Drill Shop | W38: FABJr. / BSC / - | X38: MOG - MMME - Non-Mobile | Y38: Superficial Avulsed Wound, 3rd Digit Left Hand | Z38: Xray of Left Hand, Anti-Tetanous Vaccine, Antibiotics, Analgesic | AA38: Fit to Work
A39: MARCH, 2026 | B39: Underground | C39: ALBERT M. ALIGA | D39: 9946 | E39: Assistant Miner | F39: Struck by Falling Rock | G39: Development | H39: 1000L | I39: 46097 | J39: 0.15625 | K39: First | L39: Hilbert G. Andong | M39: Ruben T. Saliwey | N39: Andy M. Delumen | O39: FAC | P39: Cleaning of Blast Hole through blow piping | Q39: WDL/RWV | R39: MOG | S39: Dept. 2 | T39: Section 5 | U39: MAT | V39: 320 XCE | W39: HGA / RTS / AMD | X39: MOG - 2: Section 5 | Y39: Multiple Lacerated Wound on Forehead | Z39: Wound Suturing | AA39: Fit to Work
A40: MARCH, 2026 | B40: Underground | C40: REYMARK L. LANGOEY | D40: 1930 | E40: Shaftman | F40: Occupational Illness / Pain | G40: Shaft Station / Resting Area | H40: S (N/A) | I40: 46098 | J40: 0.5625 | K40: Second | L40: Jayson T. Capia-ao | M40: Edie S. Pacsay | N40: Angelito A. Delim | O40: OI | P40: Changing his working clothes | Q40: MAT/WLT | R40: MOG | S40: GMS | T40: Tubo Shaft Operation / 670L Pumping | U40: KTA | V40: Change Room, Tubo | W40: JTC / ESP / AAD | X40: MOG - GMS - Tubo Shaft | Y40: Acute Gastritis | Z40: Admitted for IV Hydration and Medication | AA40: Fit to Work
A41: MARCH, 2026 | B41: Underground | C41: KEVIN A. PALANGDAO | D41: 8489 | E41: Assistant Miner | F41: Fall on Lower level | G41: Timber Yard, Nayak | H41: S (N/A) | I41: 46099 | J41: 0.27916667 | K41: First | L41: Venancio A. Bad-ay | M41: Dimas S. Gao-ay | N41: Mauricio D. Bangngayon | O41: FAC | P41: Going out of the Service Truck | Q41: AOV/WLT/EAR/MAT | R41: MOG | S41: Dept. 1 | T41: Section 1 | U41: MAT | V41: Nayak Adit Portal | W41: VAB / DSG / MDB | X41: MOG - 1: Section 1 | Y41: Multiple Physical Injuryies, Secondary to fall | Z41: Skull Xray, Wound Suturing, Anti-Tetanous Vaccine, Antibiotics, Analgesics | AA41: Fit to Work
A42: MARCH, 2026 | B42: Surface | C42: GUERICK LEE B. BALONG | D42: 4127 | E42: Maintenance Man (TSF) | F42: Fall on Same Level | G42: Bonanza Quarry, TSF | H42: S (N/A) | I42: 46099 | J42: 0.35416667 | K42: Second | L42: Fabrian Roderick S. Likigan | M42: Jordan P. Masidong | N42: N/A | O42: FAC | P42: Clearing vegetation | Q42: ENC | R42: GMG | S42: TSF 5A | U42: KTA | V42: Bonanza Quarry | W42: FRSL / JPM / - | X42: MPG - TSF 5A | Y42: Lacerated Wound, Left Hand | Z42: Wound Suturing, Anti-Tetanous Vaccine, Antibiotics, Analgesics | AA42: Fit to Work
A43: MARCH, 2026 | B43: Surface | C43: NORVY P. FRANCISCO | D43: 207 | E43: Mill Mechanical ADH | F43: Struck by Object | G43: Boiler Room Extension | H43: S (N/A) | I43: March 24, 2026 | J43: 0.36458333 | K43: Second | L43: Kay B. Lacambra | M43: Reynaldo G. Cawi | N43: N/A | O43: NM | P43: Roof Installment | Q43: MBK / RML | R43: MPG | S43: Mill Mechanical | T43: Mill Projects | U43: KTA | W43: KBL / RGC / - | X43: MPG - Mill Mechanical | Y43: N/A | Z43: N/A | AA43: N/A
A44: MARCH, 2026 | B44: Surface | C44: JOEBERT G. BITOT | D44: 3618 | E44: Mill Mechanical Fitter | F44: Struck by Object | G44: Boiler Room Extension | H44: S (N/A) | I44: March 24, 2026 | J44: 0.36458333 | K44: Second | L44: Kay B. Lacambra | M44: Reynaldo G. Cawi | N44: Jefferson V. Ramos | O44: NM | P44: Roof Installment | Q44: MBK / RML | R44: MPG | S44: Mill Engineering | T44: Mill Projects | U44: KTA | W44: KBL / RGC / JVR | X44: MPG - Mill Engineering | Y44: N/A | Z44: N/A | AA44: N/A
A45: MARCH, 2026 | B45: Surface | C45: FOREST FIRE | D45: N/A - EI | E45: Forest Fire | F45: Fire | G45: Old Gate 3 | H45: S (N/A) | I45: March 25, 2026 | J45: 0.75 | K45: Third | L45: N/A | M45: N/A | N45: N/A | O45: EI | P45: Normal Surface Operations | Q45: ENC | R45: ASG | S45: IOSD | T45: N/A - Community | U45: KTA | W45: N/A | X45: N/A - Emergency Incident | Y45: N/A | Z45: N/A | AA45: N/A
A46: MARCH, 2026 | B46: Surface | C46: FOREST FIRE | D46: N/A - EI | E46: Forest Fire | F46: Fire | G46: Casubigan, Sapid | H46: S (N/A) | I46: March 25, 2026 | J46: 0.75 | K46: Third | L46: N/A | M46: N/A | N46: N/A | O46: EI | P46: Normal Surface Operations | Q46: ENC | R46: ASG | S46: IOSD | T46: N/A - Community | U46: KTA | W46: N/A | X46: N/A - Emergency Incident | Y46: N/A | Z46: N/A | AA46: N/A
A47: MARCH, 2026 | B47: Surface | C47: FOREST FIRE | D47: N/A - EI | E47: Forest Fire | F47: Fire | G47: Sapid Crusher | H47: S (N/A) | I47: March 25, 2026 | J47: 0.75 | K47: Third | L47: N/A | M47: N/A | N47: N/A | O47: EI | P47: Normal Surface Operations | Q47: ENC | R47: ASG | S47: IOSD | T47: N/A - Community | U47: KTA | W47: N/A | X47: N/A - Emergency Incident | Y47: N/A | Z47: N/A | AA47: N/A
A48: MARCH, 2026 | B48: Underground | C48: REYMAR M. GINPAC | D48: 7849 | E48: Geologic Sampler | F48: Occupational Illness / Pain | G48: Mainline / Access | H48: 860L | I48: March 26, 2026 | J48: 0.40277778 | K48: Second | L48: Kurt Linis Ljomir Ursua | M48: Bullet P. Tangcalagan | N48: Sandro Daniel G. Cababa | O48: OI | P48: Finding for a resting place after sampling on Section 1 | Q48: AOV/MAT/JAW/WDL | R48: MEGG | S48: Mine Geology | T48: Mine Geology Operations | U48: KTA | V48: 249 Roadway | W48: KLLU / BPT / SDGC | X48: MEGG - Mine Geology | Y48: T/C Electrolyte Imbalance vs. Heat Exhaustion | Z48: Oral Hydration | AA48: For further Medical Evaluation: For Serum Electrolytes; Fit to work
A49: MARCH, 2026 | B49: Surface | C49: FOREST FIRE | D49: N/A - EI | E49: Forest Fire | F49: Fire | G49: Sapid Crusher | H49: S (N/A) | I49: March 28, 2026 | J49: 0.57638889 | K49: Second | L49: N/A | M49: N/A | N49: N/A | O49: EI | P49: Normal Surface Operations | Q49: ENC / KTA / ACG | R49: ASG | S49: IOSD | T49: N/A - Community | U49: KTA | V49: left upon entrance from Marivic of the Golf area | W49: N/A | X49: N/A - Emergency Incident | Y49: N/A | Z49: N/A | AA49: N/A
A50: MARCH, 2026 | B50: Surface | C50: FOREST FIRE | D50: N/A - EI | E50: Forest Fire | F50: Fire | G50: Sapid Crusher | H50: S (N/A) | I50: March 29, 2026 | J50: 0.56875 | K50: Second | L50: N/A | M50: N/A | N50: N/A | O50: EI | P50: Normal Surface Operations | Q50: ENC | R50: ASG | S50: IOSD | T50: N/A - Community | U50: KTA | V50: left upon entrance from Marivic of the Golf area | W50: N/A | X50: N/A - Emergency Incident | Y50: N/A | Z50: N/A | AA50: N/A
A51: MARCH, 2026 | B51: Surface | C51: FOREST FIRE | D51: N/A - EI | E51: Forest Fire | F51: Fire | G51: Panad Roadway, Poblacion | H51: S (N/A) | I51: March 30, 2026 | J51: 0.40972222 | K51: Second | L51: N/A | M51: N/A | N51: N/A | O51: EI | P51: Industrial Fire Drill at Carpentry Area | Q51: ENC / RML | R51: ASG | S51: IOSD | T51: N/A - Community | U51: KTA | V51: Near Executive House | W51: N/A | X51: N/A - Emergency Incident | Y51: N/A | Z51: N/A | AA51: N/A
A52: MARCH, 2026 | B52: Surface | C52: LEE L. DEYA-AS JR. | D52: 8500 | E52: Maintenance Man (PCES) | F52: Punctured | G52: Carpentry Shop | H52: S (N/A) | I52: March 30, 2026 | J52: 0.45833333 | K52: Second | L52: Abraham L. Davis | M52: N/A | N52: Nathaneal D. Jugal | O52: NLTA | P52: Resizing salvaged lumber using an arbor saw | Q52: RML / ENC / ACG | R52: TSG | S52: PCES | T52: Building Maintenance | U52: KTA | W52: ALD / - / NDJ | X52: TSG - PCES - Building Maintenance | Y52: Non Penetrating Chest Injury | Z52: Wound Suturing, Anti-Tetanous Vaccine, Antibiotics, Analgesics | AA52: For further Medical Evaluation: Recommended for light works, 7 days subject to re-evaluation; Fit to work
A53: MARCH, 2026 | B53: Surface | C53: FOREST FIRE | D53: N/A - EI | E53: Forest Fire | F53: Fire | G53: Casubigan / Marivic Area | H53: S (N/A) | I53: March 31, 2026 | J53: 0.62986111 | K53: Second | L53: N/A | M53: N/A | N53: N/A | O53: EI | P53: Normal Surface Operations | Q53: ENC / RML | R53: ASG | S53: IOSD | T53: N/A - Community | U53: KTA | V53: Near Basketball Court / Bridge | W53: N/A | X53: N/A - Emergency Incident | Y53: N/A | Z53: N/A | AA53: N/A
A54: MARCH, 2026 | B54: Surface | C54: FOREST FIRE | D54: N/A - EI | E54: Forest Fire | F54: Fire | G54: LMD Morgue Area | H54: S (N/A) | I54: March 31, 2026 | J54: 0.7375 | K54: Third | L54: N/A | M54: N/A | N54: N/A | O54: EI | P54: Normal Surface Operations | Q54: ENC / RML | R54: ASG | S54: IOSD | T54: N/A - Community | U54: KTA | V54: Below LMD Morgue Area | W54: N/A | X54: N/A - Emergency Incident | Y54: N/A | Z54: N/A | AA54: N/A
A55: APRIL, 2026 | B55: Surface | C55: FOREST FIRE | D55: N/A - EI | E55: Forest Fire | F55: Fire | G55: Golf Course, Sapid | H55: S (N/A) | I55: April 1, 2026 | J55: 0.88888889 | K55: Third | L55: N/A | M55: N/A | N55: N/A | O55: EI | P55: Normal Surface Operations | Q55: N/A | R55: ASG | S55: IOSD | T55: N/A - Community | U55: KTA | V55: Beside Golf Club Hanging Bridge | W55: N/A | X55: N/A - Emergency Incident | Y55: N/A | Z55: N/A | AA55: N/A
A56: APRIL, 2026 | B56: Surface | C56: FOREST FIRE | D56: N/A - EI | E56: Forest Fire | F56: Fire | G56: Golf Course, Sapid | H56: S (N/A) | I56: April 4, 2026 | J56: 0.52291667 | K56: Second | L56: N/A | M56: N/A | N56: N/A | O56: EI | P56: Normal Surface Operations | Q56: MBK | R56: ASG | S56: IOSD | T56: N/A - Community | U56: KTA | V56: Beside Golf Club | W56: N/A | X56: N/A - Emergency Incident | Y56: N/A | Z56: N/A | AA56: N/A
A57: APRIL, 2026 | B57: Surface | C57: FOREST FIRE | D57: N/A - EI | E57: Forest Fire | F57: Fire | G57: Casubigan / Marivic Area | H57: S (N/A) | I57: April 7, 2026 | J57: 0.39652778 | K57: Second | L57: N/A | M57: N/A | N57: N/A | O57: EI | P57: Normal Surface Operations | Q57: RML / MBK | R57: ASG | S57: IOSD | T57: N/A - Community | U57: KTA | V57: Pathway Shortcut Going to Marivic, Near Waiting Shed | W57: N/A | X57: N/A - Emergency Incident | Y57: N/A | Z57: N/A | AA57: N/A
A58: APRIL, 2026 | B58: Surface | C58: FOREST FIRE | D58: N/A - EI | E58: Forest Fire | F58: Fire | G58: Tamangan Area, Lime 2 | H58: S (N/A) | I58: April 8, 2026 | J58: 0.46180556 | K58: Second | L58: N/A | M58: N/A | N58: N/A | O58: EI | P58: Normal Surface Operations | Q58: RML / MBK | R58: ASG | S58: IOSD | T58: N/A - Community | U58: KTA | V58: Temporary Storage Area | W58: N/A | X58: N/A - Emergency Incident | Y58: N/A | Z58: N/A | AA58: N/A
A59: APRIL, 2026 | B59: Surface | C59: FOREST FIRE | D59: N/A - EI | E59: Forest Fire | F59: Fire | G59: San Antonio Area | H59: S (N/A) | I59: April 9, 2026 | J59: 0.46666667 | K59: Second | L59: N/A | M59: N/A | N59: N/A | O59: EI | P59: Normal Surface Operations | Q59: ENC | R59: ASG | S59: IOSD | T59: N/A - Community | U59: KTA | V59: Near Tank 10 | W59: N/A | X59: N/A - Emergency Incident | Y59: N/A | Z59: N/A | AA59: N/A
A60: APRIL, 2026 | B60: Surface | C60: FOREST FIRE | D60: N/A - EI | E60: Forest Fire | F60: Fire | G60: TP3 Dam Area | H60: S (N/A) | I60: April 17, 2026 | J60: 0.68888889 | K60: Third | L60: N/A | M60: N/A | N60: N/A | O60: EI | P60: Normal Surface Operations | Q60: N/A | R60: ASG | S60: IOSD | T60: N/A - Community | U60: KTA | V60: N/A | W60: N/A | X60: N/A - Emergency Incident | Y60: N/A | Z60: N/A | AA60: N/A
A61: APRIL, 2026 | B61: Surface | C61: FOREST FIRE | D61: N/A - EI | E61: Forest Fire | F61: Fire | G61: Sapid Crusher | H61: S (N/A) | I61: April 17, 2026 | J61: 0.81111111 | K61: Third | L61: N/A | M61: N/A | N61: N/A | O61: EI | P61: Normal Surface Operations | Q61: N/A | R61: ASG | S61: IOSD | T61: N/A - Community | U61: KTA | V61: Old Crusher, Golf Course | W61: N/A | X61: N/A - Emergency Incident | Y61: N/A | Z61: N/A | AA61: N/A
A62: APRIL, 2026 | B62: Surface | C62: FOREST FIRE | D62: N/A - EI | E62: Forest Fire | F62: Fire | G62: Gate 1, Panad | H62: S (N/A) | I62: April 19, 2026 | J62: 0.70694444 | K62: Third | L62: N/A | M62: N/A | N62: N/A | O62: EI | P62: Normal Surface Operations | Q62: N/A | R62: ASG | S62: IOSD | T62: N/A - Community | U62: KTA | V62: Gate 1 Shortcut to Casubigan, Marivic | W62: N/A | X62: N/A - Emergency Incident | Y62: N/A | Z62: N/A | AA62: N/A
A63: APRIL, 2026 | B63: Underground | C63: LUCKY F. GERONILLA | D63: 9927 | E63: Grade Application Analyst | F63: Occupational Illness / Pain | G63: Nayak Mine Office Compound | H63: S (N/A) | I63: 46113 | J63: 0.29513889 | K63: Second | L63: Kurt Linis Ljomir Ursua | M63: Keziah C. Chamollog | N63: Mark D. Banasan | O63: OI | P63: Outgoing : Running in an attempt to ride the bus. | Q63: AOV / MAT / WDL | R63: MEGG | S63: Mine Geology | T63: Mine Resource and Ore Reserves | U63: KTA | V63: In front of Mine Office | W63: KLLU / KCC / MDB | X63: MEGG - Mine Geology | Y63: Left Knee Strain; Left Shoulder Abrasion | Z63: Celecoxib 200mg cap, Elastic Bandage Placed on left knee | AA63: Rest affected knee, pain meds as needed. Follow up if with persistense of pain; otherwise, Fit to Work
A64: APRIL, 2026 | B64: Underground | C64: RUBEN C. MIANA | D64: 7241 | E64: Locomotive Optr. / Helper | F64: Occupational Illness / Pain | G64: Mainline / Access | H64: 900L | I64: 46116 | J64: 0.75 | K64: Third | L64: Jayson T. Capia-ao | M64: Randolf O. Anongos | N64: Silvestre L. Miguel | O64: OI | P64: Cutting of trabessa along 6KB | Q64: ENC / WLT / FPP | R64: MOG | S64: GMS | T64: Main Haulage / Drift & Track Maintenance | U64: KTA | V64: 6KB 900L Mainline | W64: JTC / ROA / SLM | X64: MOG - GMS - Drift and Track Maintenance | Y64: Community Acquired Pneumonia; Bronchitis, Pulmonary TB | Z64: Admitted | AA64: To complete 2 weeks of Anti-Koch's Theraphy
A65: APRIL, 2026 | B65: Underground | C65: BAGNI G. DOMONGIT | D65: 1133 | E65: QA/QC Aide | F65: Occupational Illness / Pain | G65: Stope | H65: 900L | I65: 46120 | J65: 0.38888889 | K65: Second | L65: Kurt Linis Ljomir Ursua | M65: Bullet P. Tangcalagan | N65: Sandro Daniel G. Cababa | O65: OI | P65: To conduct sampling activity along Section 1 | Q65: AOV / MAT | R65: MEGG | S65: Mine Geology | T65: Mine Geology Operations | U65: KTA | V65: 249 Area | W65: KLLU / BPT / SDGC | X65: MEGG - Mine Geology | Y65: Migraine Headache | Z65: Pain Control, Hydration | AA65: Admitted
A66: APRIL, 2026 | B66: Underground | C66: GASPAR T. BANGGUIYAO JR. | D66: 7081 | E66: Maintenance Man (MMME) | F66: Struck by Falling Rock | G66: Rock Drill Shop | H66: 1150L | I66: 46120 | J66: 0.66180556 | K66: Third | L66: Fernando A. Bustillo Jr. | M66: Alfon B. Yodong | N66: Arthur M. Padica | O66: FAC | P66: Manual handling of an LHD tire | Q66: JAW | R66: MOG | S66: MMME | T66: Mobile | U66: KTA | V66: 1150 Rock Drill Shop | W66: FABJr. / ABY / AMP | X66: MOG - MMME - Mobile | Y66: Fracture Digital Phalanges 2nd Digit Right Hand | Z66: For Debridement | AA66: Fit to Work
A67: APRIL, 2026 | B67: Underground | C67: FELIPE A. DIWAG | D67: 1942 | E67: Locomotive Optr. / Helper | F67: Struck by Object | G67: Mainline / Access | H67: 900L | I67: 46124 | J67: 0.17361111 | K67: First | L67: Jayson T. Capia-ao | M67: Randolf O. Anongos | N67: Antonio D. Siyao | O67: FAC | P67: Traversing the access of 900L while operating the Locomotive | Q67: FPP | R67: MOG | S67: GMS | T67: Main Haulage / Drift & Track Maintenance | U67: KTA | V67: 745 Tubo switch point | W67: JTC / ROA / ADS | X67: MOG - GMS - Drift and Track Maintenance | Y67: Contusion Hematoma; Abrasion Right Periorbital Area | Z67: "Treated" according to Hospital Records | AA67: Fit to Work
A68: APRIL, 2026 | B68: Underground | C68: LEONITO PEROLINO | D68: N/A - Contracts | E68: Drill Helper / Drilling Aide | F68: Struck by Object | G68: Cuddy | H68: 800L | I68: 46126 | J68: 0.44444444 | K68: Second | L68: DDCP - A.R. Domalsin | M68: N/A | N68: DDCP - Allan Kitma | O68: FAC | P68: Jarring and pulling out of rods | Q68: AOV / MAT / JAW / SAU / WLT | R68: Contracts | S68: DDCP | T68: Section 6 | U68: KTA | V68: 800 ME-2 CUDDY | W68: Contracts - DDCP | X68: Contracts - DDCP | Y68: Lacerated Wound, Left Elbow | Z68: N/A | AA68: N/A
A69: APRIL, 2026 | B69: Underground | C69: JERON P. MEDRANO | D69: 8486 | E69: Assistant Miner | F69: Occupational Illness / Pain | G69: Mainline / Access | H69: 970L | I69: 46133 | J69: 0.42708333 | K69: Second | L69: Venancio A. Bad-ay | M69: Mariel T. Ayong | N69: N/A | O69: OI | P69: Barring Down | Q69: AOV / MAT / WDL | R69: MOG | S69: Dept. 1 | T69: Section 2 | U69: KTA | V69: 24048 Access | W69: VAB / MTA / - | X69: MOG - 1: Section 2 | Y69: T/C Electrolyte Imbalance | Z69: Admitted for hydration
A70: APRIL, 2026 | B70: Underground | C70: JOSEPH A. BANTIYAG | D70: 1171 | E70: Lead Miner | F70: Struck by Falling Rock | G70: Mainline / Access | H70: 1150L | I70: 46134 | J70: 0.0625 | K70: First | L70: Hilbert G. Andong | M70: Allab B. Lal-wet | N70: Wincy C. Awingan | O70: FAC | P70: Blast Holes Driiling | Q70: JAW / SAU | R70: MOG | S70: Dept. 2 | T70: Section 4 | U70: KTA | V70: 320 B Ramp 1150L | W70: HGA / ABL / - | X70: MOG - 2: Section 4 | Y70: Abrasion, Lacerated Wound, Left Leg | Z70: ATS/TT, Wound Suturing | AA70: May go on light job, provided wound will not be soiled. Otherwise, for further medical evaluation until wound has dried and healed
A71: APRIL, 2026 | B71: Underground | C71: EDWARD P. DAPIDAP | D71: 7665 | E71: Locomotive Optr. / Helper | F71: Fall on Same Level | G71: Old Traffic Area / Junction | H71: 900L | I71: April 4, 2026 | J71: 0.0625 | K71: First | L71: Jayson T. Capia-ao | M71: Randolf O. Anongos | N71: N/A | O71: FAC | P71: Hand Mucking | Q71: N/A | R71: MOG | S71: GMS | T71: Main Haulage / Drift & Track Maintenance | U71: KTA | V71: Tubo, Old Traffic Area | W71: JTC / ROA / - | X71: MOG - GMS - Drift and Track Maintenance | Y71: Punctured, Left Forearm | Z71: Wound care; Amoxicilin 500mg/tab, 1 tab TID PO x 7 days. Paracetamol 500mg/tab 1 tab Q^H PRN for Pain/Fever | AA71: Fit to Work | AB71: Inadequate Housekeeping | AD71: Hazardous Environment Conditions
A72: APRIL, 2026 | B72: Surface | C72: JOHN WAYNE L. TUDLONG; JAY-AR B. BANASAN | D72: 8627; 0063 | E72: Mill Mechanical Fitter | F72: Caught on | G72: Crushing Area | H72: S (N/A) | I72: April 6, 2026 | J72: 0.4375 | K72: Second | L72: Abraham L. Davis | M72: Julius K. Finatec | N72: N/A | O72: NM | P72: Hot works: Welding at Crushing area | Q72: RML / MBK | R72: MPG | S72: Mill Engineering | T72: Mill Projects | U72: KTA | V72: =G72 -> Crushing Area | W72: ALD / JKF / - | X72: MPG - Mill Engineering | Y72: N/A | Z72: N/A | AA72: N/A | AB72: Failure to Warn | AC72: Inadequate Physical Physiological Capability: Vision deficiency | AD72: Congestion / Restricted Action | AE72: Inadequate Engineering: Inadequate consideration of human factors / ergonomics, Inadequate minotoring / initial operation
A73: APRIL, 2026 | B73: Surface | C73: HOLDING MOTOR OF THE P&H CRANE #1 | D73: N/A - PD | E73: Lifting Equipment | F73: Over-Excertion in Pushing / Pulling Objects | G73: Lower Tram | H73: S (N/A) | I73: April 27, 2026 | J73: 0.020833333 | K73: First | L73: Dexter B. Arevalo | M73: Christopher T. Baniaga | N73: Ernie S. Ringor | O73: PD | P73: Crane in operation | Q73: MBK | R73: MPG | S73: Mill Operations | T73: Sand Production | U73: KTA | V73: =G73 -> Lower Tram | W73: DBA / CTB / ESR | X73: MPG - Mill Operations - Sand Production
A74: APRIL, 2026 | B74: Surface | C74: FOREST FIRE | D74: N/A - EI | E74: Forest Fire | F74: Fire | G74: Panad Roadway, Poblacion | H74: S (N/A) | I74: April 27, 2026 | J74: 0.47638889 | K74: Second | L74: N/A | M74: N/A | N74: N/A | O74: EI | P74: Normal Surface Operations | Q74: N/A | R74: ASG | S74: IOSD | T74: N/A - Community | U74: KTA | V74: Panad, Near Rotunda | W74: N/A | X74: N/A - Emergency Incident | Y74: N/A | Z74: N/A | AA74: N/A
A75: APRIL, 2026 | B75: Surface | C75: SLURRY SPILL | D75: N/A - EI | E75: Leach Tank | F75: Environmental Incident - Chemical Spill | G75: CIP | H75: S (N/A) | I75: April 21, 2026 | J75: 0.46597222 | K75: Second | L75: Dexter B. Arevalo | M75: Jeah B. Taguran | N75: Tofer T. Padsoyan | O75: EI | P75: Normal Surface Operations | Q75: MBK / RML | R75: MPG | S75: Mill Operations | T75: CIP | U75: KTA | V75: Leach Tank Area | W75: DBA / JBT / TTP | X75: MPG - Mill Operations - CIP | Y75: N/A | Z75: N/A | AA75: N/A
A76: APRIL, 2026 | B76: Surface | C76: SANDY A. SAD-AYAN | D76: 9954 | E76: Mill Mechanical Fitter | F76: Fall on Same Level | G76: Boiler Room Extension | H76: S (N/A) | I76: April 28, 2026 | J76: 0.44444444 | K76: Second | L76: Abraham L. Davis | M76: Julius K. Finatec | N76: N/A | O76: LTA-NF | P76: Window panel installation | Q76: ENC / RML | R76: MPG | S76: Mill Engineering | T76: Mill Projects | U76: KTA | V76: =G76 -> Boiler Room Extension | W76: ALD / JKF / - | X76: MPG - Mill Engineering | Y76: Impacted fracture, distal radius left wrist | Z76: Closed reduction, Long arm Circular cast left | AA76: Week 0-4: Immobilization with long arm circular cast Week 5-6: Convert to short arm circular cast Week 7-8: Physical Theraphy | AB76: Inadequate Housekeeping | AC76: Inadequate identification and evaluation of loss exposure
A77: MAY, 2026 | B77: Surface | C77: LUMADAO, JUNE MARK S. | D77: 303 | E77: Maintenance Man (PCES) | F77: Fall on Same Level | G77: Golf Course, Sapid | H77: S (N/A) | I77: May 8, 2026 | J77: 0.55902778 | K77: Second | L77: Abraham L. Davis | M77: Dember F. Dictaan Jr. | N77: N/A | O77: FAC | P77: Loading of excavated soil at the service dump truck | Q77: MBK / RML | R77: MPG | S77: PCES | T77: Road & Camp Maintenance | U77: KTA | V77: Golf Course Road | W77: ALD / DBDJr. / - | X77: MPG - PCES - Road & Camp Maint. | Y77: Soft Tissue cintusion right lumbar | Z77: X-Ray and Pain Reliever | AA77: Fit to Work | AB77: Failure to Warn, Failure to Secure Personal Safety | AC77: - | AD77: N/A | AE77: N/A
A78: MAY, 2026 | B78: Surface | C78: SACPA, JEROUS CAD-AN | D78: 1095 | E78: Mill Operations Aide | F78: Caught on | G78: Crushing Area | H78: S (N/A) | I78: May 12, 2026 | J78: 0.30902778 | K78: Second | L78: Dexter B. Arevalo | M78: Wendel D. Balag-ey | N78: N/A | O78: LTA-NF | P78: Scraping material build-up | Q78: MBK / RML | R78: MPG | S78: Mill Operations | T78: Crushing & Grinding | U78: KTA | V78: Mill Crushing Conveyor 5A | W78: DBA / WDB / - | X78: MPG - Mill Operations - Crushing & Grinding | Y78: Complete transection 3rd extensor distorsion tendon, right hand secondary to entanglement injury | Z78: Wound exploration, wound suturing, tendon repair, x-rays ATS, TT, & Ketorolac given | AA78: Week 0-4: Protection Phase Week 4-8: Splint weaning, Light Exercise Week 8-12: Strengthening | AB78: Failure to Secure Personal Safety; Servicing Equipment in Operation; Lack of SOP dissemination | AC78: - | AD78: Inadequate Guards / Barriers; Inadequate Warning system (signages, signals)
A79: MAY, 2026 | B79: Surface | C79: BAUTISTA, LEO V. II | D79: 8477 | E79: Jr. Mechanic | F79: Eye Contact with Foreign Object | G79: Machine Shop | H79: S (N/A) | I79: May 15, 2026 | J79: 0.36111111 | K79: Second | L79: Larry A. Arigue | M79: James I. Consolacion | N79: Kristian Lloyd D. Bulay | O79: FAC | P79: Grooving operations on pipes | Q79: ENC / RML | R79: MOG | S79: MWSO | T79: Machine Shop | U79: KTA | V79: =G79 -> Machine Shop | W79: LEA / JIC / KLDB | X79: MOG - MWSO - Machine Shop | Y79: Traumatic Conjunctivitis | Z79: Eye Irrigation | AA79: Advised Ophtha Consult | AB79: Failure to Secure Personal Safety; Improper position for task; Lack of Hazard Assessment | AC79: - | AD79: Inadequate / Improper protective Equipment | AE79: Inadequate tools & equipment
A80: MAY, 2026 | B80: Surface | C80: FOREST FIRE | D80: N/A | E80: N/A | F80: Fire | G80: Pukitan Area | H80: S (N/A) | I80: May 16, 2026 | J80: 0.74583333 | K80: Third | L80: N/A | M80: N/A | N80: N/A | O80: EI | P80: Normal Surface Operations | Q80: N/A | R80: ASG | S80: IOSD | T80: N/A - Community | U80: KTA | V80: Pukitan, Below Tamayo residence | W80: N/A | X80: N/A - Emergency Incident | Y80: N/A | Z80: N/A | AA80: N/A
A81: MAY, 2026 | B81: Surface | C81: REX KEVIN B. DAO-AS | D81: 3717 | E81: Heavy Equipment Operator | F81: Occupational Illness / Pain | G81: On the road | H81: S (N/A) | I81: May 20, 2026 | J81: 0.47916667 | K81: Second | L81: Larry A. Arigue | M81: Melno S. Palayen | N81: Raul S. Visperas | O81: OI | P81: Registration of assigned vehicle | Q81: ENC / RML | R81: MOG | S81: MWSO | T81: Motorpool / Transport | U81: KTA | V81: Bontoc Roadway | W81: LEA / MSP / RSV | X81: MOG - MWSO - Motorpool | Y81: Supraventricular Tachycardia, S/P Medical Conversion; HPN Stage II; Hyperthyroidism | Z81: Admitted at Bontoc General Hospital | AA81: For 2d Echo | AB81: Failure to secure personal Safety | AC81: Physical / Physiological Stress | AD81: Temperature Extremes | AE81: N/A
A82: MAY, 2026 | B82: Surface | C82: CATBAGAN, NARRY D. | D82: 4095 | E82: CIP Operator | F82: Contact with Object | G82: CIP - Barren Pump Area | H82: S (N/A) | I82: May 23, 2026 | J82: 0.40625 | K82: Second | L82: Dexter B. Arevalo | M82: Jeric T. Dulawan | N82: John Ray T. Salguit | O82: FAC | P82: Transferring operation of Barren pump 1 to 2 | Q82: RML | R82: MPG | S82: Mill Operations | T82: CIP | U82: KTA | V82: Barren pump area | W82: DBA / JTD / JRTS | X82: MPG - Mill Operations - CIP | Y82: Chemical Burn (RLQ Abdomen) R/O Cyanide Toxicity | Z82: Decontamination, Wound Care & Oral Medication, Admitted for observation and Monitoring | AA82: For observation & monitoring | AB82: Failure to use PPE Properly | AC82: Lack of Knowledge | AD82: Defective tools / Equipment materials; Temperature Extremes | AE82: Inadequate Maintenenace; Inadequate Tools & Equipment
A83: MAY, 2026 | B83: Surface | C83: GISGISWANG, RUEL R. | D83: 4135 | E83: Grinding Operator | F83: Contact with Object | G83: CIP - Barren Pump Area | H83: S (N/A) | I83: May 23, 2026 | J83: 0.40625 | K83: Second | L83: Dexter B. Arevalo | M83: Jeric T. Dulawan | N83: John Ray T. Salguit | O83: FAC | P83: Transferring operation of Barren pump 1 to 2 | Q83: RML | R83: MPG | S83: Mill Operations | T83: Crushing & Grinding | U83: KTA | V83: Barren pump area | W83: DBA / JTD / JRTS | X83: MPG - Mill Operations - Crushing & Grinding | Y83: Chemical Burn (Left Forearm) R/O Cyanide Toxicity | Z83: Decontamination, Wound Care & Oral Medication, Admitted for observation and Monitoring | AA83: For observation & monitoring | AB83: Failure to use PPE Properly | AC83: Lack of Knowledge | AD83: Defective tools / Equipment materials; Temperature Extremes | AE83: Inadequate Maintenenace; Inadequate Tools & Equipment
A84: MAY, 2026 | B84: Underground | C84: BADOL, EUSEBIO G. | D84: 8465 | E84: Assistant Miner | F84: Struck by object | G84: Stope | H84: 850L | I84: 46150 | J84: 0.78125 | K84: Third | L84: Venancio A. Bad-ay | M84: Dimas S. Gao-ay | N84: Regie D. Espinosa | O84: FAC | P84: Pulling of RDM prior to rock bolting | Q84: FPP/RWV | R84: MOG | S84: Dept. 1 | T84: Section 1 | U84: MAT | V84: 24802 SPLIT #1 | W84: VAB / DSG / RDE | X84: MOG - 1: Section 1 | Y84: Lacerated Wound Lower Lip Secondary to industrial injury | Z84: Wound Suturing, Antibiotics, Tetanus Injection | AA84: Healing period of seven (7) days prior to assessment but can attend to light works | AB84: Failure to secure personal safety | AC84: Inadequate mental / psychological capability | AD84: Congestion / Restricted Action | AE84: Inadequate Work standards and / or risk assessment
A85: MAY, 2026 | B85: Underground | C85: OSSOG, ANDRE MARK A. | D85: 8483 | E85: Assistant Miner | F85: Caught in between | G85: Shaft Station / Resting Area | H85: 1150L | I85: 46151 | J85: 0.61527778 | K85: Third | L85: Hilbert G. Andong | M85: Ruben T. Saliwey | N85: Reynaldo C. Agno | O85: FAC | P85: Transport of LHD tires to Mancage at 1150 Shaft | Q85: FPP | R85: MOG | S85: Dept. 2 | T85: Section 5 | U85: MAT | V85: 1150 Shaft Station | W85: HGA / RTS / RCA | X85: MOG - 2: Section 5 | Y85: Avulsed wound 1st digit left hand secondary to industrial injury | Z85: Wound suturing, wound dressing, debridement and nail excision / X-ray, ATS, TT & Ketorolac Given | AA85: May go back to work provided the wound does not get infected | AB85: Failure to secure personal safety; Improper position for task; | AC85: Inadequate mental / psychological capability | AD85: Congestion / Restricted Action | AE85: Inadequate Leadership and / or Supervision; Inadequate Work standards and / or risk assessment
A86: MAY, 2026 | B86: Underground | C86: GUMAAD, EDMUND T. | D86: 9844 | E86: Ventilation Installation Man | F86: Struck by object | G86: Stope | H86: 1150L | I86: 46155 | J86: 0.39583333 | K86: Second | L86: Richard C. Ducusin | M86: Francis E. Mabunga | N86: Eufrosino A. De Leon Jr. | O86: FAC | P86: Cutting of vent tube cord | Q86: MAT/AOV | R86: MEGG | S86: Mine Ventilation | U86: MAT | V86: 1081 A32N, Sect. 4, Teresa | W86: RCD / FEM / EADJr. | X86: MEGG - Mine Ventilation | Y86: Lacerated wound, Palmar Surface, Left Hand | Z86: Wound Suturing, ATS / TT | AA86: Recommended for light works for seven (7) days, provided wound will not be soiled. Sutures will be removed after. Follow-up the next day. | AB86: Improper position for task | AC86: Inadequate physical Physiological Capability | AD86: Inadequate or Improper protective equipment; Congestion / Restricted Action | AE86: Inadequate Tools & Equipment
A87: MAY, 2026 | B87: Underground | C87: REFUGIA, JOHN PAULINE M. | D87: 8787 | E87: PMS Foreman (Acting) | F87: Caught in between | G87: Repair Bay | H87: 900L | I87: 46160 | J87: 0.41666667 | K87: Second | L87: Fernando A. Bustillo Jr. | M87: N/A | N87: N/A | O87: LTA-NF | P87: Attempting to install the timber support to theLHD boom | Q87: MAT/AOV/WLT | R87: MOG | S87: MMME | T87: Mobile | U87: MAT | V87: 249 Repair Bay | W87: FABJr. / - / - | X87: MOG - MMME - Mobile | Y87: Crushing injury 1st digit left hand | Z87: Wound exploration, Wound closure, X-Ray, Admitted | AA87: For further medical evaluation | AB87: Failure to secure personal safety; Improper position for task | AC87: Inadequate mental / psychological capability | AD87: Congestion / Restricted Action | AE87: Inadequate Engineering
A88: MAY, 2026 | B88: Underground | C88: SORIANO W. PALAT | D88: 8632 | E88: Mine Services Aide | F88: Occupational Illness / Pain | G88: Mainline / Access | H88: 900L | I88: 46160 | J88: 0.47916667 | K88: Second | L88: Jayson T. Capia-ao | M88: Randolf O. Anongos | N88: N/A | O88: OI | P88: Transit of Ore to UG Crusher | Q88: MAT/AOV/WLT | R88: MOG | S88: GMS | T88: Main Haulage / Drift & Track Maintenance | U88: MAT | V88: Carmen Mainline | W88: JTC / ROA / - | X88: MOG - GMS - Drift and Track Maintenance | Y88: Cramps Secondary to Electrolyte Imbalance | Z88: Admitted | AA88: For further medical evelaution | AB88: Failure to secure personal Safety | AC88: Physical / Physiological Stress | AD88: Temperature Extremes | AE88: Inadequate Work standards and / or risk assessment
A89: MAY, 2026 | B89: Underground | C89: RAUL S. GALDOC | D89: 1425 | E89: Lead Miner | F89: Struck by Falling Rock | G89: Stope | H89: 870L | I89: 46160 | J89: 0.64583333 | K89: Second | L89: Venancio A. Bad-ay | M89: Dimas S. Gao-ay | N89: Regie D. Espinosa | O89: FAC | P89: Mucking Activity | Q89: MAT/AOV/WLT | R89: MOG | S89: Dept. 1 | T89: Section 1 | U89: MAT | V89: 2490 8M1 | W89: VAB / DSG / RDE | X89: MOG - 1: Section 1 | Y89: Laceration right hand | Z89: Wound suturing, wound dressing, X-Ray | AA89: Recommended for light works for seven (7) to 14 days, provided the wound does not get infected. | AB89: Failure to secure personal Safety | AC89: Inadequate mental / psychological capability | AD89: Hazardous Environment Conditions | AE89: Inadequate Work standards and / or risk assessment
A90: MAY, 2026 | B90: Underground | C90: JORDAN JAMES W. BAGUISTA | D90: 1207 | E90: LHD Optr | F90: Struck by Falling Rock | G90: Stope | H90: 870L | I90: 46160 | J90: 0.8125 | K90: Third | L90: Venancio A. Bad-ay | M90: Dimas S. Gao-ay | N90: Efren L. Mangamti | O90: FAC | P90: Mucking Activity | Q90: MAT/AOV/WLT | R90: MOG | S90: Dept. 1 | T90: Section 1 | U90: MAT | V90: 2490 8M1 | W90: VAB / DSG / ELM | X90: MOG - 1: Section 1 | Y90: Laceration right leg, right knee | Z90: Wound suturing, wound dressing, X-Ray, and Ketorolac given | AA90: Recommended for light works for seven (7) to 14 days, provided the wound does not get infected. | AB90: Failure to secure personal Safety | AC90: Inadequate mental / psychological capability | AD90: Hazardous Environment Conditions | AE90: Inadequate Work standards and / or risk assessment
A91: MAY, 2026 | B91: Surface | C91: SUNI, RONALD S. | D91: 7023 | E91: Sand Production Operator | F91: Caught in Between | G91: Upper Tram | H91: S (N/A) | I91: May 26, 2026 | J91: 0.42361111 | K91: Second | L91: Dexter B. Arevalo | M91: Christopher T. Baniaga | N91: Vincent S. Camiling | O91: LTA-NF | P91: Reinstalling detached cable | Q91: MBK / RML | R91: MPG | S91: Mill Operations | T91: Sand Production | U91: KTA | V91: Upper Tram Slusher Bin | W91: DBA / CTB / VSC | X91: MPG - Mill Operations - Sand Production
A92: MAY, 2026 | B92: Surface | C92: RUFINO, ALVIN | D92: 8354 | E92: Jr. Mechanical Engineer | F92: Fall on Same Level | G92: Poblacion, Mankayan | H92: S (N/A) | I92: May 6, 2026 | J92: 0.28819444 | K92: First | L92: Larry E. Arigue | M92: James I. Consolacion | N92: N/A | O92: FAC | P92: Riding Motorcycle to work | Q92: MBK / RML | R92: MOG | S92: MWSO | T92: Machine Shop | U92: KTA | V92: Guiwe, Poblacion Mankayan | W92: LEA / JIC / - | X92: MOG - MWSO - Machine Shop | Y92: Multiple Abrasion secondary to vehicular crash | Z92: Wound Care, X-Ray | AA92: For Sick Leave | AB92: N/A | AC92: N/A | AD92: Poorly Maintained Haul Roads (Stray Dogs) | AE92: Inadequate Leadership / Supervision
A93: JUNE, 2026 | B93: Underground | C93: LUMASOK, JOHANNAH SHAYNE T. | D93: STUDENT | E93: OJT | F93: Occupational Illness / Pain | G93: Hoist Room | H93: 1150L | I93: June 2, 2026 | J93: 0.44444444 | K93: Second | L93: Nelson L. Baguya II | M93: Jet Lee V. Chinanglas | N93: Clinton O. Lingyasan | O93: OI | P93: Mine tour: Discussion at Hoist Room 1150L | Q93: MAT/AOV/RWV | R93: ASG | S93: Human Resources | T93: HR-Training | U93: MAT | V93: 1150L Hoist Room | W93: NLBII / JLVC / COL | X93: ASG - HR - Training | AB93: Failure to secure personal safety | AD93: Temperature extremes (extreme heat/cold)
A94: JUNE, 2026 | B94: Underground | C94: GAMMONG, ROLLY B. | D94: 818 | E94: Lead Miner | F94: Caught in Between | G94: Stope | H94: 850L | I94: 46186 | J94: 0.013888889 | K94: First | L94: Venancio A. Bad-ay | M94: Dimas S. Gao-ay | N94: Ryan M. Macaburas | O94: FAC | P94: Barring Down | Q94: FPP | R94: MOG | S94: Dept. 1 | T94: Section 1 | U94: MAT | V94: 2487 8M2 | W94: VAB / DSG / RMM | X94: MOG - 1: Section 1 | Y94: Lacerated Wound Left Foot, Chip Fracture 4th Metatarsal Bone Left, Secondary to Rockfall | Z94: Wound Suturing, Wound Dressing, X-Ray, ATS, TT | AA94: Fit to Work | AB94: Failure to secure personal safety | AD94: Congestion or restricted action
A95: JUNE, 2026 | B95: Underground | C95: LUGAO, KYLE RUSSEL T | D95: 8473 | E95: Assistant Miner | F95: Over-Exertion in Lifting Objects | G95: Stope | H95: 870L | I95: 46189 | J95: 0.37847222 | K95: Second | L95: Venancio A. Bad-ay | M95: Dimas S. Gao-ay | N95: N/A | O95: FAC | P95: Preaparation of tools and equipment prior for Rock Bolting | Q95: MAT/AOV/SAU | R95: MOG | S95: Dept. 1 | T95: Section 1 | U95: MAT | V95: 2490 8M2 | W95: VAB / DSG / - | X95: MOG - 1: Section 1 | Y95: Lumbosacral Strain | Z95: LSV X-Ray, Analgesics | AA95: Rest for 1-2 days | AB95: Improper position for task | AD95: Congestion or restricted action
A96: JUNE, 2026 | B96: Underground | C96: OMERAG, FRIELAND F. | D96: 7235 | E96: Jr. Maintenance Man | F96: Contact with Object | G96: Repair Bay | H96: 1150L | I96: 46193 | J96: 0.14583333 | K96: First | L96: Fernando A. Bustillo Jr. | M96: Alfon B. Yodong | N96: Paterno B. Basingan | O96: FAC | P96: Cutting of LHD Canopy | Q96: MAT/AOV | R96: MOG | S96: MMME | T96: Mobile | U96: MAT | V96: 1150L Repair Bay | W96: FABJr. / ABY / PBB | X96: MOG - MMME - Mobile | Y96: Cellulitis Right Foot, Secondary to Burn | Z96: IV Antibiotics, Analgesics | AA96: Admitted | AB96: Failure to secure personal safety | AD96: Inadequate or improper protective equipment
A97: JUNE, 2026 | B97: Surface | C97: ESCAYO, BENCIO W. | D97: 301 | E97: UG Crusher Operator | F97: Struck by Object | G97: UG Crusher | H97: 900L | I97: 46181 | J97: 0 | K97: First | L97: Jayson T. Capia-ao | M97: Jenipher B. Rosito | N97: Reynaldo C. Agno | O97: FAC | P97: Blasting big boulder | Q97: ENC | R97: MOG | S97: GMS | T97: Underground Crusher | U97: RML | V97: UG Crusher | W97: JTC / JBP / RCA | X97: MOG - GMS - Underground Crusher | Y97: No Diagnosis | Z97: Wound Care | AA97: Fit to Work | AB97: Improper position for task | AC97: Lack of Knowledge | AD97: Congestion / Restricted Action | AE97: Inadequate Work standards and / or risk assessment
A98: JUNE, 2026 | B98: Surface | C98: GALAO, MARK ANTHONY J. | D98: 9580 | E98: Mill Mechanical Fitter | F98: Struck by Object | G98: CIP - Refinery | H98: S (N/A) | I98: 46182 | J98: 0.70833333 | K98: Third | L98: Kay B. Lacambra | M98: Ernesto L. Locaben Jr. | N98: Ranel R. Narciso | O98: FAC | P98: Tightening of bolts | Q98: MBK | R98: MPG | S98: Mill Mechanical | T98: Refinery | U98: RML | V98: Elution Column 1 3rd Floor | W98: KBL / ELLJr. / RRN | X98: MPG - Mill Operations - Refinery | Y98: No Diagnosis | Z98: Wound Suturing, Anti Tetanus and Anti Biotic Prophylaxis, X-ray | AA98: Fit to Work | AB98: Improper position for task | AD98: Inadequate Tools and Equipment
A99: JUNE, 2026 | B99: Surface | C99: WALLIS, MAYNARD | D99: 3107 | E99: Electrician | F99: Contact with Object | G99: La Guerta Area | H99: S (N/A) | I99: 46203 | J99: 0.4375 | K99: Second | L99: Rolando E. Ventura | M99: Darwin S. Coloma | N99: Larry S. Andomang | O99: FAC | P99: Tensioning of cable wire | Q99: RML | R99: TSG | S99: SMED | T99: Surface Electrical | U99: RML | V99: St. Albans Church | W99: REV / DSC / LSA | X99: TSG - SMED - Surface Electrical | Y99: R/O Arrhytmia | Z99: ECG, CBC, Serum Electrolytes, Troponin I, Urinalysis, Creatinine, CBG | AA99: Fit to Work | AB99: N/A | AC99: N/A | AD99: Electrical Cable | AE99: N/A
A100: JUNE, 2026 | B100: Surface | C100: DAO-WOK, KELVIN | D100: 8667 | E100: Jr. Mechanic / Driver | F100: Caught on | G100: Upper Tram | H100: S (N/A) | I100: 46203 | J100: 0.54166667 | K100: Second | L100: Larry E. Arigue | M100: Melno S. Palayen | N100: Raul S. Visperas | O100: NM | P100: Unloading of sandfill | Q100: RML | R100: TSG | S100: MWSO | T100: Motorpool / Transport | U100: RML | V100: Upper Tram | W100: LEA / MSP / RSV | X100: TSG - MWSO - Motorpool | Y100: N/A | Z100: N/A | AA100: N/A | AB100: N/A | AC100: Lack of Knowledge | AD100: N/A | AE100: N/A
...

Sheet Description of Incidents
A1: Brief Description of Incident (s): | B1: 46023
A2: =input!$C$2 -> RYAN DAVE MAWI-IT | B2: Janauary 10, 2026: The victim, together with his companions, was assigned to clean the canal along the drift at the RP. 22 Area. After completing the activity, he took a bath and suddenly felt chills accompanied by shivering. As a result, his on-shift supervisor, Reynaldo P. Kiking, advised him to rest at eating station and immediately called an ambulance for medical check up.
A3: OI
A4: RP NO.22 900L
A5: =input!$C$3 -> JOEY A. LASSIN | B5: January 16, 2026: At approximately 11:00 AM, Messrs. Ladwingon and the victim were assigned to 21516 4M4. Their supervisor, Engr. Fawayan, instructed them to conduct barring down and update ground support (rock bolting) after noticing a five-meter backlog in rock bolting from the previous shift. Messrs. Ladwingon and Lassin began their work, performing barring down and reinstalling the disturbed stull caused by the previous shift’s blasting activity. While conducting the rock bolting operation, the victim was collaring the 18th hole when a loose rock unexpectedly fell from behind, resulting in an abrasion injury to his back.Immediately after the incident, Mr. Ladwingon sought assistance from a nearby LHD operator and reported the injury to their supervisor.
A6: FAC
A7: 21516 4M4, 970L
A8: =input!$C$4 -> MANUEL D. BALAIS | B8: Janauary 24, 2026: The victim did his routine in all working areas, at arround 3:00 am. He returned at 305 Ramp to double check his crew working thereat. The crew were eating their snack so the victim continued breaking the uneven roadway using the breaker. On the process, the air nozzle of the breaker flashes to the ground and a particle hit the left eye of the victim.
A9: FAC
A10: 305 RAMP, 1100L
A11: =input!$C$5 -> WILBUR D. AWIS | B11: Janauary 25, 2026: The victim was at the eating station while preparing to conduct his work when he suddenly felt dizzy. Later on, it was found out that the victim forgot to take his maintenance medicine.
A12: OI
A13: RP NO.22 900L
A14: =input!$C$6 -> DUMAGUING M. LIBAN | B14: On January 26, 2026, LHD operator Mr. Liban descended to the ramp after conducting scraping from the upper elevation. During his descent, a crew noticed him approaching them who were conducting timbering in a section of the Ramp. At approximately 07:30 PM, Mr. Liban engaged the park brake of his loader and subsequently alighted to engage the shut-off valve engine. The loader suddenly moved in a free wheeled and downward the ramp towards the crew timbering crew so he immediately warned the crew nearby. Apparently, he attempted to re- ride in his unit to stop. The crew fled from the area upon hearing the warning of Mr. Liban, few moments later, they already found him unresponsive, lying on his left side and his head was positioned almost underneath of the stepping board of the unit. Rescuers extricated him and was brought to hospital where he already lifeless.
A15: LTA-F
A16: 207 K Ramp, 1012 Elevation, 1000L
A17: =input!$C$7 -> GLENN MARK B. LABOTAN | B17: On January 30, 2026, at approximately 9:45 AM, Messrs. M. Caligner, A. Molano, and A. De Leon were engaged in storing fuel oil drum at the C30 Fuel Storage Area, Mr. Labotan observed the activity and voluntarily offered his assistance. During unloading, the drum was initailly placed in a resting position and subsequently rolled inside the storage area for proper placement. While Mr. Caligner and Mr. labotan were lifting the drum to its rack, the drum suddenly shifted due to its weight. Mr. Labotan was unable to withdraw his hand in time resulting in his fingers being caught in a pich point and sustaining injury. The injured employee was immediately transported to the 1150L shaft station and subsequently conveyed by ambulance to the company hospital for further treatment.
A18: LTA-NF
A19: C30 Fuel Storage
A20: =input!$C$8 -> BINSON I. ZAPARITA | B20: The material of ball mill #1 pinion shaft was already cut off at the power saw. The supervisor of the victim instructed him to assist in unloading the excess material from the machine. The victim measured the center of the shaft and placed the rope. His companion operates the crane while he and his other coworker are supporting at each end of the shaft. The lifting of the material was unbalanced on their first attempt so they adjusted the rope. They lifted the shaft but unfortunately the rope swung which resulted in the injury of the victim. The right ring finger of the victim was caught in between the shaft and the clamping vise.
A21: =input!O8 -> FAC
A22: Machine Shop
A23: =input!C9 -> ROWELL C. DELA CRUZ | B23: Around 7:45 AM of January 12, 2026 the victim and his companions are loading caustic sodas in the steelyard to be delivered at CIP. As they were lifting the caustic sodas, a bunch of sacks tipped over. The victim together with his workmate repiled the bags of caustic sodas. The victim did not realized that a small portion of caustic sodas was spilled into his left shoe. At around past 8:00 AM they delivered the caustic sodas to CIP and returned at the steelyard approximately 9:00 AM. The victim felt stingy on his left foot and reported to his supervisor. He was admitted at the hospital 10:02 AM.
A24: =input!O9 -> FAC
A25: Steel Yard
A26: =input!C10 -> JOHN REY BAGUIYAC | B26: The victim together with his companions were deployed and assigned to repair termite-infested columns and beams at the proposed hemodialysis station of the hospital. The existing columns and beams were scheduled to be replaced with 6x6 H-beams to stabilize area. The crew was instructed that all cutting of H-beams should be performed outside the hospital premises. Due to the large number of hospital clients at the time, the crew decided to haul the H-beams inside the area. During the lowering of the H-beam while counting and coordinating the movement, the victim was delayed in pulling his hand resulting in his hand being caught in between the beam.
A27: =input!O10 -> FAC
A28: =input!V10 -> Proposed Hemodialysis Station
A29: =input!C11 -> FUSE CUT-OFF SWITCH | B29: There was a sudden power loss from the 220V transformer. Control group was called since the jaw crusher was not able to perform with the power loss. Upon inspection the team noticed that the fuse cut-off switch was sparking and producing smoke. The workers quenched the spark with fire extinguisher.
A30: =input!O11 -> PD
A31: =input!V11 -> 300 KVA Substation
A32: =input!C12 -> PINE TREES | B32: January 21, 2026: Buaki, Sapid: Around 4:00 PM, GO Guard received a phone call from Buaki Guard regarding an ongoing fire incident located at Buaki Area. They noticed that the fire was spreading so responders borded the firetruck and proceeded to the area. Upon arrival at 4:14PM, VSAI responders, along with the community began to suppress the fire by allowing them to utilize their water hoses, while safety responders on site were in charge of safety measures. After inspection, at least 25 grown pine trees were partially burnt in the 450 square meter of affected area. Witnesses from the community stated that they saw two (2) minor children roaming the affected area before the fire occured. No one identified the minors but they were advised to submit the names once found out. Fire-out was declared at 5:27 PM. Debriefing was headed by Mr. Alfe C. Guaki.
A33: =input!O12 -> EI
A34: =input!G12 -> Buaki, Sapid
A35: =input!C13 -> BURNT GARBAGE | B35: January 24, 2026, Golf Course, Sapid: GO Guard on duty received a phone call relayed by the Gate 3 guard regarding an onhoing fire at Golf Course, Sapid noticed by a Mr. Bustillo when he was passing through at the area. The powerhouse wa notified to sound the alarm. Other concerned departments were also notified. Responders arrived at 7:46 PM, who saw that the fire was on its dying-out stage as the onsite VSAI personnel used tree branches to suppress the fire. For certainty, the firetruck was used to thoroughly sweep burning ashes and smoky portions. Clearing and investigations was conducted after: at least 30 square meters was burnt and no damages was found. Fire our was announced at about 8:10PM followed by debriefing headed by Engr. Alfe C. Guaki.
A36: =input!O13 -> EI
A37: =input!G13 -> Golf Course, Sapid
A38: =input!C14 -> VOLVO TRUCK | B38: January 30, 2026: 6:54 AM: Shipside-operated delivery truck / hauler, was assigned to transport materials from Bulacan. Skid marks indicated that the truck lost traction on the right side, swung left and struck the parapet. The driver stated that whiledescending a curved section of Upper Golf Course Rd., he observed an oncoming SUV travelling upheil. To yield the right of way, he steered the truck toward the right side of the road. However, the trucks' right-side wheel inadvertently entered a roadside canal approcimately two feet deep. In an effort to recover the vehicles and turn it to the roadway, he steered left, briefly accelerated, and then applied the breaks. unfortunately the brakes failed to function. Due to the vehicles' weight ant the slippery conditions caused by muddy soil and wet pine needles along the roadside, the ruck lost traction, skidded forward, and ultimately slid into the ditch on the left side of the roadway. The truck was found at the bottom of a ravine, sustaining extensive damage which scattered 10 sacks of Sodium metabisulphite (SMBS) around the site, resulting in a solid chemical spill, which were transferred into new sacks for safetkeeping before the materials were delivered to the Mill Detox Area. The driver and his companion was immediately transported to the LMD Hospital for medical assessment and treatment. The driver sustained a laceration on the right hand, fifth digit and back pain, while the passenger suffered a right infraorbital contusion with hematoma. The truck was recovered at around 11:00 PM using Loaders deployed by LMD and was temporarily parked at Mr. Negradas' plce in Tubo. As of the written report, the vehicle remains there pending a complete assessment by Shipside Maintenance.
A39: =input!O14 -> EI
A40: =input!G14 -> Tubo, Sapid
A41: Brief Description of Incident (s): | B41: 46054
A42: Norel Alagon | B42: At approximately 3:00 PM (Day Shift), the victim, together with his co-workers was in the process of retrieving the inner tube. During the operation, the rod clamp wa connected to the rotating rods in an attempt to loosen them. Due to difficulty in loosening the rods, the victim used a pipe wrench size-36 to assist in the task. However, the pipe wrench failed to properly grip the rod and suddenly slipped, striking the victim on the right side of his lower back.
A43: FAC - Lower Back
A44: LM90 1000L Cuddy
A45: Julius M. Fanggot | B45: The victim and his assigned buddy was assigned at 21516 Raise access, after conducting barring down and fixing their air and water pipes. His buddy proceeded to inspect the RDM for any defects while the victim went to hand muck at the left side of the panel while facing the right side. While the victime was on the midst of clearing rock materials intended for the lifter holes, he bowed down to remove some rocks that are hard to be removed by the shovel while his left hand is still holding the shovel on a standing position while his other hand was doing the work. Moments later a small rock fell, he was about to straighten his posture to inspect the source of the rock when a larger rock suddenly slide from the chest level of the side wall area.
A46: LTA-NF
A47: 21526 Raise Access
A48: Aljon J. Valdez | B48: Innitially, the victim felt dizziness while he was resting at the 249 station. Suddenly, he complained of pain on his stomach and was extricated from site to the company hospital.
A49: OI - Stomach ache & dizziness
A50: 249 Station
A51: Ramil A. Bayyoc | B51: At approximately 8:20 AM, the victim was at the 900L resting station waiting for the locomotive battery to charge. While waiting, he suddenly experienced dizziness and cramping in his shoulder. He immediately reported the incident to his superior, who then contacted the control room to arrange for an ambulance to transport Mr. Bayyoc to the company hopital for further medical evaluation and treatment.
A52: OI
A53: 249 Station
A54: William S. Bagyon | B54: The victim and his companion was assigned at 2091 Access 980 el. Section 2 for jack up purposes at around 1:00 AM. He ignored the sudden pain on his stomach and continued drilling for blast holes (BH). Rright after drilling 12 BH his stomach ache intensified and decided to report the matter to his supervisor, who called the control room to ferry the victim via ambulance to LMD hospital for medical check-up.
A55: OI
A56: 2091 Access
A57: Jhon Jhon B. Angdason | B57: After blasting, the victim was pulling out the blasted boulders prior to rock bolting. Suddenly, a boulder nearby moved and his left hand (back of hand) was caught in between boulder causing laceration injury. The victim was then immediately transported at LMD hospital for medical check-up.
A58: FAC
A59: 12541 G31S
A60: Jackford D. Palsaan | B60: The victim was operating the LHD 124 about to muck at the stope. He noticed that the back and wall gave signs to fall (ag abiso) so he shifted the LHD to reverse. Unfortunately, the loader and his right middle finger causing his injury was caught in the action.
A61: FAC
A62: 2325 6M4 890L
A63: Crayton B. Calsiyao | B63: The victim and the LHD Operator were pulling out 6x8 timber logs along the muckpile prior to mucking. They did not notice a sticking nail from the 6x8 log that cause puncture injury at the left leg of Mr. Calsiyao.the victim.
A64: FAC
A65: 205 4M4 1000L
A66: Leaonard D. Salingsing | B66: A Rock Mechanics Assistant, conducted a ground condition and report assessment within the panel. While inspecting, he identified open cracks at distance 22-26. Determining that a bardown was necessary, he directed the victim to hand over a pinch bar partially covered in muck. As the victim was retrieving the tool, a boulder slab fell from the panel wall/ shoulder and struck him.
A67: LTA-NF
A68: 12508 H31N, 880L
A69: Jerry L. Bistayok | B69: The victim and his team were assigned to man 320 XCE. They proceeded to conduct barring down at the face. Upon completion, rock fragments had accumulated on the floor of the face. With the intent to clear the floor for lifter holes, the victim began hand mucking using a shovel. While bent down, a rock approximately the size of his skull guard sloughed off from the left side of the panel near the face. The rock struck his skull guard, dislodging it, and hit his right shoulder, causing numbness, abrasion, and dizziness.
A70: FAC
A71: 320 Crosscut
A72: Simon A. Taliwan Jr. | B72: After conducting crushing product sampling for metallurgical testing, the victim proceeded to descend the ramp. His foot nearly slipped intot eh gap between the conveypr and the ramp, which could have resulted in loss of balance and fall.
A73: NM
A74: Access Ramp, Crushing Area
A75: Community Area | B75: February 06, 2026; 5:05 PM, Gravel Pit: A VSAI Officer was notified via call from a concerned citizen, who was attending an ongoing IEC at Barangay Sapid, about a suspected bush-fire above the Barangay. This was also relayed to him via call so VSAI officers went to confirm the incident. After a positive sighting, the VSAI Officer radiod central base. The LMD ERT responded together with two Barangay Tanod. Fire suspension was made and at 5:50 PM, fire out was announced. Investigations reveal that approximately 100 square meter and seven (7) grown pine trees were affected, which started at the burnt garbages below the road mixed with dried leaves which evemtually spread out.
A76: EI
A77: Gravel Pit, Sapid
A78: LMD Employees | B78: February 16, 2026; 9:40 AM: An earthquake was felt, particularly by MEPEO, Accounting, and IMD employees, who proceeded to the evacuation point. However, not all individuals within the mine camp experienced the tremor. A comprehensive inspection on the physical stability of the GO buildings was conducted by the PCES department. During inspection one remaining employee was found to be left behind, who was excorted by Mr. Cabrera to the muster point. After confirming that there were no physical / structural damage, and no safety hazards identified, employees were advised that it was safe of return to their stations and resume normal operations. Personnel were reminded to remain vigilant and exercise caution in the event of possible aftershocks. Subsequent follow-up inquiries confirmed that the earthquake was slightly felt at DTC, Tubo Collar, and Nayak, but was not experienced in Mill, DAM 4&5 areas.
A79: EI
A80: General Office Area
A81: Pine Trees | B81: February 21, 2026; 4:45 PM; Tagumbao, Sapid: Security personnel initially responded to the bush fire. When it began spreading to the bushes and can't be controlled through manual deed, centrall was called upon for ERT presonnel to respond. Responders immediately got to work and connected three (3) fire hose to suppress the fire. Arounf 5:12 PM, fire-out was declared. Inspection reveals 20 grown pine trees partially burnt. Source of the fire points to cigarette butts thrown away by bystanders / picknickers.
A82: EI
A83: Golf Course, Sapid
A84: Pine Trees | B84: February 26, 2026; 8:35 PM: Security personnel from carpentry area was monitoring from the radio and reported to central of the fire at the Tagumbao short cut area. Responders proceeded at the scene and declared fire-out at 9:00PM. Investigations reveal that the fire was started by burnt garbages. Approximately 200 square meters were affected and five (5) grown trees and bamboo were partially burnt.
A85: EI
A86: Tagumbao, Sapid
A87: Hoses, and Fences | B87: A phone call from a concerned citizen from Pukitan was intercepted by Internal Operators. A fire was reported hence the fire brigade team responded along with the ER team. Fire-out was declared at 12:13 PM. Investigations point oit to unidentified suspects who started the fire using dry grass. Approximately 600 square meters was affected along with 30 plastic hose fence and two (2) water hoses.
A88: EI
A89: Aerodome Area, Pukitan
A90: Brief Description of Incident (s): | B90: 46082
A91: Bush Fire | B91: At 9:51 PM, a fire incident was relayed within the IOSD Guards. The Fire Brigade Team proceeded to the scene, where it was already being secured. Three fire hoses were connected and the fire was suppressed and out at 11:12 PM. Invenstigation disclosed that the dry grass was ignited by unidentified suspect/s which made the fire to spread. Approximately 200 sqm of dry brushed grass was affected and 15 trees were partially damaged by the fire. An IEC to nearby residents were made to stop burning brushed grasses to avoid recurrence of the same event and adviced golf course maintenance and security guard to monitor the area properly.
A92: EI
A93: Golf Course, Sapid
A94: Oil Spill | B94: At approximately 9:39 AM, a vehicle (TFQ 524) arrived at the General Office Area. During the unloading / handling process, fuel was accidentally spilled from the vehicle, resulting in a minor fuel spill on the ground near the office vicinity. As stated from Central Operator, the vehicle intended to park at the G.O. area. Whilst backing, the assigned driver noticed the trouble and immediately rushed the vehicle to the Motorpool, which cause the minor spill to spread through its tracks. Spill response procedures were arried out on affected areas. Contaminated absorbent materials were properly turned over to IMD and no injuries were noted. The situation was secured at 9:58 AM.
A95: EI - TFQ 524
A96: General Office Area
A97: Lime Surge Tank | B97: On the third shift of March 14, 2026, Operators noticed Dossing of Lime to Starter Sump was of no / zero supply. Lime operators found out busted lime tank below tank 17/25. The tank was made out of fiber materials which does not meet standards to hold lime materials, which was th only available light materials transported to site by Engineering men who installed. Replacement of damaged area with steel plates was recommmended. This is to be done by the Mill Engineering Department.
A98: PD
A99: Lime Plant
A100: Bush Fire | B100: At around 6:00 PM, a fire was reported from the Nayak Guard stating that the incident is ongoing at San Roque Area. Upon arrival of the Lepanto fire brigade, SME SH Anongos was on stand by for response, followed y the arrival of the BFP Mankayan. Fire hoses were immediatly connected alng with an ongoing manual suppression by other concerned citizens, while SI Kiblasan and the BFP Mankayan controlled the fire at the upper level near the Orient Cottages. The BFP Mankayak was left behind to suppress the incident while Lepanto Fire Brigade refilled at Tank #7 to proceed at Tagumbao, Sapid where another fire was reported. The Tagumbao fire was out at 8:45PM Investigations disclosed that the fire at San Roque began from a bonfire or burnt dry woods / leaves of unidentified passerby / picknickers), while the fire at Tagumbao was started by burnt garbages from unidentifies suspects. Approximately 900 sqm was affected at San Roque Area while 400 sqm at Tagumbao, Sapid Area.
...

Sheet January
B1: ACCIDENT MONITORING REPORT
B2: JANUARY, 2026
B3: Name of Person Injured / Damaged Property | D3: CN / Unit # | E3: Occupation / Designation | F3: Type of Incident | H3: Work Place / Area | I3: Level | J3: Date | L3: Time | N3: Shift | O3: Dep't Head | P3: Section Head | Q3: Immediate Supervisor | R3: Nature of Injury | S3: On-Going Activity | T3: Safety Inspector On-duty | V3: Group | W3: Department | Y3: Section | Z3: Recorded By
B5: UNDERGROUND:
B6: =input!C2 -> RYAN DAVE MAWI-IT | D6: =input!D2 -> 8471 | E6: =input!E2 -> Assistant Miner | F6: =input!F2 -> Occupational Illness / Pain | H6: =input!G2 -> Shaft Station / Resting Area | I6: =input!H2 -> 900L | J6: =input!I2 -> 46032 | L6: =input!J2 -> 0.97916667 | N6: =input!K2 -> Second | O6: =input!L2 -> Hilbert G. Andong | P6: =input!M2 -> Reynaldo P. Kiking | Q6: =input!N2 -> Stephen Adams D. Mamanteo | R6: =input!O2 -> OI | S6: =input!P2 -> Cleaning of canal. | T6: =input!Q2 -> WDL / MAT | V6: =input!R2 -> MOG | W6: =input!S2 -> Dept. 2 | Y6: =input!T2 -> Section 6 | Z6: =input!U2 -> MAT
B7: =input!C3 -> JOEY A. LASSIN | D7: =input!D3 -> 9728 | E7: =input!E3 -> Assistant Miner | F7: =input!F3 -> Struck by Falling Rock | H7: =input!G3 -> Stope | I7: =input!H3 -> 970L | J7: =input!I3 -> 46038 | L7: =input!J3 -> 0.97916667 | N7: =input!K3 -> Second | O7: =input!L3 -> Venancio A. Bad-ay | P7: =input!M3 -> Mariel T. Ayong | Q7: =input!N3 -> Leonard K. Fawayan | R7: =input!O3 -> FAC | S7: =input!P3 -> Rock Bolting | T7: =input!Q3 -> JAW / EAR / MAT / AOV | V7: =input!R3 -> MOG | W7: =input!S3 -> Dept. 1 | Y7: =input!T3 -> Section 2 | Z7: =input!U3 -> MAT
B8: =input!C4 -> MANUEL D. BALAIS | D8: =input!D4 -> 1209 | E8: =input!E4 -> Shiftboss | F8: =input!F4 -> Foreign Object in the Eye/s | H8: =input!G4 -> Ramp | I8: =input!H4 -> 1100L | J8: =input!I4 -> 46046 | L8: =input!J4 -> 0.125 | N8: =input!K4 -> First | O8: =input!L4 -> Hilbert G. Andong | P8: =input!M4 -> Allab B. Lal-wet | Q8: =input!N4 -> Dummory Joseff Febrei O. Estepa | R8: =input!O4 -> FAC | S8: =input!P4 -> Operating the breaker | T8: =input!Q4 -> WLT / SUU / FPP | V8: =input!R4 -> MOG | W8: =input!S4 -> Dept. 2 | Y8: =input!T4 -> Section 4 | Z8: =input!U4 -> MAT
B9: =input!C5 -> WILBUR D. AWIS | D9: =input!D5 -> 9940 | E9: =input!E5 -> Maintenance Man (MMME) | F9: =input!F5 -> Occupational Illness / Pain | H9: =input!G5 -> Shaft Station / Resting Area | I9: =input!H5 -> 900L | J9: =input!I5 -> 46047 | L9: =input!J5 -> 0.29166667 | N9: =input!K5 -> Second | O9: =input!L5 -> Fernando A. Bustillo Jr. | P9: =input!M5 -> Alfon B. Yodong | Q9: =input!N5 -> John Pauline M. Refugia | R9: =input!O5 -> OI | S9: =input!P5 -> Preparing for task | T9: =input!Q5 -> SUU | V9: =input!R5 -> MOG | W9: =input!S5 -> MMME | Y9: =input!T5 -> Mobile | Z9: =input!U5 -> MAT
B10: =input!C6 -> DUMAGUING M. LIBAN | D10: =input!D6 -> 1336 | E10: =input!E6 -> LHD Optr | F10: =input!F6 -> Caught in Between | H10: =input!G6 -> Ramp | I10: =input!H6 -> 1000L | J10: =input!I6 -> 46048 | L10: =input!J6 -> 0.8125 | N10: =input!K6 -> Third | O10: =input!L6 -> Venancio A. Bad-ay | P10: =input!M6 -> June O. Golocan | Q10: =input!N6 -> Danilo M. Galande | R10: =input!O6 -> LTA-F | S10: =input!P6 -> Descending towards 900L | T10: =input!Q6 -> WLT / EAR | V10: =input!R6 -> MOG | W10: =input!S6 -> Dept. 1 | Y10: =input!T6 -> Section 3 | Z10: =input!U6 -> MAT
B11: =input!C7 -> GLENN MARK B. LABOTAN | D11: =input!D7 -> 9346 | E11: =input!E7 -> UG Senior Warehouseman | F11: =input!F7 -> Caught in Between | H11: =input!G7 -> Fuel Storage Area | I11: =input!H7 -> 900L | J11: =input!I7 -> 46052 | L11: =input!J7 -> 0.40625 | N11: =input!K7 -> Second | O11: =input!L7 -> Fe Marie W. Mates | P11: =input!M7 -> Samson A. Fotyong | Q11: =input!N7 -> Marvin B. Caligner | R11: =input!O7 -> LTA-NF | S11: =input!P7 -> Unloading fuel oil drum | T11: =input!Q7 -> MAT / AOV | V11: =input!R7 -> FSG | W11: =input!S7 -> IMD | Y11: =input!T7 -> Underground Warehouse | Z11: =input!U7 -> KTA
B12: SURFACE:
B13: =input!C8 -> BINSON I. ZAPARITA | D13: =input!D8 -> 9901 | E13: =input!E8 -> Jr. Machinist | F13: =input!F8 -> Caught in Between | H13: =input!G8 -> Machine Shop | I13: =input!H8 -> S (N/A) | J13: =input!I8 -> 46039 | L13: =input!J8 -> 0.46527778 | N13: =input!K8 -> Second | O13: =input!L8 -> Larry A. Arigue | P13: =input!M8 -> James I. Consolacion | Q13: =input!N8 -> N/A | R13: =input!O8 -> FAC | S13: =input!P8 -> Unloading via crane operation | T13: =input!Q8 -> MBK / RML | V13: =input!R8 -> TSG | W13: =input!S8 -> MWSO | Y13: =input!T8 -> Machine Shop | Z13: =input!U8 -> RML
B14: =input!C9 -> ROWELL C. DELA CRUZ | D14: =input!D9 -> 9386 | E14: =input!E9 -> Surface Warehouseman | F14: =input!F9 -> Contact with Object | H14: =input!G9 -> Steel Yard | I14: =input!H9 -> S (N/A) | J14: =input!I9 -> 46034 | L14: =input!J9 -> 0.32291667 | N14: =input!K9 -> Second | O14: =input!L9 -> Fe Marie W. Mates | P14: =input!M9 -> Julian Manuel S. Casuga | Q14: =input!N9 -> Karl Lloyd S. Valentin | R14: =input!O9 -> FAC | S14: =input!P9 -> Loading of Causic Soda | T14: =input!Q9 -> ENC / RML | V14: =input!R9 -> FSG | W14: =input!S9 -> IMD | Y14: =input!T9 -> Surface Warehouse | Z14: =input!U9 -> RML
B15: =input!C10 -> JOHN REY BAGUIYAC | D15: =input!D10 -> N/A - Contracts | E15: =input!E10 -> Carpenter | F15: =input!F10 -> Caught in Between | H15: =input!G10 -> Hospital | I15: =input!H10 -> S (N/A) | J15: =input!I10 -> 46045 | L15: =input!J10 -> 0.33333333 | N15: =input!K10 -> Second | O15: =input!L10 -> Abraham L. Davis | P15: =input!M10 -> Nathaneal D. Jugal | Q15: =input!N10 -> Kathy M. Domogo | R15: =input!O10 -> FAC | S15: =input!P10 -> Hauling of H-beams | T15: =input!Q10 -> ENC / RML | V15: =input!R10 -> Contracts | W15: =input!S10 -> MD&C Construction | Y15: =input!T10 -> Building Maintenance | Z15: =input!U10 -> RML
B16: PROPERTY DAMAGE:
B17: =input!C11 -> FUSE CUT-OFF SWITCH | D17: =input!D11 -> N/A - PD | E17: =input!E11 -> Fuse Cut-Off Switch | F17: =input!F11 -> Property Damage | H17: =input!G11 -> UG Crusher | I17: =input!H11 -> S (N/A) | J17: =input!I11 -> 46039 | L17: =input!J11 -> 0.77083333 | N17: =input!K11 -> Third | O17: =input!L11 -> Fernando A. Bustillo Jr. | P17: =input!M11 -> Neil Marcel F. Paquito | Q17: =input!N11 -> Pedro B. Lambino | R17: =input!O11 -> PD | S17: =input!P11 -> Sudden Power Loss | T17: =input!Q11 -> MBK | V17: =input!R11 -> MOG | W17: =input!S11 -> MMME | Y17: =input!T11 -> Electrical | Z17: =input!U11 -> KTA
B18: EMERGENCY INCIDENT
B19: =input!C12 -> PINE TREES | D19: =input!D12 -> N/A - EI | E19: =input!E12 -> Forest Fire | F19: =input!F12 -> Fire | H19: =input!G12 -> Buaki, Sapid | I19: =input!H12 -> S (N/A) | J19: =input!I12 -> 46043 | L19: =input!J12 -> 0.66666667 | N19: =input!K12 -> Second | O19: =input!L12 -> N/A | P19: =input!M12 -> N/A | Q19: =input!N12 -> N/A | R19: =input!O12 -> EI | S19: =input!P12 -> 0 | T19: =input!Q12 -> MBK | V19: =input!R12 -> ASG | W19: =input!S12 -> IOSD | Y19: =input!T12 -> N/A - Community | Z19: =input!U12 -> KTA
B20: =input!C13 -> BURNT GARBAGE | D20: =input!D13 -> N/A - EI | E20: =input!E13 -> Forest Fire | F20: =input!F13 -> Fire | H20: =input!G13 -> Golf Course, Sapid | I20: =input!H13 -> S (N/A) | J20: =input!I13 -> 46046 | L20: =input!J13 -> 0.82361111 | N20: =input!K13 -> Third | O20: =input!L13 -> N/A | P20: =input!M13 -> N/A | Q20: =input!N13 -> N/A | R20: =input!O13 -> EI | S20: =input!P13 -> 0 | T20: =input!Q13 -> ENC | V20: =input!R13 -> ASG | W20: =input!S13 -> IOSD | Y20: =input!T13 -> N/A - Community | Z20: =input!U13 -> KTA
B21: =input!C14 -> VOLVO TRUCK | D21: =input!D14 -> TDQ 954 | E21: =input!E14 -> Shipside - Volvo Truck | F21: =input!F14 -> Fall on Lower level | H21: =input!G14 -> Tubo, Sapid | I21: =input!H14 -> S (N/A) | J21: =input!I14 -> 46052 | L21: =input!J14 -> 0.29027778 | N21: =input!K14 -> Second | O21: =input!L14 -> N/A | P21: =input!M14 -> N/A | Q21: =input!N14 -> N/A | R21: =input!O14 -> EI | S21: =input!P14 -> Delivery of goods | T21: =input!Q14 -> MBK | V21: =input!R14 -> FSG | W21: =input!S14 -> IMD | Y21: =input!T14 -> Surface Warehouse | Z21: =input!U14 -> KTA
B22: Occupation/ Equipment | D22: LTA-F | E22: LTA-NF | F22: NLTA | G22: FAC | H22: NM | I22: OI | J22: PD | K22: EI | L22: Total | M22: % Distribution | N22: Type of Incident | Q22: LTA-F | R22: LTA-NF | S22: NLTA | T22: FAC | U22: NM | V22: OI | W22: PD | X22: EI | Y22: Total | Z22: % Distribution
B23: Assistant Miner | D23: =COUNTIFS(input!$O:$O,January!$D$22,input!$E:$E,January!B23,input!$A:$A,January!$B$2) -> 0 | E23: =COUNTIFS(input!$O:$O,January!$E$22,input!$E:$E,January!B23,input!$A:$A,January!$B$2) -> 0 | F23: =COUNTIFS(input!$O:$O,January!$F$22,input!$E:$E,January!B23,input!$A:$A,January!$B$2) -> 0 | G23: =COUNTIFS(input!$O:$O,January!$G$22,input!$E:$E,January!B23,input!$A:$A,January!$B$2) -> 1 | H23: =COUNTIFS(input!$O:$O,January!$H$22,input!$E:$E,January!B23,input!$A:$A,January!$B$2) -> 0 | I23: =COUNTIFS(input!$O:$O,January!$I$22,input!$E:$E,January!B23,input!$A:$A,January!$B$2) -> 1 | J23: =COUNTIFS(input!$O:$O,January!$J$22,input!$E:$E,January!B23,input!$A:$A,January!$B$2) -> 0 | K23: =COUNTIFS(input!$O:$O,January!$K$22,input!$E:$E,January!B23,input!$A:$A,January!$B$2) -> 0 | L23: =SUM(D23:K23) -> 2 | M23: {=_xlfn.IFS(L23=0,0,L23>=1,L23/L44)} -> 0.15384615 | N23: Struck by Falling Rock | Q23: =COUNTIFS(input!$O:$O,January!$Q$22,input!$F:$F,January!N23,input!$A:$A,January!$B$2) -> 0 | R23: =COUNTIFS(input!$O:$O,January!$R$22,input!$F:$F,January!N23,input!$A:$A,January!$B$2) -> 0 | S23: =COUNTIFS(input!$O:$O,January!$S$22,input!$F:$F,January!N23,input!$A:$A,January!$B$2) -> 0 | T23: =COUNTIFS(input!$O:$O,January!$T$22,input!$F:$F,January!N23,input!$A:$A,January!$B$2) -> 1 | U23: =COUNTIFS(input!$O:$O,January!$U$22,input!$F:$F,January!N23,input!$A:$A,January!$B$2) -> 0 | V23: =COUNTIFS(input!$O:$O,January!$V$22,input!$F:$F,January!N23,input!$A:$A,January!$B$2) -> 0 | W23: =COUNTIFS(input!$O:$O,January!$W$22,input!$F:$F,January!N23,input!$A:$A,January!$B$2) -> 0 | X23: =COUNTIFS(input!$O:$O,January!$X$22,input!$F:$F,January!N23,input!$A:$A,January!$B$2) -> 0 | Y23: =SUM(Q23:X23) -> 1 | Z23: {=_xlfn.IFS(Y23=0,0,Y23>=1,Y23/Y44)} -> 0.076923077
B24: Lead Miner | D24: =COUNTIFS(input!$O:$O,January!$D$22,input!$E:$E,January!B24,input!$A:$A,January!$B$2) -> 0 | E24: =COUNTIFS(input!$O:$O,January!$E$22,input!$E:$E,January!B24,input!$A:$A,January!$B$2) -> 0 | F24: =COUNTIFS(input!$O:$O,January!$F$22,input!$E:$E,January!B24,input!$A:$A,January!$B$2) -> 0 | G24: =COUNTIFS(input!$O:$O,January!$G$22,input!$E:$E,January!B24,input!$A:$A,January!$B$2) -> 0 | H24: =COUNTIFS(input!$O:$O,January!$H$22,input!$E:$E,January!B24,input!$A:$A,January!$B$2) -> 0 | I24: =COUNTIFS(input!$O:$O,January!$I$22,input!$E:$E,January!B24,input!$A:$A,January!$B$2) -> 0 | J24: =COUNTIFS(input!$O:$O,January!$J$22,input!$E:$E,January!B24,input!$A:$A,January!$B$2) -> 0 | K24: =COUNTIFS(input!$O:$O,January!$K$22,input!$E:$E,January!B24,input!$A:$A,January!$B$2) -> 0 | L24: =SUM(D24:K24) -> 0 | M24: {=_xlfn.IFS(L24=0,0,L24>=1,L24/L44)} -> 0 | N24: Struck Against | Q24: =COUNTIFS(input!$O:$O,January!$Q$22,input!$F:$F,January!N24,input!$A:$A,January!$B$2) -> 0 | R24: =COUNTIFS(input!$O:$O,January!$R$22,input!$F:$F,January!N24,input!$A:$A,January!$B$2) -> 0 | S24: =COUNTIFS(input!$O:$O,January!$S$22,input!$F:$F,January!N24,input!$A:$A,January!$B$2) -> 0 | T24: =COUNTIFS(input!$O:$O,January!$T$22,input!$F:$F,January!N24,input!$A:$A,January!$B$2) -> 0 | U24: =COUNTIFS(input!$O:$O,January!$U$22,input!$F:$F,January!N24,input!$A:$A,January!$B$2) -> 0 | V24: =COUNTIFS(input!$O:$O,January!$V$22,input!$F:$F,January!N24,input!$A:$A,January!$B$2) -> 0 | W24: =COUNTIFS(input!$O:$O,January!$W$22,input!$F:$F,January!N24,input!$A:$A,January!$B$2) -> 0 | X24: =COUNTIFS(input!$O:$O,January!$X$22,input!$F:$F,January!N24,input!$A:$A,January!$B$2) -> 0 | Y24: =SUM(Q24:X24) -> 0 | Z24: {=_xlfn.IFS(Y24=0,0,Y24>=1,Y24/Y44)} -> 0
B25: LPT Optr | D25: =COUNTIFS(input!$O:$O,January!$D$22,input!$E:$E,January!B25,input!$A:$A,January!$B$2) -> 0 | E25: =COUNTIFS(input!$O:$O,January!$E$22,input!$E:$E,January!B25,input!$A:$A,January!$B$2) -> 0 | F25: =COUNTIFS(input!$O:$O,January!$F$22,input!$E:$E,January!B25,input!$A:$A,January!$B$2) -> 0 | G25: =COUNTIFS(input!$O:$O,January!$G$22,input!$E:$E,January!B25,input!$A:$A,January!$B$2) -> 0 | H25: =COUNTIFS(input!$O:$O,January!$H$22,input!$E:$E,January!B25,input!$A:$A,January!$B$2) -> 0 | I25: =COUNTIFS(input!$O:$O,January!$I$22,input!$E:$E,January!B25,input!$A:$A,January!$B$2) -> 0 | J25: =COUNTIFS(input!$O:$O,January!$J$22,input!$E:$E,January!B25,input!$A:$A,January!$B$2) -> 0 | K25: =COUNTIFS(input!$O:$O,January!$K$22,input!$E:$E,January!B25,input!$A:$A,January!$B$2) -> 0 | L25: =SUM(D25:K25) -> 0 | M25: {=_xlfn.IFS(L25=0,0,L25>=1,L25/L44)} -> 0 | N25: Struck by object | Q25: =COUNTIFS(input!$O:$O,January!$Q$22,input!$F:$F,January!N25,input!$A:$A,January!$B$2) -> 0 | R25: =COUNTIFS(input!$O:$O,January!$R$22,input!$F:$F,January!N25,input!$A:$A,January!$B$2) -> 0 | S25: =COUNTIFS(input!$O:$O,January!$S$22,input!$F:$F,January!N25,input!$A:$A,January!$B$2) -> 0 | T25: =COUNTIFS(input!$O:$O,January!$T$22,input!$F:$F,January!N25,input!$A:$A,January!$B$2) -> 0 | U25: =COUNTIFS(input!$O:$O,January!$U$22,input!$F:$F,January!N25,input!$A:$A,January!$B$2) -> 0 | V25: =COUNTIFS(input!$O:$O,January!$V$22,input!$F:$F,January!N25,input!$A:$A,January!$B$2) -> 0 | W25: =COUNTIFS(input!$O:$O,January!$W$22,input!$F:$F,January!N25,input!$A:$A,January!$B$2) -> 0 | X25: =COUNTIFS(input!$O:$O,January!$X$22,input!$F:$F,January!N25,input!$A:$A,January!$B$2) -> 0 | Y25: =SUM(Q25:X25) -> 0 | Z25: {=_xlfn.IFS(Y25=0,0,Y25>=1,Y25/Y44)} -> 0
B26: LHD Optr | D26: =COUNTIFS(input!$O:$O,January!$D$22,input!$E:$E,January!B26,input!$A:$A,January!$B$2) -> 1 | E26: =COUNTIFS(input!$O:$O,January!$E$22,input!$E:$E,January!B26,input!$A:$A,January!$B$2) -> 0 | F26: =COUNTIFS(input!$O:$O,January!$F$22,input!$E:$E,January!B26,input!$A:$A,January!$B$2) -> 0 | G26: =COUNTIFS(input!$O:$O,January!$G$22,input!$E:$E,January!B26,input!$A:$A,January!$B$2) -> 0 | H26: =COUNTIFS(input!$O:$O,January!$H$22,input!$E:$E,January!B26,input!$A:$A,January!$B$2) -> 0 | I26: =COUNTIFS(input!$O:$O,January!$I$22,input!$E:$E,January!B26,input!$A:$A,January!$B$2) -> 0 | J26: =COUNTIFS(input!$O:$O,January!$J$22,input!$E:$E,January!B26,input!$A:$A,January!$B$2) -> 0 | K26: =COUNTIFS(input!$O:$O,January!$K$22,input!$E:$E,January!B26,input!$A:$A,January!$B$2) -> 0 | L26: =SUM(D26:K26) -> 1 | M26: {=_xlfn.IFS(L26=0,0,L26>=1,L26/L44)} -> 0.076923077 | N26: Caught in between | Q26: =COUNTIFS(input!$O:$O,January!$Q$22,input!$F:$F,January!N26,input!$A:$A,January!$B$2) -> 1 | R26: =COUNTIFS(input!$O:$O,January!$R$22,input!$F:$F,January!N26,input!$A:$A,January!$B$2) -> 1 | S26: =COUNTIFS(input!$O:$O,January!$S$22,input!$F:$F,January!N26,input!$A:$A,January!$B$2) -> 0 | T26: =COUNTIFS(input!$O:$O,January!$T$22,input!$F:$F,January!N26,input!$A:$A,January!$B$2) -> 2 | U26: =COUNTIFS(input!$O:$O,January!$U$22,input!$F:$F,January!N26,input!$A:$A,January!$B$2) -> 0 | V26: =COUNTIFS(input!$O:$O,January!$V$22,input!$F:$F,January!N26,input!$A:$A,January!$B$2) -> 0 | W26: =COUNTIFS(input!$O:$O,January!$W$22,input!$F:$F,January!N26,input!$A:$A,January!$B$2) -> 0 | X26: =COUNTIFS(input!$O:$O,January!$X$22,input!$F:$F,January!N26,input!$A:$A,January!$B$2) -> 0 | Y26: =SUM(Q26:X26) -> 4 | Z26: {=_xlfn.IFS(Y26=0,0,Y26>=1,Y26/Y44)} -> 0.30769231
B27: Locomotive Optr./ Helper | D27: =COUNTIFS(input!$O:$O,January!$D$22,input!$E:$E,January!B27,input!$A:$A,January!$B$2) -> 0 | E27: =COUNTIFS(input!$O:$O,January!$E$22,input!$E:$E,January!B27,input!$A:$A,January!$B$2) -> 0 | F27: =COUNTIFS(input!$O:$O,January!$F$22,input!$E:$E,January!B27,input!$A:$A,January!$B$2) -> 0 | G27: =COUNTIFS(input!$O:$O,January!$G$22,input!$E:$E,January!B27,input!$A:$A,January!$B$2) -> 0 | H27: =COUNTIFS(input!$O:$O,January!$H$22,input!$E:$E,January!B27,input!$A:$A,January!$B$2) -> 0 | I27: =COUNTIFS(input!$O:$O,January!$I$22,input!$E:$E,January!B27,input!$A:$A,January!$B$2) -> 0 | J27: =COUNTIFS(input!$O:$O,January!$J$22,input!$E:$E,January!B27,input!$A:$A,January!$B$2) -> 0 | K27: =COUNTIFS(input!$O:$O,January!$K$22,input!$E:$E,January!B27,input!$A:$A,January!$B$2) -> 0 | L27: =SUM(D27:K27) -> 0 | M27: {=_xlfn.IFS(L27=0,0,L27>=1,L27/L44)} -> 0 | N27: Caught on | Q27: =COUNTIFS(input!$O:$O,January!$Q$22,input!$F:$F,January!N27,input!$A:$A,January!$B$2) -> 0 | R27: =COUNTIFS(input!$O:$O,January!$R$22,input!$F:$F,January!N27,input!$A:$A,January!$B$2) -> 0 | S27: =COUNTIFS(input!$O:$O,January!$S$22,input!$F:$F,January!N27,input!$A:$A,January!$B$2) -> 0 | T27: =COUNTIFS(input!$O:$O,January!$T$22,input!$F:$F,January!N27,input!$A:$A,January!$B$2) -> 0 | U27: =COUNTIFS(input!$O:$O,January!$U$22,input!$F:$F,January!N27,input!$A:$A,January!$B$2) -> 0 | V27: =COUNTIFS(input!$O:$O,January!$V$22,input!$F:$F,January!N27,input!$A:$A,January!$B$2) -> 0 | W27: =COUNTIFS(input!$O:$O,January!$W$22,input!$F:$F,January!N27,input!$A:$A,January!$B$2) -> 0 | X27: =COUNTIFS(input!$O:$O,January!$X$22,input!$F:$F,January!N27,input!$A:$A,January!$B$2) -> 0 | Y27: =SUM(Q27:X27) -> 0 | Z27: {=_xlfn.IFS(Y27=0,0,Y27>=1,Y27/Y44)} -> 0
B28: Shiftboss | D28: =COUNTIFS(input!$O:$O,January!$D$22,input!$E:$E,January!B28,input!$A:$A,January!$B$2) -> 0 | E28: =COUNTIFS(input!$O:$O,January!$E$22,input!$E:$E,January!B28,input!$A:$A,January!$B$2) -> 0 | F28: =COUNTIFS(input!$O:$O,January!$F$22,input!$E:$E,January!B28,input!$A:$A,January!$B$2) -> 0 | G28: =COUNTIFS(input!$O:$O,January!$G$22,input!$E:$E,January!B28,input!$A:$A,January!$B$2) -> 1 | H28: =COUNTIFS(input!$O:$O,January!$H$22,input!$E:$E,January!B28,input!$A:$A,January!$B$2) -> 0 | I28: =COUNTIFS(input!$O:$O,January!$I$22,input!$E:$E,January!B28,input!$A:$A,January!$B$2) -> 0 | J28: =COUNTIFS(input!$O:$O,January!$J$22,input!$E:$E,January!B28,input!$A:$A,January!$B$2) -> 0 | K28: =COUNTIFS(input!$O:$O,January!$K$22,input!$E:$E,January!B28,input!$A:$A,January!$B$2) -> 0 | L28: =SUM(D28:K28) -> 1 | M28: {=_xlfn.IFS(L28=0,0,L28>=1,L28/L44)} -> 0.076923077 | N28: Fall on same level | Q28: =COUNTIFS(input!$O:$O,January!$Q$22,input!$F:$F,January!N28,input!$A:$A,January!$B$2) -> 0 | R28: =COUNTIFS(input!$O:$O,January!$R$22,input!$F:$F,January!N28,input!$A:$A,January!$B$2) -> 0 | S28: =COUNTIFS(input!$O:$O,January!$S$22,input!$F:$F,January!N28,input!$A:$A,January!$B$2) -> 0 | T28: =COUNTIFS(input!$O:$O,January!$T$22,input!$F:$F,January!N28,input!$A:$A,January!$B$2) -> 0 | U28: =COUNTIFS(input!$O:$O,January!$U$22,input!$F:$F,January!N28,input!$A:$A,January!$B$2) -> 0 | V28: =COUNTIFS(input!$O:$O,January!$V$22,input!$F:$F,January!N28,input!$A:$A,January!$B$2) -> 0 | W28: =COUNTIFS(input!$O:$O,January!$W$22,input!$F:$F,January!N28,input!$A:$A,January!$B$2) -> 0 | X28: =COUNTIFS(input!$O:$O,January!$X$22,input!$F:$F,January!N28,input!$A:$A,January!$B$2) -> 0 | Y28: =SUM(Q28:X28) -> 0 | Z28: {=_xlfn.IFS(Y28=0,0,Y28>=1,Y28/Y44)} -> 0
B29: UG Senior Warehouseman | D29: =COUNTIFS(input!$O:$O,January!$D$22,input!$E:$E,January!B29,input!$A:$A,January!$B$2) -> 0 | E29: =COUNTIFS(input!$O:$O,January!$E$22,input!$E:$E,January!B29,input!$A:$A,January!$B$2) -> 1 | F29: =COUNTIFS(input!$O:$O,January!$F$22,input!$E:$E,January!B29,input!$A:$A,January!$B$2) -> 0 | G29: =COUNTIFS(input!$O:$O,January!$G$22,input!$E:$E,January!B29,input!$A:$A,January!$B$2) -> 0 | H29: =COUNTIFS(input!$O:$O,January!$H$22,input!$E:$E,January!B29,input!$A:$A,January!$B$2) -> 0 | I29: =COUNTIFS(input!$O:$O,January!$I$22,input!$E:$E,January!B29,input!$A:$A,January!$B$2) -> 0 | J29: =COUNTIFS(input!$O:$O,January!$J$22,input!$E:$E,January!B29,input!$A:$A,January!$B$2) -> 0 | K29: =COUNTIFS(input!$O:$O,January!$K$22,input!$E:$E,January!B29,input!$A:$A,January!$B$2) -> 0 | L29: =SUM(D29:K29) -> 1 | M29: {=_xlfn.IFS(L29=0,0,L29>=1,L29/L44)} -> 0.076923077 | N29: Fall on Lower Level | Q29: =COUNTIFS(input!$O:$O,January!$Q$22,input!$F:$F,January!N29,input!$A:$A,January!$B$2) -> 0 | R29: =COUNTIFS(input!$O:$O,January!$R$22,input!$F:$F,January!N29,input!$A:$A,January!$B$2) -> 0 | S29: =COUNTIFS(input!$O:$O,January!$S$22,input!$F:$F,January!N29,input!$A:$A,January!$B$2) -> 0 | T29: =COUNTIFS(input!$O:$O,January!$T$22,input!$F:$F,January!N29,input!$A:$A,January!$B$2) -> 0 | U29: =COUNTIFS(input!$O:$O,January!$U$22,input!$F:$F,January!N29,input!$A:$A,January!$B$2) -> 0 | V29: =COUNTIFS(input!$O:$O,January!$V$22,input!$F:$F,January!N29,input!$A:$A,January!$B$2) -> 0 | W29: =COUNTIFS(input!$O:$O,January!$W$22,input!$F:$F,January!N29,input!$A:$A,January!$B$2) -> 0 | X29: =COUNTIFS(input!$O:$O,January!$X$22,input!$F:$F,January!N29,input!$A:$A,January!$B$2) -> 1 | Y29: =SUM(Q29:X29) -> 1 | Z29: {=_xlfn.IFS(Y29=0,0,Y29>=1,Y29/Y44)} -> 0.076923077
B30: Surface Warehouseman | D30: =COUNTIFS(input!$O:$O,January!$D$22,input!$E:$E,January!B30,input!$A:$A,January!$B$2) -> 0 | E30: =COUNTIFS(input!$O:$O,January!$E$22,input!$E:$E,January!B30,input!$A:$A,January!$B$2) -> 0 | F30: =COUNTIFS(input!$O:$O,January!$F$22,input!$E:$E,January!B30,input!$A:$A,January!$B$2) -> 0 | G30: =COUNTIFS(input!$O:$O,January!$G$22,input!$E:$E,January!B30,input!$A:$A,January!$B$2) -> 1 | H30: =COUNTIFS(input!$O:$O,January!$H$22,input!$E:$E,January!B30,input!$A:$A,January!$B$2) -> 0 | I30: =COUNTIFS(input!$O:$O,January!$I$22,input!$E:$E,January!B30,input!$A:$A,January!$B$2) -> 0 | J30: =COUNTIFS(input!$O:$O,January!$J$22,input!$E:$E,January!B30,input!$A:$A,January!$B$2) -> 0 | K30: =COUNTIFS(input!$O:$O,January!$K$22,input!$E:$E,January!B30,input!$A:$A,January!$B$2) -> 0 | L30: =SUM(D30:K30) -> 1 | M30: {=_xlfn.IFS(L30=0,0,L30>=1,L30/L44)} -> 0.076923077 | N30: Fall of material or structure | Q30: =COUNTIFS(input!$O:$O,January!$Q$22,input!$F:$F,January!N30,input!$A:$A,January!$B$2) -> 0 | R30: =COUNTIFS(input!$O:$O,January!$R$22,input!$F:$F,January!N30,input!$A:$A,January!$B$2) -> 0 | S30: =COUNTIFS(input!$O:$O,January!$S$22,input!$F:$F,January!N30,input!$A:$A,January!$B$2) -> 0 | T30: =COUNTIFS(input!$O:$O,January!$T$22,input!$F:$F,January!N30,input!$A:$A,January!$B$2) -> 0 | U30: =COUNTIFS(input!$O:$O,January!$U$22,input!$F:$F,January!N30,input!$A:$A,January!$B$2) -> 0 | V30: =COUNTIFS(input!$O:$O,January!$V$22,input!$F:$F,January!N30,input!$A:$A,January!$B$2) -> 0 | W30: =COUNTIFS(input!$O:$O,January!$W$22,input!$F:$F,January!N30,input!$A:$A,January!$B$2) -> 0 | X30: =COUNTIFS(input!$O:$O,January!$X$22,input!$F:$F,January!N30,input!$A:$A,January!$B$2) -> 0 | Y30: =SUM(Q30:X30) -> 0 | Z30: {=_xlfn.IFS(Y30=0,0,Y30>=1,Y30/Y44)} -> 0
B31: Jr. Machinist | D31: =COUNTIFS(input!$O:$O,January!$D$22,input!$E:$E,January!B31,input!$A:$A,January!$B$2) -> 0 | E31: =COUNTIFS(input!$O:$O,January!$E$22,input!$E:$E,January!B31,input!$A:$A,January!$B$2) -> 0 | F31: =COUNTIFS(input!$O:$O,January!$F$22,input!$E:$E,January!B31,input!$A:$A,January!$B$2) -> 0 | G31: =COUNTIFS(input!$O:$O,January!$G$22,input!$E:$E,January!B31,input!$A:$A,January!$B$2) -> 1 | H31: =COUNTIFS(input!$O:$O,January!$H$22,input!$E:$E,January!B31,input!$A:$A,January!$B$2) -> 0 | I31: =COUNTIFS(input!$O:$O,January!$I$22,input!$E:$E,January!B31,input!$A:$A,January!$B$2) -> 0 | J31: =COUNTIFS(input!$O:$O,January!$J$22,input!$E:$E,January!B31,input!$A:$A,January!$B$2) -> 0 | K31: =COUNTIFS(input!$O:$O,January!$K$22,input!$E:$E,January!B31,input!$A:$A,January!$B$2) -> 0 | L31: =SUM(D31:K31) -> 1 | M31: {=_xlfn.IFS(L31=0,0,L31>=1,L31/L44)} -> 0.076923077 | N31: Punctured | Q31: =COUNTIFS(input!$O:$O,January!$Q$22,input!$F:$F,January!N31,input!$A:$A,January!$B$2) -> 0 | R31: =COUNTIFS(input!$O:$O,January!$R$22,input!$F:$F,January!N31,input!$A:$A,January!$B$2) -> 0 | S31: =COUNTIFS(input!$O:$O,January!$S$22,input!$F:$F,January!N31,input!$A:$A,January!$B$2) -> 0 | T31: =COUNTIFS(input!$O:$O,January!$T$22,input!$F:$F,January!N31,input!$A:$A,January!$B$2) -> 0 | U31: =COUNTIFS(input!$O:$O,January!$U$22,input!$F:$F,January!N31,input!$A:$A,January!$B$2) -> 0 | V31: =COUNTIFS(input!$O:$O,January!$V$22,input!$F:$F,January!N31,input!$A:$A,January!$B$2) -> 0 | W31: =COUNTIFS(input!$O:$O,January!$W$22,input!$F:$F,January!N31,input!$A:$A,January!$B$2) -> 0 | X31: =COUNTIFS(input!$O:$O,January!$X$22,input!$F:$F,January!N31,input!$A:$A,January!$B$2) -> 0 | Y31: =SUM(Q31:X31) -> 0 | Z31: {=_xlfn.IFS(Y31=0,0,Y31>=1,Y31/Y44)} -> 0
B32: Carpenter | D32: =COUNTIFS(input!$O:$O,January!$D$22,input!$E:$E,January!B32,input!$A:$A,January!$B$2) -> 0 | E32: =COUNTIFS(input!$O:$O,January!$E$22,input!$E:$E,January!B32,input!$A:$A,January!$B$2) -> 0 | F32: =COUNTIFS(input!$O:$O,January!$F$22,input!$E:$E,January!B32,input!$A:$A,January!$B$2) -> 0 | G32: =COUNTIFS(input!$O:$O,January!$G$22,input!$E:$E,January!B32,input!$A:$A,January!$B$2) -> 1 | H32: =COUNTIFS(input!$O:$O,January!$H$22,input!$E:$E,January!B32,input!$A:$A,January!$B$2) -> 0 | I32: =COUNTIFS(input!$O:$O,January!$I$22,input!$E:$E,January!B32,input!$A:$A,January!$B$2) -> 0 | J32: =COUNTIFS(input!$O:$O,January!$J$22,input!$E:$E,January!B32,input!$A:$A,January!$B$2) -> 0 | K32: =COUNTIFS(input!$O:$O,January!$K$22,input!$E:$E,January!B32,input!$A:$A,January!$B$2) -> 0 | L32: =SUM(D32:K32) -> 1 | M32: {=_xlfn.IFS(L32=0,0,L32>=1,L32/L44)} -> 0.076923077 | N32: Over-exertion in lifting objects | Q32: =COUNTIFS(input!$O:$O,January!$Q$22,input!$F:$F,January!N32,input!$A:$A,January!$B$2) -> 0 | R32: =COUNTIFS(input!$O:$O,January!$R$22,input!$F:$F,January!N32,input!$A:$A,January!$B$2) -> 0 | S32: =COUNTIFS(input!$O:$O,January!$S$22,input!$F:$F,January!N32,input!$A:$A,January!$B$2) -> 0 | T32: =COUNTIFS(input!$O:$O,January!$T$22,input!$F:$F,January!N32,input!$A:$A,January!$B$2) -> 0 | U32: =COUNTIFS(input!$O:$O,January!$U$22,input!$F:$F,January!N32,input!$A:$A,January!$B$2) -> 0 | V32: =COUNTIFS(input!$O:$O,January!$V$22,input!$F:$F,January!N32,input!$A:$A,January!$B$2) -> 0 | W32: =COUNTIFS(input!$O:$O,January!$W$22,input!$F:$F,January!N32,input!$A:$A,January!$B$2) -> 0 | X32: =COUNTIFS(input!$O:$O,January!$X$22,input!$F:$F,January!N32,input!$A:$A,January!$B$2) -> 0 | Y32: =SUM(Q32:X32) -> 0 | Z32: {=_xlfn.IFS(Y32=0,0,Y32>=1,Y32/Y44)} -> 0
B33: Maintenance Man (MMME) | D33: =COUNTIFS(input!$O:$O,January!$D$22,input!$E:$E,January!B33,input!$A:$A,January!$B$2) -> 0 | E33: =COUNTIFS(input!$O:$O,January!$E$22,input!$E:$E,January!B33,input!$A:$A,January!$B$2) -> 0 | F33: =COUNTIFS(input!$O:$O,January!$F$22,input!$E:$E,January!B33,input!$A:$A,January!$B$2) -> 0 | G33: =COUNTIFS(input!$O:$O,January!$G$22,input!$E:$E,January!B33,input!$A:$A,January!$B$2) -> 0 | H33: =COUNTIFS(input!$O:$O,January!$H$22,input!$E:$E,January!B33,input!$A:$A,January!$B$2) -> 0 | I33: =COUNTIFS(input!$O:$O,January!$I$22,input!$E:$E,January!B33,input!$A:$A,January!$B$2) -> 1 | J33: =COUNTIFS(input!$O:$O,January!$J$22,input!$E:$E,January!B33,input!$A:$A,January!$B$2) -> 0 | K33: =COUNTIFS(input!$O:$O,January!$K$22,input!$E:$E,January!B33,input!$A:$A,January!$B$2) -> 0 | L33: =SUM(D33:K33) -> 1 | M33: {=_xlfn.IFS(L33=0,0,L33>=1,L33/L44)} -> 0.076923077 | N33: Over-exertion in pushing or pulling objects | Q33: =COUNTIFS(input!$O:$O,January!$Q$22,input!$F:$F,January!N33,input!$A:$A,January!$B$2) -> 0 | R33: =COUNTIFS(input!$O:$O,January!$R$22,input!$F:$F,January!N33,input!$A:$A,January!$B$2) -> 0 | S33: =COUNTIFS(input!$O:$O,January!$S$22,input!$F:$F,January!N33,input!$A:$A,January!$B$2) -> 0 | T33: =COUNTIFS(input!$O:$O,January!$T$22,input!$F:$F,January!N33,input!$A:$A,January!$B$2) -> 0 | U33: =COUNTIFS(input!$O:$O,January!$U$22,input!$F:$F,January!N33,input!$A:$A,January!$B$2) -> 0 | V33: =COUNTIFS(input!$O:$O,January!$V$22,input!$F:$F,January!N33,input!$A:$A,January!$B$2) -> 0 | W33: =COUNTIFS(input!$O:$O,January!$W$22,input!$F:$F,January!N33,input!$A:$A,January!$B$2) -> 0 | X33: =COUNTIFS(input!$O:$O,January!$X$22,input!$F:$F,January!N33,input!$A:$A,January!$B$2) -> 0 | Y33: =SUM(Q33:X33) -> 0 | Z33: {=_xlfn.IFS(Y33=0,0,Y33>=1,Y33/Y44)} -> 0
B34: Mill Operations Aide | D34: =COUNTIFS(input!$O:$O,January!$D$22,input!$E:$E,January!B34,input!$A:$A,January!$B$2) -> 0 | E34: =COUNTIFS(input!$O:$O,January!$E$22,input!$E:$E,January!B34,input!$A:$A,January!$B$2) -> 0 | F34: =COUNTIFS(input!$O:$O,January!$F$22,input!$E:$E,January!B34,input!$A:$A,January!$B$2) -> 0 | G34: =COUNTIFS(input!$O:$O,January!$G$22,input!$E:$E,January!B34,input!$A:$A,January!$B$2) -> 0 | H34: =COUNTIFS(input!$O:$O,January!$H$22,input!$E:$E,January!B34,input!$A:$A,January!$B$2) -> 0 | I34: =COUNTIFS(input!$O:$O,January!$I$22,input!$E:$E,January!B34,input!$A:$A,January!$B$2) -> 0 | J34: =COUNTIFS(input!$O:$O,January!$J$22,input!$E:$E,January!B34,input!$A:$A,January!$B$2) -> 0 | K34: =COUNTIFS(input!$O:$O,January!$K$22,input!$E:$E,January!B34,input!$A:$A,January!$B$2) -> 0 | L34: =SUM(D34:K34) -> 0 | M34: {=_xlfn.IFS(L34=0,0,L34>=1,L34/L44)} -> 0 | N34: Over-exertion in handling or throwing objects | Q34: =COUNTIFS(input!$O:$O,January!$Q$22,input!$F:$F,January!N34,input!$A:$A,January!$B$2) -> 0 | R34: =COUNTIFS(input!$O:$O,January!$R$22,input!$F:$F,January!N34,input!$A:$A,January!$B$2) -> 0 | S34: =COUNTIFS(input!$O:$O,January!$S$22,input!$F:$F,January!N34,input!$A:$A,January!$B$2) -> 0 | T34: =COUNTIFS(input!$O:$O,January!$T$22,input!$F:$F,January!N34,input!$A:$A,January!$B$2) -> 0 | U34: =COUNTIFS(input!$O:$O,January!$U$22,input!$F:$F,January!N34,input!$A:$A,January!$B$2) -> 0 | V34: =COUNTIFS(input!$O:$O,January!$V$22,input!$F:$F,January!N34,input!$A:$A,January!$B$2) -> 0 | W34: =COUNTIFS(input!$O:$O,January!$W$22,input!$F:$F,January!N34,input!$A:$A,January!$B$2) -> 0 | X34: =COUNTIFS(input!$O:$O,January!$X$22,input!$F:$F,January!N34,input!$A:$A,January!$B$2) -> 0 | Y34: =SUM(Q34:X34) -> 0 | Z34: {=_xlfn.IFS(Y34=0,0,Y34>=1,Y34/Y44)} -> 0
B35: GMS Supervisor | D35: =COUNTIFS(input!$O:$O,January!$D$22,input!$E:$E,January!B35,input!$A:$A,January!$B$2) -> 0 | E35: =COUNTIFS(input!$O:$O,January!$E$22,input!$E:$E,January!B35,input!$A:$A,January!$B$2) -> 0 | F35: =COUNTIFS(input!$O:$O,January!$F$22,input!$E:$E,January!B35,input!$A:$A,January!$B$2) -> 0 | G35: =COUNTIFS(input!$O:$O,January!$G$22,input!$E:$E,January!B35,input!$A:$A,January!$B$2) -> 0 | H35: =COUNTIFS(input!$O:$O,January!$H$22,input!$E:$E,January!B35,input!$A:$A,January!$B$2) -> 0 | I35: =COUNTIFS(input!$O:$O,January!$I$22,input!$E:$E,January!B35,input!$A:$A,January!$B$2) -> 0 | J35: =COUNTIFS(input!$O:$O,January!$J$22,input!$E:$E,January!B35,input!$A:$A,January!$B$2) -> 0 | K35: =COUNTIFS(input!$O:$O,January!$K$22,input!$E:$E,January!B35,input!$A:$A,January!$B$2) -> 0 | L35: =SUM(D35:K35) -> 0 | M35: {=_xlfn.IFS(L35=0,0,L35>=1,L35/L44)} -> 0 | N35: Fire | Q35: =COUNTIFS(input!$O:$O,January!$Q$22,input!$F:$F,January!N35,input!$A:$A,January!$B$2) -> 0 | R35: =COUNTIFS(input!$O:$O,January!$R$22,input!$F:$F,January!N35,input!$A:$A,January!$B$2) -> 0 | S35: =COUNTIFS(input!$O:$O,January!$S$22,input!$F:$F,January!N35,input!$A:$A,January!$B$2) -> 0 | T35: =COUNTIFS(input!$O:$O,January!$T$22,input!$F:$F,January!N35,input!$A:$A,January!$B$2) -> 0 | U35: =COUNTIFS(input!$O:$O,January!$U$22,input!$F:$F,January!N35,input!$A:$A,January!$B$2) -> 0 | V35: =COUNTIFS(input!$O:$O,January!$V$22,input!$F:$F,January!N35,input!$A:$A,January!$B$2) -> 0 | W35: =COUNTIFS(input!$O:$O,January!$W$22,input!$F:$F,January!N35,input!$A:$A,January!$B$2) -> 0 | X35: =COUNTIFS(input!$O:$O,January!$X$22,input!$F:$F,January!N35,input!$A:$A,January!$B$2) -> 2 | Y35: =SUM(Q35:X35) -> 2 | Z35: {=_xlfn.IFS(Y35=0,0,Y35>=1,Y35/Y44)} -> 0.15384615
B36: Services Crew | D36: =COUNTIFS(input!$O:$O,January!$D$22,input!$E:$E,January!B36,input!$A:$A,January!$B$2) -> 0 | E36: =COUNTIFS(input!$O:$O,January!$E$22,input!$E:$E,January!B36,input!$A:$A,January!$B$2) -> 0 | F36: =COUNTIFS(input!$O:$O,January!$F$22,input!$E:$E,January!B36,input!$A:$A,January!$B$2) -> 0 | G36: =COUNTIFS(input!$O:$O,January!$G$22,input!$E:$E,January!B36,input!$A:$A,January!$B$2) -> 0 | H36: =COUNTIFS(input!$O:$O,January!$H$22,input!$E:$E,January!B36,input!$A:$A,January!$B$2) -> 0 | I36: =COUNTIFS(input!$O:$O,January!$I$22,input!$E:$E,January!B36,input!$A:$A,January!$B$2) -> 0 | J36: =COUNTIFS(input!$O:$O,January!$J$22,input!$E:$E,January!B36,input!$A:$A,January!$B$2) -> 0 | K36: =COUNTIFS(input!$O:$O,January!$K$22,input!$E:$E,January!B36,input!$A:$A,January!$B$2) -> 0 | L36: =SUM(D36:K36) -> 0 | M36: {=_xlfn.IFS(L36=0,0,L36>=1,L36/L44)} -> 0 | N36: Contact with object | Q36: =COUNTIFS(input!$O:$O,January!$Q$22,input!$F:$F,January!N36,input!$A:$A,January!$B$2) -> 0 | R36: =COUNTIFS(input!$O:$O,January!$R$22,input!$F:$F,January!N36,input!$A:$A,January!$B$2) -> 0 | S36: =COUNTIFS(input!$O:$O,January!$S$22,input!$F:$F,January!N36,input!$A:$A,January!$B$2) -> 0 | T36: =COUNTIFS(input!$O:$O,January!$T$22,input!$F:$F,January!N36,input!$A:$A,January!$B$2) -> 1 | U36: =COUNTIFS(input!$O:$O,January!$U$22,input!$F:$F,January!N36,input!$A:$A,January!$B$2) -> 0 | V36: =COUNTIFS(input!$O:$O,January!$V$22,input!$F:$F,January!N36,input!$A:$A,January!$B$2) -> 0 | W36: =COUNTIFS(input!$O:$O,January!$W$22,input!$F:$F,January!N36,input!$A:$A,January!$B$2) -> 0 | X36: =COUNTIFS(input!$O:$O,January!$X$22,input!$F:$F,January!N36,input!$A:$A,January!$B$2) -> 0 | Y36: =SUM(Q36:X36) -> 1 | Z36: {=_xlfn.IFS(Y36=0,0,Y36>=1,Y36/Y44)} -> 0.076923077
B37: Service Vehicle | D37: =COUNTIFS(input!$O:$O,January!$D$22,input!$E:$E,January!B37,input!$A:$A,January!$B$2) -> 0 | E37: =COUNTIFS(input!$O:$O,January!$E$22,input!$E:$E,January!B37,input!$A:$A,January!$B$2) -> 0 | F37: =COUNTIFS(input!$O:$O,January!$F$22,input!$E:$E,January!B37,input!$A:$A,January!$B$2) -> 0 | G37: =COUNTIFS(input!$O:$O,January!$G$22,input!$E:$E,January!B37,input!$A:$A,January!$B$2) -> 0 | H37: =COUNTIFS(input!$O:$O,January!$H$22,input!$E:$E,January!B37,input!$A:$A,January!$B$2) -> 0 | I37: =COUNTIFS(input!$O:$O,January!$I$22,input!$E:$E,January!B37,input!$A:$A,January!$B$2) -> 0 | J37: =COUNTIFS(input!$O:$O,January!$J$22,input!$E:$E,January!B37,input!$A:$A,January!$B$2) -> 0 | K37: =COUNTIFS(input!$O:$O,January!$K$22,input!$E:$E,January!B37,input!$A:$A,January!$B$2) -> 0 | L37: =SUM(D37:K37) -> 0 | M37: {=_xlfn.IFS(L37=0,0,L37>=1,L37/L44)} -> 0 | N37: Contact with smoke | Q37: =COUNTIFS(input!$O:$O,January!$Q$22,input!$F:$F,January!N37,input!$A:$A,January!$B$2) -> 0 | R37: =COUNTIFS(input!$O:$O,January!$R$22,input!$F:$F,January!N37,input!$A:$A,January!$B$2) -> 0 | S37: =COUNTIFS(input!$O:$O,January!$S$22,input!$F:$F,January!N37,input!$A:$A,January!$B$2) -> 0 | T37: =COUNTIFS(input!$O:$O,January!$T$22,input!$F:$F,January!N37,input!$A:$A,January!$B$2) -> 0 | U37: =COUNTIFS(input!$O:$O,January!$U$22,input!$F:$F,January!N37,input!$A:$A,January!$B$2) -> 0 | V37: =COUNTIFS(input!$O:$O,January!$V$22,input!$F:$F,January!N37,input!$A:$A,January!$B$2) -> 0 | W37: =COUNTIFS(input!$O:$O,January!$W$22,input!$F:$F,January!N37,input!$A:$A,January!$B$2) -> 0 | X37: =COUNTIFS(input!$O:$O,January!$X$22,input!$F:$F,January!N37,input!$A:$A,January!$B$2) -> 0 | Y37: =SUM(Q37:X37) -> 0 | Z37: {=_xlfn.IFS(Y37=0,0,Y37>=1,Y37/Y44)} -> 0
B38: Mechanic | D38: =COUNTIFS(input!$O:$O,January!$D$22,input!$E:$E,January!B38,input!$A:$A,January!$B$2) -> 0 | E38: =COUNTIFS(input!$O:$O,January!$E$22,input!$E:$E,January!B38,input!$A:$A,January!$B$2) -> 0 | F38: =COUNTIFS(input!$O:$O,January!$F$22,input!$E:$E,January!B38,input!$A:$A,January!$B$2) -> 0 | G38: =COUNTIFS(input!$O:$O,January!$G$22,input!$E:$E,January!B38,input!$A:$A,January!$B$2) -> 0 | H38: =COUNTIFS(input!$O:$O,January!$H$22,input!$E:$E,January!B38,input!$A:$A,January!$B$2) -> 0 | I38: =COUNTIFS(input!$O:$O,January!$I$22,input!$E:$E,January!B38,input!$A:$A,January!$B$2) -> 0 | J38: =COUNTIFS(input!$O:$O,January!$J$22,input!$E:$E,January!B38,input!$A:$A,January!$B$2) -> 0 | K38: =COUNTIFS(input!$O:$O,January!$K$22,input!$E:$E,January!B38,input!$A:$A,January!$B$2) -> 0 | L38: =SUM(D38:K38) -> 0 | M38: {=_xlfn.IFS(L38=0,0,L38>=1,L38/L44)} -> 0 | N38: Contact or exposure to extreme temperatures | Q38: =COUNTIFS(input!$O:$O,January!$Q$22,input!$F:$F,January!N38,input!$A:$A,January!$B$2) -> 0 | R38: =COUNTIFS(input!$O:$O,January!$R$22,input!$F:$F,January!N38,input!$A:$A,January!$B$2) -> 0 | S38: =COUNTIFS(input!$O:$O,January!$S$22,input!$F:$F,January!N38,input!$A:$A,January!$B$2) -> 0 | T38: =COUNTIFS(input!$O:$O,January!$T$22,input!$F:$F,January!N38,input!$A:$A,January!$B$2) -> 0 | U38: =COUNTIFS(input!$O:$O,January!$U$22,input!$F:$F,January!N38,input!$A:$A,January!$B$2) -> 0 | V38: =COUNTIFS(input!$O:$O,January!$V$22,input!$F:$F,January!N38,input!$A:$A,January!$B$2) -> 0 | W38: =COUNTIFS(input!$O:$O,January!$W$22,input!$F:$F,January!N38,input!$A:$A,January!$B$2) -> 0 | X38: =COUNTIFS(input!$O:$O,January!$X$22,input!$F:$F,January!N38,input!$A:$A,January!$B$2) -> 0 | Y38: =SUM(Q38:X38) -> 0 | Z38: {=_xlfn.IFS(Y38=0,0,Y38>=1,Y38/Y44)} -> 0
B39: Welding Machine | D39: =COUNTIFS(input!$O:$O,January!$D$22,input!$E:$E,January!B39,input!$A:$A,January!$B$2) -> 0 | E39: =COUNTIFS(input!$O:$O,January!$E$22,input!$E:$E,January!B39,input!$A:$A,January!$B$2) -> 0 | F39: =COUNTIFS(input!$O:$O,January!$F$22,input!$E:$E,January!B39,input!$A:$A,January!$B$2) -> 0 | G39: =COUNTIFS(input!$O:$O,January!$G$22,input!$E:$E,January!B39,input!$A:$A,January!$B$2) -> 0 | H39: =COUNTIFS(input!$O:$O,January!$H$22,input!$E:$E,January!B39,input!$A:$A,January!$B$2) -> 0 | I39: =COUNTIFS(input!$O:$O,January!$I$22,input!$E:$E,January!B39,input!$A:$A,January!$B$2) -> 0 | J39: =COUNTIFS(input!$O:$O,January!$J$22,input!$E:$E,January!B39,input!$A:$A,January!$B$2) -> 0 | K39: =COUNTIFS(input!$O:$O,January!$K$22,input!$E:$E,January!B39,input!$A:$A,January!$B$2) -> 0 | L39: =SUM(D39:K39) -> 0 | M39: {=_xlfn.IFS(L39=0,0,L39>=1,L39/L44)} -> 0 | N39: Exposure to radiation | Q39: =COUNTIFS(input!$O:$O,January!$Q$22,input!$F:$F,January!N39,input!$A:$A,January!$B$2) -> 0 | R39: =COUNTIFS(input!$O:$O,January!$R$22,input!$F:$F,January!N39,input!$A:$A,January!$B$2) -> 0 | S39: =COUNTIFS(input!$O:$O,January!$S$22,input!$F:$F,January!N39,input!$A:$A,January!$B$2) -> 0 | T39: =COUNTIFS(input!$O:$O,January!$T$22,input!$F:$F,January!N39,input!$A:$A,January!$B$2) -> 0 | U39: =COUNTIFS(input!$O:$O,January!$U$22,input!$F:$F,January!N39,input!$A:$A,January!$B$2) -> 0 | V39: =COUNTIFS(input!$O:$O,January!$V$22,input!$F:$F,January!N39,input!$A:$A,January!$B$2) -> 0 | W39: =COUNTIFS(input!$O:$O,January!$W$22,input!$F:$F,January!N39,input!$A:$A,January!$B$2) -> 0 | X39: =COUNTIFS(input!$O:$O,January!$X$22,input!$F:$F,January!N39,input!$A:$A,January!$B$2) -> 0 | Y39: =SUM(Q39:X39) -> 0 | Z39: {=_xlfn.IFS(Y39=0,0,Y39>=1,Y39/Y44)} -> 0
B40: Shipside - Volvo Truck | D40: =COUNTIFS(input!$O:$O,January!$D$22,input!$E:$E,January!B40,input!$A:$A,January!$B$2) -> 0 | E40: =COUNTIFS(input!$O:$O,January!$E$22,input!$E:$E,January!B40,input!$A:$A,January!$B$2) -> 0 | F40: =COUNTIFS(input!$O:$O,January!$F$22,input!$E:$E,January!B40,input!$A:$A,January!$B$2) -> 0 | G40: =COUNTIFS(input!$O:$O,January!$G$22,input!$E:$E,January!B40,input!$A:$A,January!$B$2) -> 0 | H40: =COUNTIFS(input!$O:$O,January!$H$22,input!$E:$E,January!B40,input!$A:$A,January!$B$2) -> 0 | I40: =COUNTIFS(input!$O:$O,January!$I$22,input!$E:$E,January!B40,input!$A:$A,January!$B$2) -> 0 | J40: =COUNTIFS(input!$O:$O,January!$J$22,input!$E:$E,January!B40,input!$A:$A,January!$B$2) -> 0 | K40: =COUNTIFS(input!$O:$O,January!$K$22,input!$E:$E,January!B40,input!$A:$A,January!$B$2) -> 1 | L40: =SUM(D40:K40) -> 1 | M40: {=_xlfn.IFS(L40=0,0,L40>=1,L40/L44)} -> 0.076923077 | N40: Foreign Object in the eye/s | Q40: =COUNTIFS(input!$O:$O,January!$Q$22,input!$F:$F,January!N40,input!$A:$A,January!$B$2) -> 0 | R40: =COUNTIFS(input!$O:$O,January!$R$22,input!$F:$F,January!N40,input!$A:$A,January!$B$2) -> 0 | S40: =COUNTIFS(input!$O:$O,January!$S$22,input!$F:$F,January!N40,input!$A:$A,January!$B$2) -> 0 | T40: =COUNTIFS(input!$O:$O,January!$T$22,input!$F:$F,January!N40,input!$A:$A,January!$B$2) -> 1 | U40: =COUNTIFS(input!$O:$O,January!$U$22,input!$F:$F,January!N40,input!$A:$A,January!$B$2) -> 0 | V40: =COUNTIFS(input!$O:$O,January!$V$22,input!$F:$F,January!N40,input!$A:$A,January!$B$2) -> 0 | W40: =COUNTIFS(input!$O:$O,January!$W$22,input!$F:$F,January!N40,input!$A:$A,January!$B$2) -> 0 | X40: =COUNTIFS(input!$O:$O,January!$X$22,input!$F:$F,January!N40,input!$A:$A,January!$B$2) -> 0 | Y40: =SUM(Q40:X40) -> 1 | Z40: {=_xlfn.IFS(Y40=0,0,Y40>=1,Y40/Y44)} -> 0.076923077
B41: Garbage Fire | D41: =COUNTIFS(input!$O:$O,January!$D$22,input!$E:$E,January!B41,input!$A:$A,January!$B$2) -> 0 | E41: =COUNTIFS(input!$O:$O,January!$E$22,input!$E:$E,January!B41,input!$A:$A,January!$B$2) -> 0 | F41: =COUNTIFS(input!$O:$O,January!$F$22,input!$E:$E,January!B41,input!$A:$A,January!$B$2) -> 0 | G41: =COUNTIFS(input!$O:$O,January!$G$22,input!$E:$E,January!B41,input!$A:$A,January!$B$2) -> 0 | H41: =COUNTIFS(input!$O:$O,January!$H$22,input!$E:$E,January!B41,input!$A:$A,January!$B$2) -> 0 | I41: =COUNTIFS(input!$O:$O,January!$I$22,input!$E:$E,January!B41,input!$A:$A,January!$B$2) -> 0 | J41: =COUNTIFS(input!$O:$O,January!$J$22,input!$E:$E,January!B41,input!$A:$A,January!$B$2) -> 0 | K41: =COUNTIFS(input!$O:$O,January!$K$22,input!$E:$E,January!B41,input!$A:$A,January!$B$2) -> 0 | L41: =SUM(D41:K41) -> 0 | M41: {=_xlfn.IFS(L41=0,0,L41>=1,L41/L44)} -> 0 | N41: Eye contact with foreign object | Q41: =COUNTIFS(input!$O:$O,January!$Q$22,input!$F:$F,January!N41,input!$A:$A,January!$B$2) -> 0 | R41: =COUNTIFS(input!$O:$O,January!$R$22,input!$F:$F,January!N41,input!$A:$A,January!$B$2) -> 0 | S41: =COUNTIFS(input!$O:$O,January!$S$22,input!$F:$F,January!N41,input!$A:$A,January!$B$2) -> 0 | T41: =COUNTIFS(input!$O:$O,January!$T$22,input!$F:$F,January!N41,input!$A:$A,January!$B$2) -> 0 | U41: =COUNTIFS(input!$O:$O,January!$U$22,input!$F:$F,January!N41,input!$A:$A,January!$B$2) -> 0 | V41: =COUNTIFS(input!$O:$O,January!$V$22,input!$F:$F,January!N41,input!$A:$A,January!$B$2) -> 0 | W41: =COUNTIFS(input!$O:$O,January!$W$22,input!$F:$F,January!N41,input!$A:$A,January!$B$2) -> 0 | X41: =COUNTIFS(input!$O:$O,January!$X$22,input!$F:$F,January!N41,input!$A:$A,January!$B$2) -> 0 | Y41: =SUM(Q41:X41) -> 0 | Z41: {=_xlfn.IFS(Y41=0,0,Y41>=1,Y41/Y45)} -> 0
B42: Forest Fire | D42: =COUNTIFS(input!$O:$O,January!$D$22,input!$E:$E,January!B42,input!$A:$A,January!$B$2) -> 0 | E42: =COUNTIFS(input!$O:$O,January!$E$22,input!$E:$E,January!B42,input!$A:$A,January!$B$2) -> 0 | F42: =COUNTIFS(input!$O:$O,January!$F$22,input!$E:$E,January!B42,input!$A:$A,January!$B$2) -> 0 | G42: =COUNTIFS(input!$O:$O,January!$G$22,input!$E:$E,January!B42,input!$A:$A,January!$B$2) -> 0 | H42: =COUNTIFS(input!$O:$O,January!$H$22,input!$E:$E,January!B42,input!$A:$A,January!$B$2) -> 0 | I42: =COUNTIFS(input!$O:$O,January!$I$22,input!$E:$E,January!B42,input!$A:$A,January!$B$2) -> 0 | J42: =COUNTIFS(input!$O:$O,January!$J$22,input!$E:$E,January!B42,input!$A:$A,January!$B$2) -> 0 | K42: =COUNTIFS(input!$O:$O,January!$K$22,input!$E:$E,January!B42,input!$A:$A,January!$B$2) -> 2 | L42: =SUM(D42:K42) -> 2 | M42: {=_xlfn.IFS(L42=0,0,L42>=1,L42/L44)} -> 0.15384615 | N42: Occupational Illness / Pain | Q42: =COUNTIFS(input!$O:$O,January!$Q$22,input!$F:$F,January!N42,input!$A:$A,January!$B$2) -> 0 | R42: =COUNTIFS(input!$O:$O,January!$R$22,input!$F:$F,January!N42,input!$A:$A,January!$B$2) -> 0 | S42: =COUNTIFS(input!$O:$O,January!$S$22,input!$F:$F,January!N42,input!$A:$A,January!$B$2) -> 0 | T42: =COUNTIFS(input!$O:$O,January!$T$22,input!$F:$F,January!N42,input!$A:$A,January!$B$2) -> 0 | U42: =COUNTIFS(input!$O:$O,January!$U$22,input!$F:$F,January!N42,input!$A:$A,January!$B$2) -> 0 | V42: =COUNTIFS(input!$O:$O,January!$V$22,input!$F:$F,January!N42,input!$A:$A,January!$B$2) -> 2 | W42: =COUNTIFS(input!$O:$O,January!$W$22,input!$F:$F,January!N42,input!$A:$A,January!$B$2) -> 0 | X42: =COUNTIFS(input!$O:$O,January!$X$22,input!$F:$F,January!N42,input!$A:$A,January!$B$2) -> 0 | Y42: =SUM(Q42:X42) -> 2 | Z42: {=_xlfn.IFS(Y42=0,0,Y42>=1,Y42/Y44)} -> 0.15384615
B43: Fuse Cut-Off Switch | D43: =COUNTIFS(input!$O:$O,January!$D$22,input!$E:$E,January!B43,input!$A:$A,January!$B$2) -> 0 | E43: =COUNTIFS(input!$O:$O,January!$E$22,input!$E:$E,January!B43,input!$A:$A,January!$B$2) -> 0 | F43: =COUNTIFS(input!$O:$O,January!$F$22,input!$E:$E,January!B43,input!$A:$A,January!$B$2) -> 0 | G43: =COUNTIFS(input!$O:$O,January!$G$22,input!$E:$E,January!B43,input!$A:$A,January!$B$2) -> 0 | H43: =COUNTIFS(input!$O:$O,January!$H$22,input!$E:$E,January!B43,input!$A:$A,January!$B$2) -> 0 | I43: =COUNTIFS(input!$O:$O,January!$I$22,input!$E:$E,January!B43,input!$A:$A,January!$B$2) -> 0 | J43: =COUNTIFS(input!$O:$O,January!$J$22,input!$E:$E,January!B43,input!$A:$A,January!$B$2) -> 1 | K43: =COUNTIFS(input!$O:$O,January!$K$22,input!$E:$E,January!B43,input!$A:$A,January!$B$2) -> 0 | L43: =SUM(D43:K43) -> 1 | M43: {=_xlfn.IFS(L43=0,0,L43>=1,L43/L44)} -> 0.076923077 | N43: Property Damage | Q43: =COUNTIFS(input!$O:$O,January!$Q$22,input!$F:$F,January!N43,input!$A:$A,January!$B$2) -> 0 | R43: =COUNTIFS(input!$O:$O,January!$R$22,input!$F:$F,January!N43,input!$A:$A,January!$B$2) -> 0 | S43: =COUNTIFS(input!$O:$O,January!$S$22,input!$F:$F,January!N43,input!$A:$A,January!$B$2) -> 0 | T43: =COUNTIFS(input!$O:$O,January!$T$22,input!$F:$F,January!N43,input!$A:$A,January!$B$2) -> 0 | U43: =COUNTIFS(input!$O:$O,January!$U$22,input!$F:$F,January!N43,input!$A:$A,January!$B$2) -> 0 | V43: =COUNTIFS(input!$O:$O,January!$V$22,input!$F:$F,January!N43,input!$A:$A,January!$B$2) -> 0 | W43: =COUNTIFS(input!$O:$O,January!$W$22,input!$F:$F,January!N43,input!$A:$A,January!$B$2) -> 1 | X43: =COUNTIFS(input!$O:$O,January!$X$22,input!$F:$F,January!N43,input!$A:$A,January!$B$2) -> 0 | Y43: =SUM(Q43:X43) -> 1 | Z43: {=_xlfn.IFS(Y43=0,0,Y43>=1,Y43/Y44)} -> 0.076923077
B44: TOTAL | D44: =SUM(D23:D43) -> 1 | E44: =SUM(E23:E43) -> 1 | F44: =SUM(F23:F43) -> 0 | G44: =SUM(G23:G43) -> 5 | H44: =SUM(H23:H43) -> 0 | I44: =SUM(I23:I43) -> 2 | J44: =SUM(J23:J43) -> 1 | K44: =SUM(K23:K43) -> 3 | ... M44: =SUM(M23:M43) -> 1 | N44: TOTAL | Q44: =SUM(Q23:Q43) -> 1 | R44: =SUM(R23:R43) -> 1 | S44: =SUM(S23:S43) -> 0 | T44: =SUM(T23:T43) -> 5 | U44: =SUM(U23:U43) -> 0 | V44: =SUM(V23:V43) -> 2 | W44: =SUM(W23:W43) -> 1 | X44: =SUM(X23:X43) -> 3 | ... Z44: =SUM(Z23:Z43) -> 1
B45: Shift of Incident | D45: LTA-F | E45: LTA-NF | F45: NLTA | G45: FAC | H45: NM | I45: OI | J45: PD | K45: EI | L45: Total | M45: % Distribution | N45: Work Place / Area | Q45: LTA-F | R45: LTA-NF | S45: NLTA | T45: FAC | U45: NM | V45: OI | W45: PD | X45: EI | Y45: Total | Z45: % Distribution
B46: First | D46: =COUNTIFS(input!$O:$O,January!$D$45,input!$K:$K,January!B46,input!$A:$A,January!$B$2) -> 0 | E46: =COUNTIFS(input!$O:$O,January!$E$45,input!$K:$K,January!B46,input!$A:$A,January!$B$2) -> 0 | F46: =COUNTIFS(input!$O:$O,January!$F$45,input!$K:$K,January!B46,input!$A:$A,January!$B$2) -> 0 | G46: =COUNTIFS(input!$O:$O,January!$G$45,input!$K:$K,January!B46,input!$A:$A,January!$B$2) -> 1 | H46: =COUNTIFS(input!$O:$O,January!$H$45,input!$K:$K,January!B46,input!$A:$A,January!$B$2) -> 0 | I46: =COUNTIFS(input!$O:$O,January!$I$45,input!$K:$K,January!B46,input!$A:$A,January!$B$2) -> 0 | J46: =COUNTIFS(input!$O:$O,January!$J$45,input!$K:$K,January!B46,input!$A:$A,January!$B$2) -> 0 | K46: =COUNTIFS(input!$O:$O,January!$K$45,input!$K:$K,January!B46,input!$A:$A,January!$B$2) -> 0 | L46: =SUM(D46:K50) -> 1 | M46: {=_xlfn.IFS(L46=0,0,L46>=1,L46/L61)} -> 0.076923077 | N46: Stope | Q46: =COUNTIFS(input!$O:$O,January!$Q$45,input!$G:$G,January!N46,input!$A:$A,January!$B$2) -> 0 | R46: =COUNTIFS(input!$O:$O,January!$R$45,input!$G:$G,January!N46,input!$A:$A,January!$B$2) -> 0 | S46: =COUNTIFS(input!$O:$O,January!$S$45,input!$G:$G,January!N46,input!$A:$A,January!$B$2) -> 0 | T46: =COUNTIFS(input!$O:$O,January!$T$45,input!$G:$G,January!N46,input!$A:$A,January!$B$2) -> 1 | U46: =COUNTIFS(input!$O:$O,January!$U$45,input!$G:$G,January!N46,input!$A:$A,January!$B$2) -> 0 | V46: =COUNTIFS(input!$O:$O,January!$V$45,input!$G:$G,January!N46,input!$A:$A,January!$B$2) -> 0 | W46: =COUNTIFS(input!$O:$O,January!$W$45,input!$G:$G,January!N46,input!$A:$A,January!$B$2) -> 0 | X46: =COUNTIFS(input!$O:$O,January!$X$45,input!$G:$G,January!N46,input!$A:$A,January!$B$2) -> 0 | Y46: =SUM(Q46:X46) -> 1 | Z46: {=_xlfn.IFS(Y46=0,0,Y46>=1,Y46/Y$61)} -> 0.076923077
D47: =COUNTIFS(input!O:O,January!$D$22,input!E:E,January!B47) -> 0 | E47: =COUNTIFS(input!P:P,January!$D$22,input!F:F,January!C47) -> 0 | F47: =COUNTIFS(input!Q:Q,January!$D$22,input!G:G,January!D47) -> 0 | G47: =COUNTIFS(input!R:R,January!$D$22,input!H:H,January!E47) -> 0 | H47: =COUNTIFS(input!S:S,January!$D$22,input!I:I,January!F47) -> 0 | I47: =COUNTIFS(input!T:T,January!$D$22,input!J:J,January!G47) -> 0 | J47: =COUNTIFS(input!U:U,January!$D$22,input!K:K,January!H47) -> 0 | K47: =COUNTIFS(input!V:V,January!$D$22,input!L:L,January!I47) -> 0 | N47: Development | Q47: =COUNTIFS(input!$O:$O,January!$Q$45,input!$G:$G,January!N47,input!$A:$A,January!$B$2) -> 0 | R47: =COUNTIFS(input!$O:$O,January!$R$45,input!$G:$G,January!N47,input!$A:$A,January!$B$2) -> 0 | S47: =COUNTIFS(input!$O:$O,January!$S$45,input!$G:$G,January!N47,input!$A:$A,January!$B$2) -> 0 | T47: =COUNTIFS(input!$O:$O,January!$T$45,input!$G:$G,January!N47,input!$A:$A,January!$B$2) -> 0 | U47: =COUNTIFS(input!$O:$O,January!$U$45,input!$G:$G,January!N47,input!$A:$A,January!$B$2) -> 0 | V47: =COUNTIFS(input!$O:$O,January!$V$45,input!$G:$G,January!N47,input!$A:$A,January!$B$2) -> 0 | W47: =COUNTIFS(input!$O:$O,January!$W$45,input!$G:$G,January!N47,input!$A:$A,January!$B$2) -> 0 | X47: =COUNTIFS(input!$O:$O,January!$X$45,input!$G:$G,January!N47,input!$A:$A,January!$B$2) -> 0 | Y47: =SUM(Q47:X47) -> 0 | Z47: {=_xlfn.IFS(Y47=0,0,Y47>=1,Y47/Y$61)} -> 0
D48: =COUNTIFS(input!O:O,January!$D$22,input!E:E,January!B48) -> 0 | E48: =COUNTIFS(input!P:P,January!$D$22,input!F:F,January!C48) -> 0 | F48: =COUNTIFS(input!Q:Q,January!$D$22,input!G:G,January!D48) -> 0 | G48: =COUNTIFS(input!R:R,January!$D$22,input!H:H,January!E48) -> 0 | H48: =COUNTIFS(input!S:S,January!$D$22,input!I:I,January!F48) -> 0 | I48: =COUNTIFS(input!T:T,January!$D$22,input!J:J,January!G48) -> 0 | J48: =COUNTIFS(input!U:U,January!$D$22,input!K:K,January!H48) -> 0 | K48: =COUNTIFS(input!V:V,January!$D$22,input!L:L,January!I48) -> 0 | N48: Raise | Q48: =COUNTIFS(input!$O:$O,January!$Q$45,input!$G:$G,January!N48,input!$A:$A,January!$B$2) -> 0 | R48: =COUNTIFS(input!$O:$O,January!$R$45,input!$G:$G,January!N48,input!$A:$A,January!$B$2) -> 0 | S48: =COUNTIFS(input!$O:$O,January!$S$45,input!$G:$G,January!N48,input!$A:$A,January!$B$2) -> 0 | T48: =COUNTIFS(input!$O:$O,January!$T$45,input!$G:$G,January!N48,input!$A:$A,January!$B$2) -> 0 | U48: =COUNTIFS(input!$O:$O,January!$U$45,input!$G:$G,January!N48,input!$A:$A,January!$B$2) -> 0 | V48: =COUNTIFS(input!$O:$O,January!$V$45,input!$G:$G,January!N48,input!$A:$A,January!$B$2) -> 0 | W48: =COUNTIFS(input!$O:$O,January!$W$45,input!$G:$G,January!N48,input!$A:$A,January!$B$2) -> 0 | X48: =COUNTIFS(input!$O:$O,January!$X$45,input!$G:$G,January!N48,input!$A:$A,January!$B$2) -> 0 | Y48: =SUM(Q48:X48) -> 0 | Z48: {=_xlfn.IFS(Y48=0,0,Y48>=1,Y48/Y$61)} -> 0
N49: Ramp | Q49: =COUNTIFS(input!$O:$O,January!$Q$45,input!$G:$G,January!N49,input!$A:$A,January!$B$2) -> 1 | R49: =COUNTIFS(input!$O:$O,January!$R$45,input!$G:$G,January!N49,input!$A:$A,January!$B$2) -> 0 | S49: =COUNTIFS(input!$O:$O,January!$S$45,input!$G:$G,January!N49,input!$A:$A,January!$B$2) -> 0 | T49: =COUNTIFS(input!$O:$O,January!$T$45,input!$G:$G,January!N49,input!$A:$A,January!$B$2) -> 1 | U49: =COUNTIFS(input!$O:$O,January!$U$45,input!$G:$G,January!N49,input!$A:$A,January!$B$2) -> 0 | V49: =COUNTIFS(input!$O:$O,January!$V$45,input!$G:$G,January!N49,input!$A:$A,January!$B$2) -> 0 | W49: =COUNTIFS(input!$O:$O,January!$W$45,input!$G:$G,January!N49,input!$A:$A,January!$B$2) -> 0 | X49: =COUNTIFS(input!$O:$O,January!$X$45,input!$G:$G,January!N49,input!$A:$A,January!$B$2) -> 0 | Y49: =SUM(Q49:X49) -> 2 | Z49: {=_xlfn.IFS(Y49=0,0,Y49>=1,Y49/Y$61)} -> 0.15384615
D50: =COUNTIFS(input!O:O,January!$D$22,input!E:E,January!B50) -> 0 | E50: =COUNTIFS(input!P:P,January!$D$22,input!F:F,January!C50) -> 0 | F50: =COUNTIFS(input!Q:Q,January!$D$22,input!G:G,January!D50) -> 0 | G50: =COUNTIFS(input!R:R,January!$D$22,input!H:H,January!E50) -> 0 | H50: =COUNTIFS(input!S:S,January!$D$22,input!I:I,January!F50) -> 0 | I50: =COUNTIFS(input!T:T,January!$D$22,input!J:J,January!G50) -> 0 | J50: =COUNTIFS(input!U:U,January!$D$22,input!K:K,January!H50) -> 0 | K50: =COUNTIFS(input!V:V,January!$D$22,input!L:L,January!I50) -> 0 | N50: Conveyor | Q50: =COUNTIFS(input!$O:$O,January!$Q$45,input!$G:$G,January!N50,input!$A:$A,January!$B$2) -> 0 | R50: =COUNTIFS(input!$O:$O,January!$R$45,input!$G:$G,January!N50,input!$A:$A,January!$B$2) -> 0 | S50: =COUNTIFS(input!$O:$O,January!$S$45,input!$G:$G,January!N50,input!$A:$A,January!$B$2) -> 0 | T50: =COUNTIFS(input!$O:$O,January!$T$45,input!$G:$G,January!N50,input!$A:$A,January!$B$2) -> 0 | U50: =COUNTIFS(input!$O:$O,January!$U$45,input!$G:$G,January!N50,input!$A:$A,January!$B$2) -> 0 | V50: =COUNTIFS(input!$O:$O,January!$V$45,input!$G:$G,January!N50,input!$A:$A,January!$B$2) -> 0 | W50: =COUNTIFS(input!$O:$O,January!$W$45,input!$G:$G,January!N50,input!$A:$A,January!$B$2) -> 0 | X50: =COUNTIFS(input!$O:$O,January!$X$45,input!$G:$G,January!N50,input!$A:$A,January!$B$2) -> 0 | Y50: =SUM(Q50:X50) -> 0 | Z50: {=_xlfn.IFS(Y50=0,0,Y50>=1,Y50/Y$61)} -> 0
B51: Second | D51: =COUNTIFS(input!$O:$O,January!$D$45,input!$K:$K,January!B51,input!$A:$A,January!$B$2) -> 0 | E51: =COUNTIFS(input!$O:$O,January!$E$45,input!$K:$K,January!B51,input!$A:$A,January!$B$2) -> 1 | F51: =COUNTIFS(input!$O:$O,January!$F$45,input!$K:$K,January!B51,input!$A:$A,January!$B$2) -> 0 | G51: =COUNTIFS(input!$O:$O,January!$G$45,input!$K:$K,January!B51,input!$A:$A,January!$B$2) -> 4 | H51: =COUNTIFS(input!$O:$O,January!$H$45,input!$K:$K,January!B51,input!$A:$A,January!$B$2) -> 0 | I51: =COUNTIFS(input!$O:$O,January!$I$45,input!$K:$K,January!B51,input!$A:$A,January!$B$2) -> 2 | J51: =COUNTIFS(input!$O:$O,January!$J$45,input!$K:$K,January!B51,input!$A:$A,January!$B$2) -> 0 | K51: =COUNTIFS(input!$O:$O,January!$K$45,input!$K:$K,January!B51,input!$A:$A,January!$B$2) -> 2 | L51: =SUM(D51:K55) -> 9 | M51: =_xlfn.IFS(L51=0,0,L51>=1,L51/L61) -> 0.69230769 | N51: Shaft Station / Resting Area | Q51: =COUNTIFS(input!$O:$O,January!$Q$45,input!$G:$G,January!N51,input!$A:$A,January!$B$2) -> 0 | R51: =COUNTIFS(input!$O:$O,January!$R$45,input!$G:$G,January!N51,input!$A:$A,January!$B$2) -> 0 | S51: =COUNTIFS(input!$O:$O,January!$S$45,input!$G:$G,January!N51,input!$A:$A,January!$B$2) -> 0 | T51: =COUNTIFS(input!$O:$O,January!$T$45,input!$G:$G,January!N51,input!$A:$A,January!$B$2) -> 0 | U51: =COUNTIFS(input!$O:$O,January!$U$45,input!$G:$G,January!N51,input!$A:$A,January!$B$2) -> 0 | V51: =COUNTIFS(input!$O:$O,January!$V$45,input!$G:$G,January!N51,input!$A:$A,January!$B$2) -> 2 | W51: =COUNTIFS(input!$O:$O,January!$W$45,input!$G:$G,January!N51,input!$A:$A,January!$B$2) -> 0 | X51: =COUNTIFS(input!$O:$O,January!$X$45,input!$G:$G,January!N51,input!$A:$A,January!$B$2) -> 0 | Y51: =SUM(Q51:X51) -> 2 | Z51: {=_xlfn.IFS(Y51=0,0,Y51>=1,Y51/Y$61)} -> 0.15384615
D52: =COUNTIFS(input!O:O,January!$D$22,input!E:E,January!B52) -> 0 | E52: =COUNTIFS(input!P:P,January!$D$22,input!F:F,January!C52) -> 0 | F52: =COUNTIFS(input!Q:Q,January!$D$22,input!G:G,January!D52) -> 0 | G52: =COUNTIFS(input!R:R,January!$D$22,input!H:H,January!E52) -> 0 | H52: =COUNTIFS(input!S:S,January!$D$22,input!I:I,January!F52) -> 0 | I52: =COUNTIFS(input!T:T,January!$D$22,input!J:J,January!G52) -> 0 | J52: =COUNTIFS(input!U:U,January!$D$22,input!K:K,January!H52) -> 0 | K52: =COUNTIFS(input!V:V,January!$D$22,input!L:L,January!I52) -> 0 | N52: Cuddy | Q52: =COUNTIFS(input!$O:$O,January!$Q$45,input!$G:$G,January!N52,input!$A:$A,January!$B$2) -> 0 | R52: =COUNTIFS(input!$O:$O,January!$R$45,input!$G:$G,January!N52,input!$A:$A,January!$B$2) -> 0 | S52: =COUNTIFS(input!$O:$O,January!$S$45,input!$G:$G,January!N52,input!$A:$A,January!$B$2) -> 0 | T52: =COUNTIFS(input!$O:$O,January!$T$45,input!$G:$G,January!N52,input!$A:$A,January!$B$2) -> 0 | U52: =COUNTIFS(input!$O:$O,January!$U$45,input!$G:$G,January!N52,input!$A:$A,January!$B$2) -> 0 | V52: =COUNTIFS(input!$O:$O,January!$V$45,input!$G:$G,January!N52,input!$A:$A,January!$B$2) -> 0 | W52: =COUNTIFS(input!$O:$O,January!$W$45,input!$G:$G,January!N52,input!$A:$A,January!$B$2) -> 0 | X52: =COUNTIFS(input!$O:$O,January!$X$45,input!$G:$G,January!N52,input!$A:$A,January!$B$2) -> 0 | Y52: =SUM(Q52:X52) -> 0 | Z52: {=_xlfn.IFS(Y52=0,0,Y52>=1,Y52/Y$61)} -> 0
N53: UG Crusher | Q53: =COUNTIFS(input!$O:$O,January!$Q$45,input!$G:$G,January!N53,input!$A:$A,January!$B$2) -> 0 | R53: =COUNTIFS(input!$O:$O,January!$R$45,input!$G:$G,January!N53,input!$A:$A,January!$B$2) -> 0 | S53: =COUNTIFS(input!$O:$O,January!$S$45,input!$G:$G,January!N53,input!$A:$A,January!$B$2) -> 0 | T53: =COUNTIFS(input!$O:$O,January!$T$45,input!$G:$G,January!N53,input!$A:$A,January!$B$2) -> 0 | U53: =COUNTIFS(input!$O:$O,January!$U$45,input!$G:$G,January!N53,input!$A:$A,January!$B$2) -> 0 | V53: =COUNTIFS(input!$O:$O,January!$V$45,input!$G:$G,January!N53,input!$A:$A,January!$B$2) -> 0 | W53: =COUNTIFS(input!$O:$O,January!$W$45,input!$G:$G,January!N53,input!$A:$A,January!$B$2) -> 1 | X53: =COUNTIFS(input!$O:$O,January!$X$45,input!$G:$G,January!N53,input!$A:$A,January!$B$2) -> 0 | Y53: =SUM(Q53:X53) -> 1 | Z53: {=_xlfn.IFS(Y53=0,0,Y53>=1,Y53/Y$61)} -> 0.076923077
D54: =COUNTIFS(input!O:O,January!$D$22,input!E:E,January!B54) -> 0 | E54: =COUNTIFS(input!P:P,January!$D$22,input!F:F,January!C54) -> 0 | F54: =COUNTIFS(input!Q:Q,January!$D$22,input!G:G,January!D54) -> 0 | G54: =COUNTIFS(input!R:R,January!$D$22,input!H:H,January!E54) -> 0 | H54: =COUNTIFS(input!S:S,January!$D$22,input!I:I,January!F54) -> 0 | I54: =COUNTIFS(input!T:T,January!$D$22,input!J:J,January!G54) -> 0 | J54: =COUNTIFS(input!U:U,January!$D$22,input!K:K,January!H54) -> 0 | K54: =COUNTIFS(input!V:V,January!$D$22,input!L:L,January!I54) -> 0 | N54: Hospital | Q54: =COUNTIFS(input!$O:$O,January!$Q$45,input!$G:$G,January!N54,input!$A:$A,January!$B$2) -> 0 | R54: =COUNTIFS(input!$O:$O,January!$R$45,input!$G:$G,January!N54,input!$A:$A,January!$B$2) -> 0 | S54: =COUNTIFS(input!$O:$O,January!$S$45,input!$G:$G,January!N54,input!$A:$A,January!$B$2) -> 0 | T54: =COUNTIFS(input!$O:$O,January!$T$45,input!$G:$G,January!N54,input!$A:$A,January!$B$2) -> 1 | U54: =COUNTIFS(input!$O:$O,January!$U$45,input!$G:$G,January!N54,input!$A:$A,January!$B$2) -> 0 | V54: =COUNTIFS(input!$O:$O,January!$V$45,input!$G:$G,January!N54,input!$A:$A,January!$B$2) -> 0 | W54: =COUNTIFS(input!$O:$O,January!$W$45,input!$G:$G,January!N54,input!$A:$A,January!$B$2) -> 0 | X54: =COUNTIFS(input!$O:$O,January!$X$45,input!$G:$G,January!N54,input!$A:$A,January!$B$2) -> 0 | Y54: =SUM(Q54:X54) -> 1 | Z54: {=_xlfn.IFS(Y54=0,0,Y54>=1,Y54/Y$61)} -> 0.076923077
D55: =COUNTIFS(input!O:O,January!$D$22,input!E:E,January!B55) -> 0 | E55: =COUNTIFS(input!P:P,January!$D$22,input!F:F,January!C55) -> 0 | F55: =COUNTIFS(input!Q:Q,January!$D$22,input!G:G,January!D55) -> 0 | G55: =COUNTIFS(input!R:R,January!$D$22,input!H:H,January!E55) -> 0 | H55: =COUNTIFS(input!S:S,January!$D$22,input!I:I,January!F55) -> 0 | I55: =COUNTIFS(input!T:T,January!$D$22,input!J:J,January!G55) -> 0 | J55: =COUNTIFS(input!U:U,January!$D$22,input!K:K,January!H55) -> 0 | K55: =COUNTIFS(input!V:V,January!$D$22,input!L:L,January!I55) -> 0 | N55: Steel Yard | Q55: =COUNTIFS(input!$O:$O,January!$Q$45,input!$G:$G,January!N55,input!$A:$A,January!$B$2) -> 0 | R55: =COUNTIFS(input!$O:$O,January!$R$45,input!$G:$G,January!N55,input!$A:$A,January!$B$2) -> 0 | S55: =COUNTIFS(input!$O:$O,January!$S$45,input!$G:$G,January!N55,input!$A:$A,January!$B$2) -> 0 | T55: =COUNTIFS(input!$O:$O,January!$T$45,input!$G:$G,January!N55,input!$A:$A,January!$B$2) -> 1 | U55: =COUNTIFS(input!$O:$O,January!$U$45,input!$G:$G,January!N55,input!$A:$A,January!$B$2) -> 0 | V55: =COUNTIFS(input!$O:$O,January!$V$45,input!$G:$G,January!N55,input!$A:$A,January!$B$2) -> 0 | W55: =COUNTIFS(input!$O:$O,January!$W$45,input!$G:$G,January!N55,input!$A:$A,January!$B$2) -> 0 | X55: =COUNTIFS(input!$O:$O,January!$X$45,input!$G:$G,January!N55,input!$A:$A,January!$B$2) -> 0 | Y55: =SUM(Q55:X55) -> 1 | Z55: {=_xlfn.IFS(Y55=0,0,Y55>=1,Y55/Y$61)} -> 0.076923077
B56: Third | D56: =COUNTIFS(input!$O:$O,January!$D$45,input!$K:$K,January!B56,input!$A:$A,January!$B$2) -> 1 | E56: =COUNTIFS(input!$O:$O,January!$E$45,input!$K:$K,January!B56,input!$A:$A,January!$B$2) -> 0 | F56: =COUNTIFS(input!$O:$O,January!$F$45,input!$K:$K,January!B56,input!$A:$A,January!$B$2) -> 0 | G56: =COUNTIFS(input!$O:$O,January!$G$45,input!$K:$K,January!B56,input!$A:$A,January!$B$2) -> 0 | H56: =COUNTIFS(input!$O:$O,January!$H$45,input!$K:$K,January!B56,input!$A:$A,January!$B$2) -> 0 | I56: =COUNTIFS(input!$O:$O,January!$I$45,input!$K:$K,January!B56,input!$A:$A,January!$B$2) -> 0 | J56: =COUNTIFS(input!$O:$O,January!$J$45,input!$K:$K,January!B56,input!$A:$A,January!$B$2) -> 1 | K56: =COUNTIFS(input!$O:$O,January!$K$45,input!$K:$K,January!B56,input!$A:$A,January!$B$2) -> 1 | L56: =SUM(D56:K60) -> 3 | M56: =_xlfn.IFS(L56=0,0,L56>=1,L56/L61) -> 0.23076923 | N56: Machine Shop | Q56: =COUNTIFS(input!$O:$O,January!$Q$45,input!$G:$G,January!N56,input!$A:$A,January!$B$2) -> 0 | R56: =COUNTIFS(input!$O:$O,January!$R$45,input!$G:$G,January!N56,input!$A:$A,January!$B$2) -> 0 | S56: =COUNTIFS(input!$O:$O,January!$S$45,input!$G:$G,January!N56,input!$A:$A,January!$B$2) -> 0 | T56: =COUNTIFS(input!$O:$O,January!$T$45,input!$G:$G,January!N56,input!$A:$A,January!$B$2) -> 1 | U56: =COUNTIFS(input!$O:$O,January!$U$45,input!$G:$G,January!N56,input!$A:$A,January!$B$2) -> 0 | V56: =COUNTIFS(input!$O:$O,January!$V$45,input!$G:$G,January!N56,input!$A:$A,January!$B$2) -> 0 | W56: =COUNTIFS(input!$O:$O,January!$W$45,input!$G:$G,January!N56,input!$A:$A,January!$B$2) -> 0 | X56: =COUNTIFS(input!$O:$O,January!$X$45,input!$G:$G,January!N56,input!$A:$A,January!$B$2) -> 0 | Y56: =SUM(Q56:X56) -> 1 | Z56: {=_xlfn.IFS(Y56=0,0,Y56>=1,Y56/Y$61)} -> 0.076923077
D57: =COUNTIFS(input!O:O,January!$D$22,input!E:E,January!B57) -> 0 | E57: =COUNTIFS(input!P:P,January!$D$22,input!F:F,January!C57) -> 0 | F57: =COUNTIFS(input!Q:Q,January!$D$22,input!G:G,January!D57) -> 0 | G57: =COUNTIFS(input!R:R,January!$D$22,input!H:H,January!E57) -> 0 | H57: =COUNTIFS(input!S:S,January!$D$22,input!I:I,January!F57) -> 0 | I57: =COUNTIFS(input!T:T,January!$D$22,input!J:J,January!G57) -> 0 | J57: =COUNTIFS(input!U:U,January!$D$22,input!K:K,January!H57) -> 0 | K57: =COUNTIFS(input!V:V,January!$D$22,input!L:L,January!I57) -> 0 | N57: Fuel Storage Area | Q57: =COUNTIFS(input!$O:$O,January!$Q$45,input!$G:$G,January!N57,input!$A:$A,January!$B$2) -> 0 | R57: =COUNTIFS(input!$O:$O,January!$R$45,input!$G:$G,January!N57,input!$A:$A,January!$B$2) -> 1 | S57: =COUNTIFS(input!$O:$O,January!$S$45,input!$G:$G,January!N57,input!$A:$A,January!$B$2) -> 0 | T57: =COUNTIFS(input!$O:$O,January!$T$45,input!$G:$G,January!N57,input!$A:$A,January!$B$2) -> 0 | U57: =COUNTIFS(input!$O:$O,January!$U$45,input!$G:$G,January!N57,input!$A:$A,January!$B$2) -> 0 | V57: =COUNTIFS(input!$O:$O,January!$V$45,input!$G:$G,January!N57,input!$A:$A,January!$B$2) -> 0 | W57: =COUNTIFS(input!$O:$O,January!$W$45,input!$G:$G,January!N57,input!$A:$A,January!$B$2) -> 0 | X57: =COUNTIFS(input!$O:$O,January!$X$45,input!$G:$G,January!N57,input!$A:$A,January!$B$2) -> 0 | Y57: =SUM(Q57:X57) -> 1 | Z57: {=_xlfn.IFS(Y57=0,0,Y57>=1,Y57/Y$61)} -> 0.076923077
D58: =COUNTIFS(input!O:O,January!$D$22,input!E:E,January!B58) -> 0 | E58: =COUNTIFS(input!P:P,January!$D$22,input!F:F,January!C58) -> 0 | F58: =COUNTIFS(input!Q:Q,January!$D$22,input!G:G,January!D58) -> 0 | G58: =COUNTIFS(input!R:R,January!$D$22,input!H:H,January!E58) -> 0 | H58: =COUNTIFS(input!S:S,January!$D$22,input!I:I,January!F58) -> 0 | I58: =COUNTIFS(input!T:T,January!$D$22,input!J:J,January!G58) -> 0 | J58: =COUNTIFS(input!U:U,January!$D$22,input!K:K,January!H58) -> 0 | K58: =COUNTIFS(input!V:V,January!$D$22,input!L:L,January!I58) -> 0 | N58: Buaki, Sapid | Q58: =COUNTIFS(input!$O:$O,January!$Q$45,input!$G:$G,January!N58,input!$A:$A,January!$B$2) -> 0 | R58: =COUNTIFS(input!$O:$O,January!$R$45,input!$G:$G,January!N58,input!$A:$A,January!$B$2) -> 0 | S58: =COUNTIFS(input!$O:$O,January!$S$45,input!$G:$G,January!N58,input!$A:$A,January!$B$2) -> 0 | T58: =COUNTIFS(input!$O:$O,January!$T$45,input!$G:$G,January!N58,input!$A:$A,January!$B$2) -> 0 | U58: =COUNTIFS(input!$O:$O,January!$U$45,input!$G:$G,January!N58,input!$A:$A,January!$B$2) -> 0 | V58: =COUNTIFS(input!$O:$O,January!$V$45,input!$G:$G,January!N58,input!$A:$A,January!$B$2) -> 0 | W58: =COUNTIFS(input!$O:$O,January!$W$45,input!$G:$G,January!N58,input!$A:$A,January!$B$2) -> 0 | X58: =COUNTIFS(input!$O:$O,January!$X$45,input!$G:$G,January!N58,input!$A:$A,January!$B$2) -> 1 | Y58: =SUM(Q58:X58) -> 1 | Z58: {=_xlfn.IFS(Y58=0,0,Y58>=1,Y58/Y$61)} -> 0.076923077
N59: Golf Course, Sapid | Q59: =COUNTIFS(input!$O:$O,January!$Q$45,input!$G:$G,January!N59,input!$A:$A,January!$B$2) -> 0 | R59: =COUNTIFS(input!$O:$O,January!$R$45,input!$G:$G,January!N59,input!$A:$A,January!$B$2) -> 0 | S59: =COUNTIFS(input!$O:$O,January!$S$45,input!$G:$G,January!N59,input!$A:$A,January!$B$2) -> 0 | T59: =COUNTIFS(input!$O:$O,January!$T$45,input!$G:$G,January!N59,input!$A:$A,January!$B$2) -> 0 | U59: =COUNTIFS(input!$O:$O,January!$U$45,input!$G:$G,January!N59,input!$A:$A,January!$B$2) -> 0 | V59: =COUNTIFS(input!$O:$O,January!$V$45,input!$G:$G,January!N59,input!$A:$A,January!$B$2) -> 0 | W59: =COUNTIFS(input!$O:$O,January!$W$45,input!$G:$G,January!N59,input!$A:$A,January!$B$2) -> 0 | X59: =COUNTIFS(input!$O:$O,January!$X$45,input!$G:$G,January!N59,input!$A:$A,January!$B$2) -> 1 | Y59: =SUM(Q59:X59) -> 1 | Z59: {=_xlfn.IFS(Y59=0,0,Y59>=1,Y59/Y$61)} -> 0.076923077
D60: =COUNTIFS(input!O:O,January!$D$22,input!E:E,January!B60) -> 0 | E60: =COUNTIFS(input!P:P,January!$D$22,input!F:F,January!C60) -> 0 | F60: =COUNTIFS(input!Q:Q,January!$D$22,input!G:G,January!D60) -> 0 | G60: =COUNTIFS(input!R:R,January!$D$22,input!H:H,January!E60) -> 0 | H60: =COUNTIFS(input!S:S,January!$D$22,input!I:I,January!F60) -> 0 | I60: =COUNTIFS(input!T:T,January!$D$22,input!J:J,January!G60) -> 0 | J60: =COUNTIFS(input!U:U,January!$D$22,input!K:K,January!H60) -> 0 | K60: =COUNTIFS(input!V:V,January!$D$22,input!L:L,January!I60) -> 0 | N60: Tubo, Sapid | Q60: =COUNTIFS(input!$O:$O,January!$Q$45,input!$G:$G,January!N60,input!$A:$A,January!$B$2) -> 0 | R60: =COUNTIFS(input!$O:$O,January!$R$45,input!$G:$G,January!N60,input!$A:$A,January!$B$2) -> 0 | S60: =COUNTIFS(input!$O:$O,January!$S$45,input!$G:$G,January!N60,input!$A:$A,January!$B$2) -> 0 | T60: =COUNTIFS(input!$O:$O,January!$T$45,input!$G:$G,January!N60,input!$A:$A,January!$B$2) -> 0 | U60: =COUNTIFS(input!$O:$O,January!$U$45,input!$G:$G,January!N60,input!$A:$A,January!$B$2) -> 0 | V60: =COUNTIFS(input!$O:$O,January!$V$45,input!$G:$G,January!N60,input!$A:$A,January!$B$2) -> 0 | W60: =COUNTIFS(input!$O:$O,January!$W$45,input!$G:$G,January!N60,input!$A:$A,January!$B$2) -> 0 | X60: =COUNTIFS(input!$O:$O,January!$X$45,input!$G:$G,January!N60,input!$A:$A,January!$B$2) -> 1 | Y60: =SUM(Q60:X60) -> 1 | Z60: {=_xlfn.IFS(Y60=0,0,Y60>=1,Y60/Y$61)} -> 0.076923077
B61: TOTAL | D61: =SUM(D46:D60) -> 1 | E61: =SUM(E46:E60) -> 1 | F61: =SUM(F46:F60) -> 0 | G61: =SUM(G46:G60) -> 5 | H61: =SUM(H46:H60) -> 0 | I61: =SUM(I46:I60) -> 2 | J61: =SUM(J46:J60) -> 1 | K61: =SUM(K46:K60) -> 3 | ... M61: =SUM(M46:M60) -> 1 | N61: TOTAL | Q61: =SUM(Q46:Q60) -> 1 | R61: =SUM(R46:R60) -> 1 | S61: =SUM(S46:S60) -> 0 | T61: =SUM(T46:T60) -> 5 | U61: =SUM(U46:U60) -> 0 | V61: =SUM(V46:V60) -> 2 | W61: =SUM(W46:W60) -> 1 | X61: =SUM(X46:X60) -> 3 | ... Z61: =SUM(Z46:Z60) -> 1
B62: Spvr. of Injured Individual / Damaged Property | D62: LTA-F | E62: LTA-NF | F62: NLTA | G62: FAC | H62: NM | I62: OI | J62: PD | K62: EI | L62: Total | M62: % Distribution | N62: Group / Dept. / Section or Contractor | Q62: LTA-F | R62: LTA-NF | S62: NLTA | T62: FAC | U62: NM | V62: OI | W62: PD | X62: EI | Y62: Total | Z62: % Distribution
B63: HGA / RPK / SADM | D63: =COUNTIFS(input!$O:$O,January!$D$62,input!$W:$W,January!B63,input!$A:$A,January!$B$2) -> 0 | E63: =COUNTIFS(input!$O:$O,January!$E$62,input!$W:$W,January!B63,input!$A:$A,January!$B$2) -> 0 | F63: =COUNTIFS(input!$O:$O,January!$F$62,input!$W:$W,January!B63,input!$A:$A,January!$B$2) -> 0 | G63: =COUNTIFS(input!$O:$O,January!$G$62,input!$W:$W,January!B63,input!$A:$A,January!$B$2) -> 0 | H63: =COUNTIFS(input!$O:$O,January!$H$62,input!$W:$W,January!B63,input!$A:$A,January!$B$2) -> 0 | I63: =COUNTIFS(input!$O:$O,January!$I$62,input!$W:$W,January!B63,input!$A:$A,January!$B$2) -> 1 | J63: =COUNTIFS(input!$O:$O,January!$J$62,input!$W:$W,January!B63,input!$A:$A,January!$B$2) -> 0 | K63: =COUNTIFS(input!$O:$O,January!$K$62,input!$W:$W,January!B63,input!$A:$A,January!$B$2) -> 0 | L63: =SUM(D63:K63) -> 1 | M63: {=_xlfn.IFS(L63=0,0,L63>=1,L63/L87)} -> 0.076923077 | N63: MOG - 1: Section 1 | Q63: =COUNTIFS(input!$O:$O,January!$Q$62,input!$X:$X,January!N63,input!$A:$A,January!$B$2) -> 0 | R63: =COUNTIFS(input!$O:$O,January!$R$62,input!$X:$X,January!N63,input!$A:$A,January!$B$2) -> 0 | S63: =COUNTIFS(input!$O:$O,January!$S$62,input!$X:$X,January!N63,input!$A:$A,January!$B$2) -> 0 | T63: =COUNTIFS(input!$O:$O,January!$T$62,input!$X:$X,January!N63,input!$A:$A,January!$B$2) -> 0 | U63: =COUNTIFS(input!$O:$O,January!$U$62,input!$X:$X,January!N63,input!$A:$A,January!$B$2) -> 0 | V63: =COUNTIFS(input!$O:$O,January!$V$62,input!$X:$X,January!N63,input!$A:$A,January!$B$2) -> 0 | W63: =COUNTIFS(input!$O:$O,January!$W$62,input!$X:$X,January!N63,input!$A:$A,January!$B$2) -> 0 | X63: =COUNTIFS(input!$O:$O,January!$X$62,input!$X:$X,January!N63,input!$A:$A,January!$B$2) -> 0 | Y63: =SUM(Q63:X63) -> 0 | Z63: {=_xlfn.IFS(Y63=0,0,Y63>=1,Y63/Y$87)} -> 0
B64: HGA / ABL / DJFOE | D64: =COUNTIFS(input!$O:$O,January!$D$62,input!$W:$W,January!B64,input!$A:$A,January!$B$2) -> 0 | E64: =COUNTIFS(input!$O:$O,January!$E$62,input!$W:$W,January!B64,input!$A:$A,January!$B$2) -> 0 | F64: =COUNTIFS(input!$O:$O,January!$F$62,input!$W:$W,January!B64,input!$A:$A,January!$B$2) -> 0 | G64: =COUNTIFS(input!$O:$O,January!$G$62,input!$W:$W,January!B64,input!$A:$A,January!$B$2) -> 1 | H64: =COUNTIFS(input!$O:$O,January!$H$62,input!$W:$W,January!B64,input!$A:$A,January!$B$2) -> 0 | I64: =COUNTIFS(input!$O:$O,January!$I$62,input!$W:$W,January!B64,input!$A:$A,January!$B$2) -> 0 | J64: =COUNTIFS(input!$O:$O,January!$J$62,input!$W:$W,January!B64,input!$A:$A,January!$B$2) -> 0 | K64: =COUNTIFS(input!$O:$O,January!$K$62,input!$W:$W,January!B64,input!$A:$A,January!$B$2) -> 0 | L64: =SUM(D64:K64) -> 1 | M64: {=_xlfn.IFS(L64=0,0,L64>=1,L64/L87)} -> 0.076923077 | N64: MOG - 1: Section 2 | Q64: =COUNTIFS(input!$O:$O,January!$Q$62,input!$X:$X,January!N64,input!$A:$A,January!$B$2) -> 0 | R64: =COUNTIFS(input!$O:$O,January!$R$62,input!$X:$X,January!N64,input!$A:$A,January!$B$2) -> 0 | S64: =COUNTIFS(input!$O:$O,January!$S$62,input!$X:$X,January!N64,input!$A:$A,January!$B$2) -> 0 | T64: =COUNTIFS(input!$O:$O,January!$T$62,input!$X:$X,January!N64,input!$A:$A,January!$B$2) -> 1 | U64: =COUNTIFS(input!$O:$O,January!$U$62,input!$X:$X,January!N64,input!$A:$A,January!$B$2) -> 0 | V64: =COUNTIFS(input!$O:$O,January!$V$62,input!$X:$X,January!N64,input!$A:$A,January!$B$2) -> 0 | W64: =COUNTIFS(input!$O:$O,January!$W$62,input!$X:$X,January!N64,input!$A:$A,January!$B$2) -> 0 | X64: =COUNTIFS(input!$O:$O,January!$X$62,input!$X:$X,January!N64,input!$A:$A,January!$B$2) -> 0 | Y64: =SUM(Q64:X64) -> 1 | Z64: {=_xlfn.IFS(Y64=0,0,Y64>=1,Y64/Y$87)} -> 0.076923077
B65: VAB / MTA / LKF | D65: =COUNTIFS(input!$O:$O,January!$D$62,input!$W:$W,January!B65,input!$A:$A,January!$B$2) -> 0 | E65: =COUNTIFS(input!$O:$O,January!$E$62,input!$W:$W,January!B65,input!$A:$A,January!$B$2) -> 0 | F65: =COUNTIFS(input!$O:$O,January!$F$62,input!$W:$W,January!B65,input!$A:$A,January!$B$2) -> 0 | G65: =COUNTIFS(input!$O:$O,January!$G$62,input!$W:$W,January!B65,input!$A:$A,January!$B$2) -> 1 | H65: =COUNTIFS(input!$O:$O,January!$H$62,input!$W:$W,January!B65,input!$A:$A,January!$B$2) -> 0 | I65: =COUNTIFS(input!$O:$O,January!$I$62,input!$W:$W,January!B65,input!$A:$A,January!$B$2) -> 0 | J65: =COUNTIFS(input!$O:$O,January!$J$62,input!$W:$W,January!B65,input!$A:$A,January!$B$2) -> 0 | K65: =COUNTIFS(input!$O:$O,January!$K$62,input!$W:$W,January!B65,input!$A:$A,January!$B$2) -> 0 | L65: =SUM(D65:K65) -> 1 | M65: {=_xlfn.IFS(L65=0,0,L65>=1,L65/L87)} -> 0.076923077 | N65: MOG - 1: Section 3 | Q65: =COUNTIFS(input!$O:$O,January!$Q$62,input!$X:$X,January!N65,input!$A:$A,January!$B$2) -> 1 | R65: =COUNTIFS(input!$O:$O,January!$R$62,input!$X:$X,January!N65,input!$A:$A,January!$B$2) -> 0 | S65: =COUNTIFS(input!$O:$O,January!$S$62,input!$X:$X,January!N65,input!$A:$A,January!$B$2) -> 0 | T65: =COUNTIFS(input!$O:$O,January!$T$62,input!$X:$X,January!N65,input!$A:$A,January!$B$2) -> 0 | U65: =COUNTIFS(input!$O:$O,January!$U$62,input!$X:$X,January!N65,input!$A:$A,January!$B$2) -> 0 | V65: =COUNTIFS(input!$O:$O,January!$V$62,input!$X:$X,January!N65,input!$A:$A,January!$B$2) -> 0 | W65: =COUNTIFS(input!$O:$O,January!$W$62,input!$X:$X,January!N65,input!$A:$A,January!$B$2) -> 0 | X65: =COUNTIFS(input!$O:$O,January!$X$62,input!$X:$X,January!N65,input!$A:$A,January!$B$2) -> 0 | Y65: =SUM(Q65:X65) -> 1 | Z65: {=_xlfn.IFS(Y65=0,0,Y65>=1,Y65/Y$87)} -> 0.076923077
B66: VAB / JOG / DMG | D66: =COUNTIFS(input!$O:$O,January!$D$62,input!$W:$W,January!B66,input!$A:$A,January!$B$2) -> 1 | E66: =COUNTIFS(input!$O:$O,January!$E$62,input!$W:$W,January!B66,input!$A:$A,January!$B$2) -> 0 | F66: =COUNTIFS(input!$O:$O,January!$F$62,input!$W:$W,January!B66,input!$A:$A,January!$B$2) -> 0 | G66: =COUNTIFS(input!$O:$O,January!$G$62,input!$W:$W,January!B66,input!$A:$A,January!$B$2) -> 0 | H66: =COUNTIFS(input!$O:$O,January!$H$62,input!$W:$W,January!B66,input!$A:$A,January!$B$2) -> 0 | I66: =COUNTIFS(input!$O:$O,January!$I$62,input!$W:$W,January!B66,input!$A:$A,January!$B$2) -> 0 | J66: =COUNTIFS(input!$O:$O,January!$J$62,input!$W:$W,January!B66,input!$A:$A,January!$B$2) -> 0 | K66: =COUNTIFS(input!$O:$O,January!$K$62,input!$W:$W,January!B66,input!$A:$A,January!$B$2) -> 0 | L66: =SUM(D66:K66) -> 1 | M66: {=_xlfn.IFS(L66=0,0,L66>=1,L66/L87)} -> 0.076923077 | N66: MOG - 2: Section 4 | Q66: =COUNTIFS(input!$O:$O,January!$Q$62,input!$X:$X,January!N66,input!$A:$A,January!$B$2) -> 0 | R66: =COUNTIFS(input!$O:$O,January!$R$62,input!$X:$X,January!N66,input!$A:$A,January!$B$2) -> 0 | S66: =COUNTIFS(input!$O:$O,January!$S$62,input!$X:$X,January!N66,input!$A:$A,January!$B$2) -> 0 | T66: =COUNTIFS(input!$O:$O,January!$T$62,input!$X:$X,January!N66,input!$A:$A,January!$B$2) -> 1 | U66: =COUNTIFS(input!$O:$O,January!$U$62,input!$X:$X,January!N66,input!$A:$A,January!$B$2) -> 0 | V66: =COUNTIFS(input!$O:$O,January!$V$62,input!$X:$X,January!N66,input!$A:$A,January!$B$2) -> 0 | W66: =COUNTIFS(input!$O:$O,January!$W$62,input!$X:$X,January!N66,input!$A:$A,January!$B$2) -> 0 | X66: =COUNTIFS(input!$O:$O,January!$X$62,input!$X:$X,January!N66,input!$A:$A,January!$B$2) -> 0 | Y66: =SUM(Q66:X66) -> 1 | Z66: {=_xlfn.IFS(Y66=0,0,Y66>=1,Y66/Y$87)} -> 0.076923077
B67: FABJr. / ABY / JPMR | D67: =COUNTIFS(input!$O:$O,January!$D$62,input!$W:$W,January!B67,input!$A:$A,January!$B$2) -> 0 | E67: =COUNTIFS(input!$O:$O,January!$E$62,input!$W:$W,January!B67,input!$A:$A,January!$B$2) -> 0 | F67: =COUNTIFS(input!$O:$O,January!$F$62,input!$W:$W,January!B67,input!$A:$A,January!$B$2) -> 0 | G67: =COUNTIFS(input!$O:$O,January!$G$62,input!$W:$W,January!B67,input!$A:$A,January!$B$2) -> 0 | H67: =COUNTIFS(input!$O:$O,January!$H$62,input!$W:$W,January!B67,input!$A:$A,January!$B$2) -> 0 | I67: =COUNTIFS(input!$O:$O,January!$I$62,input!$W:$W,January!B67,input!$A:$A,January!$B$2) -> 1 | J67: =COUNTIFS(input!$O:$O,January!$J$62,input!$W:$W,January!B67,input!$A:$A,January!$B$2) -> 0 | K67: =COUNTIFS(input!$O:$O,January!$K$62,input!$W:$W,January!B67,input!$A:$A,January!$B$2) -> 0 | L67: =SUM(D67:K67) -> 1 | M67: {=_xlfn.IFS(L67=0,0,L67>=1,L67/L87)} -> 0.076923077 | N67: MOG - 2: Section 5 | Q67: =COUNTIFS(input!$O:$O,January!$Q$62,input!$X:$X,January!N67,input!$A:$A,January!$B$2) -> 0 | R67: =COUNTIFS(input!$O:$O,January!$R$62,input!$X:$X,January!N67,input!$A:$A,January!$B$2) -> 0 | S67: =COUNTIFS(input!$O:$O,January!$S$62,input!$X:$X,January!N67,input!$A:$A,January!$B$2) -> 0 | T67: =COUNTIFS(input!$O:$O,January!$T$62,input!$X:$X,January!N67,input!$A:$A,January!$B$2) -> 0 | U67: =COUNTIFS(input!$O:$O,January!$U$62,input!$X:$X,January!N67,input!$A:$A,January!$B$2) -> 0 | V67: =COUNTIFS(input!$O:$O,January!$V$62,input!$X:$X,January!N67,input!$A:$A,January!$B$2) -> 0 | W67: =COUNTIFS(input!$O:$O,January!$W$62,input!$X:$X,January!N67,input!$A:$A,January!$B$2) -> 0 | X67: =COUNTIFS(input!$O:$O,January!$X$62,input!$X:$X,January!N67,input!$A:$A,January!$B$2) -> 0 | Y67: =SUM(Q67:X67) -> 0 | Z67: {=_xlfn.IFS(Y67=0,0,Y67>=1,Y67/Y$87)} -> 0
B68: FABJr. / NMFP / PBL | D68: =COUNTIFS(input!$O:$O,January!$D$62,input!$W:$W,January!B68,input!$A:$A,January!$B$2) -> 0 | E68: =COUNTIFS(input!$O:$O,January!$E$62,input!$W:$W,January!B68,input!$A:$A,January!$B$2) -> 0 | F68: =COUNTIFS(input!$O:$O,January!$F$62,input!$W:$W,January!B68,input!$A:$A,January!$B$2) -> 0 | G68: =COUNTIFS(input!$O:$O,January!$G$62,input!$W:$W,January!B68,input!$A:$A,January!$B$2) -> 0 | H68: =COUNTIFS(input!$O:$O,January!$H$62,input!$W:$W,January!B68,input!$A:$A,January!$B$2) -> 0 | I68: =COUNTIFS(input!$O:$O,January!$I$62,input!$W:$W,January!B68,input!$A:$A,January!$B$2) -> 0 | J68: =COUNTIFS(input!$O:$O,January!$J$62,input!$W:$W,January!B68,input!$A:$A,January!$B$2) -> 1 | K68: =COUNTIFS(input!$O:$O,January!$K$62,input!$W:$W,January!B68,input!$A:$A,January!$B$2) -> 0 | L68: =SUM(D68:K68) -> 1 | M68: {=_xlfn.IFS(L68=0,0,L68>=1,L68/L87)} -> 0.076923077 | N68: MOG - 2: Section 6 | Q68: =COUNTIFS(input!$O:$O,January!$Q$62,input!$X:$X,January!N68,input!$A:$A,January!$B$2) -> 0 | R68: =COUNTIFS(input!$O:$O,January!$R$62,input!$X:$X,January!N68,input!$A:$A,January!$B$2) -> 0 | S68: =COUNTIFS(input!$O:$O,January!$S$62,input!$X:$X,January!N68,input!$A:$A,January!$B$2) -> 0 | T68: =COUNTIFS(input!$O:$O,January!$T$62,input!$X:$X,January!N68,input!$A:$A,January!$B$2) -> 0 | U68: =COUNTIFS(input!$O:$O,January!$U$62,input!$X:$X,January!N68,input!$A:$A,January!$B$2) -> 0 | V68: =COUNTIFS(input!$O:$O,January!$V$62,input!$X:$X,January!N68,input!$A:$A,January!$B$2) -> 1 | W68: =COUNTIFS(input!$O:$O,January!$W$62,input!$X:$X,January!N68,input!$A:$A,January!$B$2) -> 0 | X68: =COUNTIFS(input!$O:$O,January!$X$62,input!$X:$X,January!N68,input!$A:$A,January!$B$2) -> 0 | Y68: =SUM(Q68:X68) -> 1 | Z68: {=_xlfn.IFS(Y68=0,0,Y68>=1,Y68/Y$87)} -> 0.076923077
B69: FMWM / SAF / MBC | D69: =COUNTIFS(input!$O:$O,January!$D$62,input!$W:$W,January!B69,input!$A:$A,January!$B$2) -> 0 | E69: =COUNTIFS(input!$O:$O,January!$E$62,input!$W:$W,January!B69,input!$A:$A,January!$B$2) -> 1 | F69: =COUNTIFS(input!$O:$O,January!$F$62,input!$W:$W,January!B69,input!$A:$A,January!$B$2) -> 0 | G69: =COUNTIFS(input!$O:$O,January!$G$62,input!$W:$W,January!B69,input!$A:$A,January!$B$2) -> 0 | H69: =COUNTIFS(input!$O:$O,January!$H$62,input!$W:$W,January!B69,input!$A:$A,January!$B$2) -> 0 | I69: =COUNTIFS(input!$O:$O,January!$I$62,input!$W:$W,January!B69,input!$A:$A,January!$B$2) -> 0 | J69: =COUNTIFS(input!$O:$O,January!$J$62,input!$W:$W,January!B69,input!$A:$A,January!$B$2) -> 0 | K69: =COUNTIFS(input!$O:$O,January!$K$62,input!$W:$W,January!B69,input!$A:$A,January!$B$2) -> 0 | L69: =SUM(D69:K69) -> 1 | M69: {=_xlfn.IFS(L69=0,0,L69>=1,L69/L87)} -> 0.076923077 | N69: MOG - MMME - Mobile | Q69: =COUNTIFS(input!$O:$O,January!$Q$62,input!$X:$X,January!N69,input!$A:$A,January!$B$2) -> 0 | R69: =COUNTIFS(input!$O:$O,January!$R$62,input!$X:$X,January!N69,input!$A:$A,January!$B$2) -> 0 | S69: =COUNTIFS(input!$O:$O,January!$S$62,input!$X:$X,January!N69,input!$A:$A,January!$B$2) -> 0 | T69: =COUNTIFS(input!$O:$O,January!$T$62,input!$X:$X,January!N69,input!$A:$A,January!$B$2) -> 0 | U69: =COUNTIFS(input!$O:$O,January!$U$62,input!$X:$X,January!N69,input!$A:$A,January!$B$2) -> 0 | V69: =COUNTIFS(input!$O:$O,January!$V$62,input!$X:$X,January!N69,input!$A:$A,January!$B$2) -> 1 | W69: =COUNTIFS(input!$O:$O,January!$W$62,input!$X:$X,January!N69,input!$A:$A,January!$B$2) -> 0 | X69: =COUNTIFS(input!$O:$O,January!$X$62,input!$X:$X,January!N69,input!$A:$A,January!$B$2) -> 0 | Y69: =SUM(Q69:X69) -> 1 | Z69: {=_xlfn.IFS(Y69=0,0,Y69>=1,Y69/Y$87)} -> 0.076923077
